Workbook

Sheet 情報入力
A1: 情報入力
A3: 基本情報
A4: 大項目 | B4: 項目名 | C4: 入力値 | D4: 補足
A5: 基本情報 | B5: プラン作成日
B6: ご家庭名
B7: 担当者名
B8: ご主人様のお名前
B9: 奥様のお名前
B10: ご主人様の生年月日
B11: 奥様の生年月日
B12: お住まいの都道府県
B13: 住まい区分 | D13: 持ち家 / 賃貸
A15: 家族情報
A16: 大項目 | B16: 項目名 | C16: 入力値 | D16: 補足
A17: 家族情報 | B17: お子さま人数 | D17: 0〜3人
B18: お子さま1 お名前
B19: お子さま1 生年月日
B20: お子さま2 お名前
B21: お子さま2 生年月日
B22: お子さま3 お名前
B23: お子さま3 生年月日
A24: 収入情報
A25: 大項目 | B25: 項目名 | C25: 入力値 | D25: 補足
A26: 収入情報 | B26: ご主人様の働き方
B27: 奥様の働き方
B28: ご主人様の毎月手取り収入 | D28: 円
B29: 奥様の毎月手取り収入 | D29: 円
B30: 賞与の有無 | D30: あり / なし
B31: ご主人様の年間賞与手取り | D31: 円
B32: 奥様の年間賞与手取り | D32: 円
B33: 児童手当（月額） | D33: 未入力なら平均額を自動反映
B34: その他の定期収入（月額） | D34: 未入力なら0円
B35: ご主人様の退職金見込額 | D35: 未入力なら0円
B36: 奥様の退職金見込額 | D36: 未入力なら0円
A38: 支出情報（主要）
A39: 大項目 | B39: 項目名 | C39: 入力値 | D39: 補足
A40: 支出情報（月額） | B40: 毎月の食費 | D40: 円
B41: 毎月の日用品費 | D41: 円
B42: 毎月の水道・光熱費 | D42: 円
B43: 毎月の通信費 | D43: 円
B44: 毎月の住居費 | D44: 円
B45: 毎月の管理費・修繕積立金 | D45: 円
B46: 住宅ローンに団信はついているか | D46: あり / なし
B47: 毎月の習い事費 | D47: 円
B48: 毎月の生命保険料 | D48: 円
B49: 毎月の医療保険料 | D49: 円
B50: 毎月の車関連費 | D50: 円
B51: 毎月のその他固定費 | D51: 円
A53: 特別支出
A54: 大項目 | B54: 項目名 | C54: 入力値 | D54: 補足
A55: 特別支出（年額） | B55: 年間の旅行費 | D55: 円
B56: 年間の帰省費 | D56: 円
B57: 年間の冠婚葬祭費 | D57: 円
B58: 年間の家電買替費 | D58: 円
B59: 年間の固定資産税 | D59: 円
A61: 資産形成情報
A62: 大項目 | B62: 項目名 | C62: 入力値 | D62: 補足
A63: 資産形成情報 | B63: 毎月のNISA積立額 | D63: 円
B64: 毎月のiDeCo積立額 | D64: 円
B65: 毎月の特定口座積立額 | D65: 円
B66: 毎月の変額保険・積立保険額 | D66: 円
B67: 毎月のその他投資積立額 | D67: 円
A69: 資産・負債情報
A70: 大項目 | B70: 項目名 | C70: 入力値 | D70: 補足
A71: 資産・負債情報 | B71: 今ある預貯金（普通預金） | D71: 円
B72: 今ある預貯金（定期預金） | D72: 円
B73: 今ある投資残高（積立投資） | D73: 円
B74: 今ある投資残高（NISA） | D74: 円
B75: 今ある投資残高（iDeCo） | D75: 円
B76: 今ある返戻金見込（学資保険など） | D76: 円
B77: 住宅ローン残高（参考） | D77: 円・参考
A79: 老後・希望条件
A80: 大項目 | B80: 項目名 | C80: 入力値 | D80: 補足
B81: ご主人様が仕事を終える想定年齢 | D81: 歳
B82: 奥様が仕事を終える想定年齢 | D82: 歳
B83: 老後生活として見始める年齢 | D83: 歳
B84: 老後に希望する生活費（月額） | D84: 円
B85: 老後に最低限みておきたい生活費（月額） | D85: 円
B86: 老後のゆとり費も見込むか | D86: あり / なし
B87: 将来のリフォーム費を見込むか | D87: あり / なし
B88: 将来の車買替費を見込むか | D88: あり / なし
B89: 相続・贈与の見込みを反映するか | D89: あり / なし
A92: 加入中の保険一覧
A93: 保険の種類 | B93: 契約者 | D93: 保険会社 | E93: 保険始期 | F93: 保険終期 | G93: 受取人 | H93: 月額保険料
A104: お子さま別の進路予定
A105: お子さま名 | B105: 幼稚園・保育園 | C105: 小学校 | D105: 中学校 | E105: 高校 | F105: 大学 | G105: 大学の通学形態

Sheet 前提条件
A1: 前提条件
A3: 昇給率
A4: 大項目 | B4: 項目名 | C4: 入力値 | D4: 補足
A5: 昇給率 | B5: ご主人様収入上昇率 | C5: 0
A6: 昇給率 | B6: 奥様収入上昇率 | C6: 0
A7: 昇給率 | B7: 賞与上昇率 | C7: 0
A8: 昇給率 | B8: 児童手当終了年齢 | C8: 18
A10: 物価上昇率
A11: 大項目 | B11: 項目名 | C11: 入力値 | D11: 補足
A12: 物価上昇率 | B12: 基本生活費上昇率 | C12: 0
A13: 物価上昇率 | B13: 教育費上昇率 | C13: 0
A14: 物価上昇率 | B14: 老後生活費上昇率 | C14: 0
A15: 物価上昇率 | B15: 住宅費上昇率 | C15: 0
A16: 物価上昇率 | B16: 老後インフレ率① | C16: 0
A17: 物価上昇率 | B17: 老後インフレ率② | C17: 0
A19: 教育費単価マスタ
A20: 大項目 | B20: 項目名 | C20: 入力値 | D20: 補足
A21: 教育費単価マスタ | B21: 幼稚園公立年額 | C21: 300000
A22: 教育費単価マスタ | B22: 幼稚園私立年額 | C22: 700000
A23: 教育費単価マスタ | B23: 小学校公立年額 | C23: 400000
A24: 教育費単価マスタ | B24: 小学校私立年額 | C24: 1800000
A25: 教育費単価マスタ | B25: 中学校公立年額 | C25: 550000
A26: 教育費単価マスタ | B26: 中学校私立年額 | C26: 1600000
A27: 教育費単価マスタ | B27: 高校公立年額 | C27: 600000
A28: 教育費単価マスタ | B28: 高校私立年額 | C28: 1200000
A29: 教育費単価マスタ | B29: 大学国公立年額 | C29: 1400000
A30: 教育費単価マスタ | B30: 大学私立文系年額 | C30: 2200000
A31: 教育費単価マスタ | B31: 大学私立理系年額 | C31: 2800000
A32: 教育費単価マスタ | B32: 下宿加算年額 | C32: 1200000
A33: 教育費単価マスタ | B33: 大学入学一時金 | C33: 300000
A35: 年金前提
A36: 大項目 | B36: 項目名 | C36: 入力値 | D36: 補足
A37: 年金前提 | B37: ご主人様年金開始年齢 | C37: 65
A38: 年金前提 | B38: 奥様年金開始年齢 | C38: 65
A39: 年金前提 | B39: ご主人様年金月額 | C39: =IFERROR(ROUND(((IF(入力データ!$C$29="",0,入力データ!$C$29)*12)+IF(入力データ!$C$31="あり",IF(入力データ!$C$32="",0,入力データ!$C$32),0))*0.2/12,0),0) | D39: 現在年収の20%を月額換算
A40: 年金前提 | B40: 奥様年金月額 | C40: =IFERROR(ROUND(((IF(入力データ!$C$30="",0,入力データ!$C$30)*12)+IF(入力データ!$C$31="あり",IF(入力データ!$C$33="",0,入力データ!$C$33),0))*0.2/12,0),0) | D40: 現在年収の20%を月額換算
A42: 住宅前提
A43: 大項目 | B43: 項目名 | C43: 入力値 | D43: 補足
A44: 住宅前提 | B44: 住宅ローン完済年齢 | C44: 60
A45: 住宅前提 | B45: 住宅ローン金利 | C45: 0.012
A46: 住宅前提 | B46: 繰上返済予定有無 | C46: なし
A47: 住宅前提 | B47: 持ち家修繕費年額 | C47: 150000
A48: 住宅前提 | B48: 賃貸更新料年額 | C48: 0
A50: リスク判定前提
A51: 大項目 | B51: 項目名 | C51: 入力値 | D51: 補足
A52: リスク判定前提 | B52: 死亡時生活費圧縮率 | C52: 0.8
A53: リスク判定前提 | B53: 就業不能収入減少率ご主人様 | C53: 1
A54: リスク判定前提 | B54: 就業不能収入減少率奥様 | C54: 1
A55: リスク判定前提 | B55: 就業不能公的保障月額ご主人様 | C55: 0
A56: リスク判定前提 | B56: 就業不能公的保障月額奥様 | C56: 0
A57: リスク判定前提 | B57: 遺族年金月額（ご主人様死亡時） | C57: 120000
A58: リスク判定前提 | B58: 遺族年金月額（奥様死亡時） | C58: 0
A59: リスク判定前提 | B59: 老後試算終了年齢 | C59: 100
A60: リスク判定前提 | B60: 投資想定利回り | C60: 0
A61: リスク判定前提 | B61: 解約返戻金増加率 | C61: 0

Sheet CF表（万円表示）
A1: CF表（万円表示）
A2: 試算終了年 | B2: =CF表!B2
A3: 年 | B3: =IF(CF表!B3="","",CF表!B3) | C3: =IF(CF表!C3="","",CF表!C3) | D3: =IF(CF表!D3="","",CF表!D3) | E3: =IF(CF表!E3="","",CF表!E3) | F3: =IF(CF表!F3="","",CF表!F3) | G3: =IF(CF表!G3="","",CF表!G3) | H3: =IF(CF表!H3="","",CF表!H3) | I3: =IF(CF表!I3="","",CF表!I3) | ... CW3: =IF(CF表!CW3="","",CF表!CW3)
A4: ご主人様年齢 | B4: =IF(CF表!B4="","",CF表!B4) | C4: =IF(CF表!C4="","",CF表!C4) | D4: =IF(CF表!D4="","",CF表!D4) | E4: =IF(CF表!E4="","",CF表!E4) | F4: =IF(CF表!F4="","",CF表!F4) | G4: =IF(CF表!G4="","",CF表!G4) | H4: =IF(CF表!H4="","",CF表!H4) | I4: =IF(CF表!I4="","",CF表!I4) | ... CW4: =IF(CF表!CW4="","",CF表!CW4)
A5: 奥様年齢 | B5: =IF(CF表!B5="","",CF表!B5) | C5: =IF(CF表!C5="","",CF表!C5) | D5: =IF(CF表!D5="","",CF表!D5) | E5: =IF(CF表!E5="","",CF表!E5) | F5: =IF(CF表!F5="","",CF表!F5) | G5: =IF(CF表!G5="","",CF表!G5) | H5: =IF(CF表!H5="","",CF表!H5) | I5: =IF(CF表!I5="","",CF表!I5) | ... CW5: =IF(CF表!CW5="","",CF表!CW5)
A6: 子1年齢 | B6: =IF(CF表!B6="","",CF表!B6) | C6: =IF(CF表!C6="","",CF表!C6) | D6: =IF(CF表!D6="","",CF表!D6) | E6: =IF(CF表!E6="","",CF表!E6) | F6: =IF(CF表!F6="","",CF表!F6) | G6: =IF(CF表!G6="","",CF表!G6) | H6: =IF(CF表!H6="","",CF表!H6) | I6: =IF(CF表!I6="","",CF表!I6) | ... CW6: =IF(CF表!CW6="","",CF表!CW6)
A7: 子2年齢 | B7: =IF(CF表!B7="","",CF表!B7) | C7: =IF(CF表!C7="","",CF表!C7) | D7: =IF(CF表!D7="","",CF表!D7) | E7: =IF(CF表!E7="","",CF表!E7) | F7: =IF(CF表!F7="","",CF表!F7) | G7: =IF(CF表!G7="","",CF表!G7) | H7: =IF(CF表!H7="","",CF表!H7) | I7: =IF(CF表!I7="","",CF表!I7) | ... CW7: =IF(CF表!CW7="","",CF表!CW7)
A8: 子3年齢 | B8: =IF(CF表!B8="","",CF表!B8) | C8: =IF(CF表!C8="","",CF表!C8) | D8: =IF(CF表!D8="","",CF表!D8) | E8: =IF(CF表!E8="","",CF表!E8) | F8: =IF(CF表!F8="","",CF表!F8) | G8: =IF(CF表!G8="","",CF表!G8) | H8: =IF(CF表!H8="","",CF表!H8) | I8: =IF(CF表!I8="","",CF表!I8) | ... CW8: =IF(CF表!CW8="","",CF表!CW8)
A9: 家族年齢
A10: ご主人様収入 | B10: =IF(CF表!B$3="","",CF表!B10/10000) | C10: =IF(CF表!C$3="","",CF表!C10/10000) | D10: =IF(CF表!D$3="","",CF表!D10/10000) | E10: =IF(CF表!E$3="","",CF表!E10/10000) | F10: =IF(CF表!F$3="","",CF表!F10/10000) | G10: =IF(CF表!G$3="","",CF表!G10/10000) | H10: =IF(CF表!H$3="","",CF表!H10/10000) | I10: =IF(CF表!I$3="","",CF表!I10/10000) | ... CW10: =IF(CF表!CW$3="","",CF表!CW10/10000)
A11: 奥様収入 | B11: =IF(CF表!B$3="","",CF表!B11/10000) | C11: =IF(CF表!C$3="","",CF表!C11/10000) | D11: =IF(CF表!D$3="","",CF表!D11/10000) | E11: =IF(CF表!E$3="","",CF表!E11/10000) | F11: =IF(CF表!F$3="","",CF表!F11/10000) | G11: =IF(CF表!G$3="","",CF表!G11/10000) | H11: =IF(CF表!H$3="","",CF表!H11/10000) | I11: =IF(CF表!I$3="","",CF表!I11/10000) | ... CW11: =IF(CF表!CW$3="","",CF表!CW11/10000)
A12: 児童手当 | B12: =IF(CF表!B$3="","",CF表!B12/10000) | C12: =IF(CF表!C$3="","",CF表!C12/10000) | D12: =IF(CF表!D$3="","",CF表!D12/10000) | E12: =IF(CF表!E$3="","",CF表!E12/10000) | F12: =IF(CF表!F$3="","",CF表!F12/10000) | G12: =IF(CF表!G$3="","",CF表!G12/10000) | H12: =IF(CF表!H$3="","",CF表!H12/10000) | I12: =IF(CF表!I$3="","",CF表!I12/10000) | ... CW12: =IF(CF表!CW$3="","",CF表!CW12/10000)
A13: その他収入 | B13: =IF(CF表!B$3="","",CF表!B13/10000) | C13: =IF(CF表!C$3="","",CF表!C13/10000) | D13: =IF(CF表!D$3="","",CF表!D13/10000) | E13: =IF(CF表!E$3="","",CF表!E13/10000) | F13: =IF(CF表!F$3="","",CF表!F13/10000) | G13: =IF(CF表!G$3="","",CF表!G13/10000) | H13: =IF(CF表!H$3="","",CF表!H13/10000) | I13: =IF(CF表!I$3="","",CF表!I13/10000) | ... CW13: =IF(CF表!CW$3="","",CF表!CW13/10000)
A14: ご主人様退職金 | B14: =IF(CF表!B$3="","",CF表!B14/10000) | C14: =IF(CF表!C$3="","",CF表!C14/10000) | D14: =IF(CF表!D$3="","",CF表!D14/10000) | E14: =IF(CF表!E$3="","",CF表!E14/10000) | F14: =IF(CF表!F$3="","",CF表!F14/10000) | G14: =IF(CF表!G$3="","",CF表!G14/10000) | H14: =IF(CF表!H$3="","",CF表!H14/10000) | I14: =IF(CF表!I$3="","",CF表!I14/10000) | ... CW14: =IF(CF表!CW$3="","",CF表!CW14/10000)
A15: 奥様退職金 | B15: =IF(CF表!B$3="","",CF表!B15/10000) | C15: =IF(CF表!C$3="","",CF表!C15/10000) | D15: =IF(CF表!D$3="","",CF表!D15/10000) | E15: =IF(CF表!E$3="","",CF表!E15/10000) | F15: =IF(CF表!F$3="","",CF表!F15/10000) | G15: =IF(CF表!G$3="","",CF表!G15/10000) | H15: =IF(CF表!H$3="","",CF表!H15/10000) | I15: =IF(CF表!I$3="","",CF表!I15/10000) | ... CW15: =IF(CF表!CW$3="","",CF表!CW15/10000)
A16: ご主人様年金収入 | B16: =IF(CF表!B$3="","",CF表!B16/10000) | C16: =IF(CF表!C$3="","",CF表!C16/10000) | D16: =IF(CF表!D$3="","",CF表!D16/10000) | E16: =IF(CF表!E$3="","",CF表!E16/10000) | F16: =IF(CF表!F$3="","",CF表!F16/10000) | G16: =IF(CF表!G$3="","",CF表!G16/10000) | H16: =IF(CF表!H$3="","",CF表!H16/10000) | I16: =IF(CF表!I$3="","",CF表!I16/10000) | ... CW16: =IF(CF表!CW$3="","",CF表!CW16/10000)
A17: 奥様年金収入 | B17: =IF(CF表!B$3="","",CF表!B17/10000) | C17: =IF(CF表!C$3="","",CF表!C17/10000) | D17: =IF(CF表!D$3="","",CF表!D17/10000) | E17: =IF(CF表!E$3="","",CF表!E17/10000) | F17: =IF(CF表!F$3="","",CF表!F17/10000) | G17: =IF(CF表!G$3="","",CF表!G17/10000) | H17: =IF(CF表!H$3="","",CF表!H17/10000) | I17: =IF(CF表!I$3="","",CF表!I17/10000) | ... CW17: =IF(CF表!CW$3="","",CF表!CW17/10000)
A18: 世帯収入合計 | B18: =IF(CF表!B$3="","",CF表!B18/10000) | C18: =IF(CF表!C$3="","",CF表!C18/10000) | D18: =IF(CF表!D$3="","",CF表!D18/10000) | E18: =IF(CF表!E$3="","",CF表!E18/10000) | F18: =IF(CF表!F$3="","",CF表!F18/10000) | G18: =IF(CF表!G$3="","",CF表!G18/10000) | H18: =IF(CF表!H$3="","",CF表!H18/10000) | I18: =IF(CF表!I$3="","",CF表!I18/10000) | ... CW18: =IF(CF表!CW$3="","",CF表!CW18/10000)
A19: 収入
A20: 基本生活費 | B20: =IF(CF表!B$3="","",CF表!B20/10000) | C20: =IF(CF表!C$3="","",CF表!C20/10000) | D20: =IF(CF表!D$3="","",CF表!D20/10000) | E20: =IF(CF表!E$3="","",CF表!E20/10000) | F20: =IF(CF表!F$3="","",CF表!F20/10000) | G20: =IF(CF表!G$3="","",CF表!G20/10000) | H20: =IF(CF表!H$3="","",CF表!H20/10000) | I20: =IF(CF表!I$3="","",CF表!I20/10000) | ... CW20: =IF(CF表!CW$3="","",CF表!CW20/10000)
A21: 住居費 | B21: =IF(CF表!B$3="","",CF表!B21/10000) | C21: =IF(CF表!C$3="","",CF表!C21/10000) | D21: =IF(CF表!D$3="","",CF表!D21/10000) | E21: =IF(CF表!E$3="","",CF表!E21/10000) | F21: =IF(CF表!F$3="","",CF表!F21/10000) | G21: =IF(CF表!G$3="","",CF表!G21/10000) | H21: =IF(CF表!H$3="","",CF表!H21/10000) | I21: =IF(CF表!I$3="","",CF表!I21/10000) | ... CW21: =IF(CF表!CW$3="","",CF表!CW21/10000)
A22: 終身系保険料 | B22: =IF(CF表!B$3="","",CF表!B22/10000) | C22: =IF(CF表!C$3="","",CF表!C22/10000) | D22: =IF(CF表!D$3="","",CF表!D22/10000) | E22: =IF(CF表!E$3="","",CF表!E22/10000) | F22: =IF(CF表!F$3="","",CF表!F22/10000) | G22: =IF(CF表!G$3="","",CF表!G22/10000) | H22: =IF(CF表!H$3="","",CF表!H22/10000) | I22: =IF(CF表!I$3="","",CF表!I22/10000) | ... CW22: =IF(CF表!CW$3="","",CF表!CW22/10000)
A23: 定期系保険料 | B23: =IF(CF表!B$3="","",CF表!B23/10000) | C23: =IF(CF表!C$3="","",CF表!C23/10000) | D23: =IF(CF表!D$3="","",CF表!D23/10000) | E23: =IF(CF表!E$3="","",CF表!E23/10000) | F23: =IF(CF表!F$3="","",CF表!F23/10000) | G23: =IF(CF表!G$3="","",CF表!G23/10000) | H23: =IF(CF表!H$3="","",CF表!H23/10000) | I23: =IF(CF表!I$3="","",CF表!I23/10000) | ... CW23: =IF(CF表!CW$3="","",CF表!CW23/10000)
A24: 教育費 | B24: =IF(CF表!B$3="","",CF表!B24/10000) | C24: =IF(CF表!C$3="","",CF表!C24/10000) | D24: =IF(CF表!D$3="","",CF表!D24/10000) | E24: =IF(CF表!E$3="","",CF表!E24/10000) | F24: =IF(CF表!F$3="","",CF表!F24/10000) | G24: =IF(CF表!G$3="","",CF表!G24/10000) | H24: =IF(CF表!H$3="","",CF表!H24/10000) | I24: =IF(CF表!I$3="","",CF表!I24/10000) | ... CW24: =IF(CF表!CW$3="","",CF表!CW24/10000)
A25: 車関連費 | B25: =IF(CF表!B$3="","",CF表!B25/10000) | C25: =IF(CF表!C$3="","",CF表!C25/10000) | D25: =IF(CF表!D$3="","",CF表!D25/10000) | E25: =IF(CF表!E$3="","",CF表!E25/10000) | F25: =IF(CF表!F$3="","",CF表!F25/10000) | G25: =IF(CF表!G$3="","",CF表!G25/10000) | H25: =IF(CF表!H$3="","",CF表!H25/10000) | I25: =IF(CF表!I$3="","",CF表!I25/10000) | ... CW25: =IF(CF表!CW$3="","",CF表!CW25/10000)
A26: その他支出 | B26: =IF(CF表!B$3="","",CF表!B26/10000) | C26: =IF(CF表!C$3="","",CF表!C26/10000) | D26: =IF(CF表!D$3="","",CF表!D26/10000) | E26: =IF(CF表!E$3="","",CF表!E26/10000) | F26: =IF(CF表!F$3="","",CF表!F26/10000) | G26: =IF(CF表!G$3="","",CF表!G26/10000) | H26: =IF(CF表!H$3="","",CF表!H26/10000) | I26: =IF(CF表!I$3="","",CF表!I26/10000) | ... CW26: =IF(CF表!CW$3="","",CF表!CW26/10000)
A27: 一時支出 | B27: =IF(CF表!B$3="","",CF表!B27/10000) | C27: =IF(CF表!C$3="","",CF表!C27/10000) | D27: =IF(CF表!D$3="","",CF表!D27/10000) | E27: =IF(CF表!E$3="","",CF表!E27/10000) | F27: =IF(CF表!F$3="","",CF表!F27/10000) | G27: =IF(CF表!G$3="","",CF表!G27/10000) | H27: =IF(CF表!H$3="","",CF表!H27/10000) | I27: =IF(CF表!I$3="","",CF表!I27/10000) | ... CW27: =IF(CF表!CW$3="","",CF表!CW27/10000)
A28: 支出合計 | B28: =IF(CF表!B$3="","",CF表!B28/10000) | C28: =IF(CF表!C$3="","",CF表!C28/10000) | D28: =IF(CF表!D$3="","",CF表!D28/10000) | E28: =IF(CF表!E$3="","",CF表!E28/10000) | F28: =IF(CF表!F$3="","",CF表!F28/10000) | G28: =IF(CF表!G$3="","",CF表!G28/10000) | H28: =IF(CF表!H$3="","",CF表!H28/10000) | I28: =IF(CF表!I$3="","",CF表!I28/10000) | ... CW28: =IF(CF表!CW$3="","",CF表!CW28/10000)
A29: 収支・資産 | B29: =IF(CF表!B$3="","",CF表!B29/10000) | C29: =IF(CF表!C$3="","",CF表!C29/10000) | D29: =IF(CF表!D$3="","",CF表!D29/10000) | E29: =IF(CF表!E$3="","",CF表!E29/10000) | F29: =IF(CF表!F$3="","",CF表!F29/10000) | G29: =IF(CF表!G$3="","",CF表!G29/10000) | H29: =IF(CF表!H$3="","",CF表!H29/10000) | I29: =IF(CF表!I$3="","",CF表!I29/10000) | ... CW29: =IF(CF表!CW$3="","",CF表!CW29/10000)
A30: 年間収支 | B30: =IF(CF表!B$3="","",CF表!B30/10000) | C30: =IF(CF表!C$3="","",CF表!C30/10000) | D30: =IF(CF表!D$3="","",CF表!D30/10000) | E30: =IF(CF表!E$3="","",CF表!E30/10000) | F30: =IF(CF表!F$3="","",CF表!F30/10000) | G30: =IF(CF表!G$3="","",CF表!G30/10000) | H30: =IF(CF表!H$3="","",CF表!H30/10000) | I30: =IF(CF表!I$3="","",CF表!I30/10000) | ... CW30: =IF(CF表!CW$3="","",CF表!CW30/10000)
A31: 預貯金残高 | B31: =IF(CF表!B$3="","",CF表!B31/10000) | C31: =IF(CF表!C$3="","",CF表!C31/10000) | D31: =IF(CF表!D$3="","",CF表!D31/10000) | E31: =IF(CF表!E$3="","",CF表!E31/10000) | F31: =IF(CF表!F$3="","",CF表!F31/10000) | G31: =IF(CF表!G$3="","",CF表!G31/10000) | H31: =IF(CF表!H$3="","",CF表!H31/10000) | I31: =IF(CF表!I$3="","",CF表!I31/10000) | ... CW31: =IF(CF表!CW$3="","",CF表!CW31/10000)
... A45: 負債合計（参考） | B45: =IF(CF表!B$3="","",CF表!B45/10000) | C45: =IF(CF表!C$3="","",CF表!C45/10000) | D45: =IF(CF表!D$3="","",CF表!D45/10000) | E45: =IF(CF表!E$3="","",CF表!E45/10000) | F45: =IF(CF表!F$3="","",CF表!F45/10000) | G45: =IF(CF表!G$3="","",CF表!G45/10000) | H45: =IF(CF表!H$3="","",CF表!H45/10000) | I45: =IF(CF表!I$3="","",CF表!I45/10000) | ... CW45: =IF(CF表!CW$3="","",CF表!CW45/10000)

Sheet CF表（ご主人様死亡時・万円表示）
A1: CF表（ご主人様死亡時・万円表示）
A2: 試算終了年 | B2: ='CF表（ご主人様死亡時）'!B2
A3: 年 | B3: =IF('CF表（ご主人様死亡時）'!B3="","",'CF表（ご主人様死亡時）'!B3) | C3: =IF('CF表（ご主人様死亡時）'!C3="","",'CF表（ご主人様死亡時）'!C3) | D3: =IF('CF表（ご主人様死亡時）'!D3="","",'CF表（ご主人様死亡時）'!D3) | E3: =IF('CF表（ご主人様死亡時）'!E3="","",'CF表（ご主人様死亡時）'!E3) | F3: =IF('CF表（ご主人様死亡時）'!F3="","",'CF表（ご主人様死亡時）'!F3) | G3: =IF('CF表（ご主人様死亡時）'!G3="","",'CF表（ご主人様死亡時）'!G3) | H3: =IF('CF表（ご主人様死亡時）'!H3="","",'CF表（ご主人様死亡時）'!H3) | I3: =IF('CF表（ご主人様死亡時）'!I3="","",'CF表（ご主人様死亡時）'!I3) | ... CW3: =IF('CF表（ご主人様死亡時）'!CW3="","",'CF表（ご主人様死亡時）'!CW3)
A4: ご主人様年齢 | B4: =IF('CF表（ご主人様死亡時）'!B4="","",'CF表（ご主人様死亡時）'!B4) | C4: =IF('CF表（ご主人様死亡時）'!C4="","",'CF表（ご主人様死亡時）'!C4) | D4: =IF('CF表（ご主人様死亡時）'!D4="","",'CF表（ご主人様死亡時）'!D4) | E4: =IF('CF表（ご主人様死亡時）'!E4="","",'CF表（ご主人様死亡時）'!E4) | F4: =IF('CF表（ご主人様死亡時）'!F4="","",'CF表（ご主人様死亡時）'!F4) | G4: =IF('CF表（ご主人様死亡時）'!G4="","",'CF表（ご主人様死亡時）'!G4) | H4: =IF('CF表（ご主人様死亡時）'!H4="","",'CF表（ご主人様死亡時）'!H4) | I4: =IF('CF表（ご主人様死亡時）'!I4="","",'CF表（ご主人様死亡時）'!I4) | ... CW4: =IF('CF表（ご主人様死亡時）'!CW4="","",'CF表（ご主人様死亡時）'!CW4)
A5: 奥様年齢 | B5: =IF('CF表（ご主人様死亡時）'!B5="","",'CF表（ご主人様死亡時）'!B5) | C5: =IF('CF表（ご主人様死亡時）'!C5="","",'CF表（ご主人様死亡時）'!C5) | D5: =IF('CF表（ご主人様死亡時）'!D5="","",'CF表（ご主人様死亡時）'!D5) | E5: =IF('CF表（ご主人様死亡時）'!E5="","",'CF表（ご主人様死亡時）'!E5) | F5: =IF('CF表（ご主人様死亡時）'!F5="","",'CF表（ご主人様死亡時）'!F5) | G5: =IF('CF表（ご主人様死亡時）'!G5="","",'CF表（ご主人様死亡時）'!G5) | H5: =IF('CF表（ご主人様死亡時）'!H5="","",'CF表（ご主人様死亡時）'!H5) | I5: =IF('CF表（ご主人様死亡時）'!I5="","",'CF表（ご主人様死亡時）'!I5) | ... CW5: =IF('CF表（ご主人様死亡時）'!CW5="","",'CF表（ご主人様死亡時）'!CW5)
A6: 子1年齢 | B6: =IF('CF表（ご主人様死亡時）'!B6="","",'CF表（ご主人様死亡時）'!B6) | C6: =IF('CF表（ご主人様死亡時）'!C6="","",'CF表（ご主人様死亡時）'!C6) | D6: =IF('CF表（ご主人様死亡時）'!D6="","",'CF表（ご主人様死亡時）'!D6) | E6: =IF('CF表（ご主人様死亡時）'!E6="","",'CF表（ご主人様死亡時）'!E6) | F6: =IF('CF表（ご主人様死亡時）'!F6="","",'CF表（ご主人様死亡時）'!F6) | G6: =IF('CF表（ご主人様死亡時）'!G6="","",'CF表（ご主人様死亡時）'!G6) | H6: =IF('CF表（ご主人様死亡時）'!H6="","",'CF表（ご主人様死亡時）'!H6) | I6: =IF('CF表（ご主人様死亡時）'!I6="","",'CF表（ご主人様死亡時）'!I6) | ... CW6: =IF('CF表（ご主人様死亡時）'!CW6="","",'CF表（ご主人様死亡時）'!CW6)
A7: 子2年齢 | B7: =IF('CF表（ご主人様死亡時）'!B7="","",'CF表（ご主人様死亡時）'!B7) | C7: =IF('CF表（ご主人様死亡時）'!C7="","",'CF表（ご主人様死亡時）'!C7) | D7: =IF('CF表（ご主人様死亡時）'!D7="","",'CF表（ご主人様死亡時）'!D7) | E7: =IF('CF表（ご主人様死亡時）'!E7="","",'CF表（ご主人様死亡時）'!E7) | F7: =IF('CF表（ご主人様死亡時）'!F7="","",'CF表（ご主人様死亡時）'!F7) | G7: =IF('CF表（ご主人様死亡時）'!G7="","",'CF表（ご主人様死亡時）'!G7) | H7: =IF('CF表（ご主人様死亡時）'!H7="","",'CF表（ご主人様死亡時）'!H7) | I7: =IF('CF表（ご主人様死亡時）'!I7="","",'CF表（ご主人様死亡時）'!I7) | ... CW7: =IF('CF表（ご主人様死亡時）'!CW7="","",'CF表（ご主人様死亡時）'!CW7)
A8: 子3年齢 | B8: =IF('CF表（ご主人様死亡時）'!B8="","",'CF表（ご主人様死亡時）'!B8) | C8: =IF('CF表（ご主人様死亡時）'!C8="","",'CF表（ご主人様死亡時）'!C8) | D8: =IF('CF表（ご主人様死亡時）'!D8="","",'CF表（ご主人様死亡時）'!D8) | E8: =IF('CF表（ご主人様死亡時）'!E8="","",'CF表（ご主人様死亡時）'!E8) | F8: =IF('CF表（ご主人様死亡時）'!F8="","",'CF表（ご主人様死亡時）'!F8) | G8: =IF('CF表（ご主人様死亡時）'!G8="","",'CF表（ご主人様死亡時）'!G8) | H8: =IF('CF表（ご主人様死亡時）'!H8="","",'CF表（ご主人様死亡時）'!H8) | I8: =IF('CF表（ご主人様死亡時）'!I8="","",'CF表（ご主人様死亡時）'!I8) | ... CW8: =IF('CF表（ご主人様死亡時）'!CW8="","",'CF表（ご主人様死亡時）'!CW8)
A9: 家族年齢
A10: ご主人様収入 | B10: =IF('CF表（ご主人様死亡時）'!B$3="","",'CF表（ご主人様死亡時）'!B10/10000) | C10: =IF('CF表（ご主人様死亡時）'!C$3="","",'CF表（ご主人様死亡時）'!C10/10000) | D10: =IF('CF表（ご主人様死亡時）'!D$3="","",'CF表（ご主人様死亡時）'!D10/10000) | E10: =IF('CF表（ご主人様死亡時）'!E$3="","",'CF表（ご主人様死亡時）'!E10/10000) | F10: =IF('CF表（ご主人様死亡時）'!F$3="","",'CF表（ご主人様死亡時）'!F10/10000) | G10: =IF('CF表（ご主人様死亡時）'!G$3="","",'CF表（ご主人様死亡時）'!G10/10000) | H10: =IF('CF表（ご主人様死亡時）'!H$3="","",'CF表（ご主人様死亡時）'!H10/10000) | I10: =IF('CF表（ご主人様死亡時）'!I$3="","",'CF表（ご主人様死亡時）'!I10/10000) | ... CW10: =IF('CF表（ご主人様死亡時）'!CW$3="","",'CF表（ご主人様死亡時）'!CW10/10000)
A11: 奥様収入 | B11: =IF('CF表（ご主人様死亡時）'!B$3="","",'CF表（ご主人様死亡時）'!B11/10000) | C11: =IF('CF表（ご主人様死亡時）'!C$3="","",'CF表（ご主人様死亡時）'!C11/10000) | D11: =IF('CF表（ご主人様死亡時）'!D$3="","",'CF表（ご主人様死亡時）'!D11/10000) | E11: =IF('CF表（ご主人様死亡時）'!E$3="","",'CF表（ご主人様死亡時）'!E11/10000) | F11: =IF('CF表（ご主人様死亡時）'!F$3="","",'CF表（ご主人様死亡時）'!F11/10000) | G11: =IF('CF表（ご主人様死亡時）'!G$3="","",'CF表（ご主人様死亡時）'!G11/10000) | H11: =IF('CF表（ご主人様死亡時）'!H$3="","",'CF表（ご主人様死亡時）'!H11/10000) | I11: =IF('CF表（ご主人様死亡時）'!I$3="","",'CF表（ご主人様死亡時）'!I11/10000) | ... CW11: =IF('CF表（ご主人様死亡時）'!CW$3="","",'CF表（ご主人様死亡時）'!CW11/10000)
A12: 児童手当 | B12: =IF('CF表（ご主人様死亡時）'!B$3="","",'CF表（ご主人様死亡時）'!B12/10000) | C12: =IF('CF表（ご主人様死亡時）'!C$3="","",'CF表（ご主人様死亡時）'!C12/10000) | D12: =IF('CF表（ご主人様死亡時）'!D$3="","",'CF表（ご主人様死亡時）'!D12/10000) | E12: =IF('CF表（ご主人様死亡時）'!E$3="","",'CF表（ご主人様死亡時）'!E12/10000) | F12: =IF('CF表（ご主人様死亡時）'!F$3="","",'CF表（ご主人様死亡時）'!F12/10000) | G12: =IF('CF表（ご主人様死亡時）'!G$3="","",'CF表（ご主人様死亡時）'!G12/10000) | H12: =IF('CF表（ご主人様死亡時）'!H$3="","",'CF表（ご主人様死亡時）'!H12/10000) | I12: =IF('CF表（ご主人様死亡時）'!I$3="","",'CF表（ご主人様死亡時）'!I12/10000) | ... CW12: =IF('CF表（ご主人様死亡時）'!CW$3="","",'CF表（ご主人様死亡時）'!CW12/10000)
A13: その他収入 | B13: =IF('CF表（ご主人様死亡時）'!B$3="","",'CF表（ご主人様死亡時）'!B13/10000) | C13: =IF('CF表（ご主人様死亡時）'!C$3="","",'CF表（ご主人様死亡時）'!C13/10000) | D13: =IF('CF表（ご主人様死亡時）'!D$3="","",'CF表（ご主人様死亡時）'!D13/10000) | E13: =IF('CF表（ご主人様死亡時）'!E$3="","",'CF表（ご主人様死亡時）'!E13/10000) | F13: =IF('CF表（ご主人様死亡時）'!F$3="","",'CF表（ご主人様死亡時）'!F13/10000) | G13: =IF('CF表（ご主人様死亡時）'!G$3="","",'CF表（ご主人様死亡時）'!G13/10000) | H13: =IF('CF表（ご主人様死亡時）'!H$3="","",'CF表（ご主人様死亡時）'!H13/10000) | I13: =IF('CF表（ご主人様死亡時）'!I$3="","",'CF表（ご主人様死亡時）'!I13/10000) | ... CW13: =IF('CF表（ご主人様死亡時）'!CW$3="","",'CF表（ご主人様死亡時）'!CW13/10000)
A14: ご主人様退職金 | B14: =IF('CF表（ご主人様死亡時）'!B$3="","",'CF表（ご主人様死亡時）'!B14/10000) | C14: =IF('CF表（ご主人様死亡時）'!C$3="","",'CF表（ご主人様死亡時）'!C14/10000) | D14: =IF('CF表（ご主人様死亡時）'!D$3="","",'CF表（ご主人様死亡時）'!D14/10000) | E14: =IF('CF表（ご主人様死亡時）'!E$3="","",'CF表（ご主人様死亡時）'!E14/10000) | F14: =IF('CF表（ご主人様死亡時）'!F$3="","",'CF表（ご主人様死亡時）'!F14/10000) | G14: =IF('CF表（ご主人様死亡時）'!G$3="","",'CF表（ご主人様死亡時）'!G14/10000) | H14: =IF('CF表（ご主人様死亡時）'!H$3="","",'CF表（ご主人様死亡時）'!H14/10000) | I14: =IF('CF表（ご主人様死亡時）'!I$3="","",'CF表（ご主人様死亡時）'!I14/10000) | ... CW14: =IF('CF表（ご主人様死亡時）'!CW$3="","",'CF表（ご主人様死亡時）'!CW14/10000)
A15: 奥様退職金 | B15: =IF('CF表（ご主人様死亡時）'!B$3="","",'CF表（ご主人様死亡時）'!B15/10000) | C15: =IF('CF表（ご主人様死亡時）'!C$3="","",'CF表（ご主人様死亡時）'!C15/10000) | D15: =IF('CF表（ご主人様死亡時）'!D$3="","",'CF表（ご主人様死亡時）'!D15/10000) | E15: =IF('CF表（ご主人様死亡時）'!E$3="","",'CF表（ご主人様死亡時）'!E15/10000) | F15: =IF('CF表（ご主人様死亡時）'!F$3="","",'CF表（ご主人様死亡時）'!F15/10000) | G15: =IF('CF表（ご主人様死亡時）'!G$3="","",'CF表（ご主人様死亡時）'!G15/10000) | H15: =IF('CF表（ご主人様死亡時）'!H$3="","",'CF表（ご主人様死亡時）'!H15/10000) | I15: =IF('CF表（ご主人様死亡時）'!I$3="","",'CF表（ご主人様死亡時）'!I15/10000) | ... CW15: =IF('CF表（ご主人様死亡時）'!CW$3="","",'CF表（ご主人様死亡時）'!CW15/10000)
A16: ご主人様年金収入 | B16: =IF('CF表（ご主人様死亡時）'!B$3="","",'CF表（ご主人様死亡時）'!B16/10000) | C16: =IF('CF表（ご主人様死亡時）'!C$3="","",'CF表（ご主人様死亡時）'!C16/10000) | D16: =IF('CF表（ご主人様死亡時）'!D$3="","",'CF表（ご主人様死亡時）'!D16/10000) | E16: =IF('CF表（ご主人様死亡時）'!E$3="","",'CF表（ご主人様死亡時）'!E16/10000) | F16: =IF('CF表（ご主人様死亡時）'!F$3="","",'CF表（ご主人様死亡時）'!F16/10000) | G16: =IF('CF表（ご主人様死亡時）'!G$3="","",'CF表（ご主人様死亡時）'!G16/10000) | H16: =IF('CF表（ご主人様死亡時）'!H$3="","",'CF表（ご主人様死亡時）'!H16/10000) | I16: =IF('CF表（ご主人様死亡時）'!I$3="","",'CF表（ご主人様死亡時）'!I16/10000) | ... CW16: =IF('CF表（ご主人様死亡時）'!CW$3="","",'CF表（ご主人様死亡時）'!CW16/10000)
A17: 奥様年金収入 | B17: =IF('CF表（ご主人様死亡時）'!B$3="","",'CF表（ご主人様死亡時）'!B17/10000) | C17: =IF('CF表（ご主人様死亡時）'!C$3="","",'CF表（ご主人様死亡時）'!C17/10000) | D17: =IF('CF表（ご主人様死亡時）'!D$3="","",'CF表（ご主人様死亡時）'!D17/10000) | E17: =IF('CF表（ご主人様死亡時）'!E$3="","",'CF表（ご主人様死亡時）'!E17/10000) | F17: =IF('CF表（ご主人様死亡時）'!F$3="","",'CF表（ご主人様死亡時）'!F17/10000) | G17: =IF('CF表（ご主人様死亡時）'!G$3="","",'CF表（ご主人様死亡時）'!G17/10000) | H17: =IF('CF表（ご主人様死亡時）'!H$3="","",'CF表（ご主人様死亡時）'!H17/10000) | I17: =IF('CF表（ご主人様死亡時）'!I$3="","",'CF表（ご主人様死亡時）'!I17/10000) | ... CW17: =IF('CF表（ご主人様死亡時）'!CW$3="","",'CF表（ご主人様死亡時）'!CW17/10000)
A18: 世帯収入合計 | B18: =IF('CF表（ご主人様死亡時）'!B$3="","",'CF表（ご主人様死亡時）'!B18/10000) | C18: =IF('CF表（ご主人様死亡時）'!C$3="","",'CF表（ご主人様死亡時）'!C18/10000) | D18: =IF('CF表（ご主人様死亡時）'!D$3="","",'CF表（ご主人様死亡時）'!D18/10000) | E18: =IF('CF表（ご主人様死亡時）'!E$3="","",'CF表（ご主人様死亡時）'!E18/10000) | F18: =IF('CF表（ご主人様死亡時）'!F$3="","",'CF表（ご主人様死亡時）'!F18/10000) | G18: =IF('CF表（ご主人様死亡時）'!G$3="","",'CF表（ご主人様死亡時）'!G18/10000) | H18: =IF('CF表（ご主人様死亡時）'!H$3="","",'CF表（ご主人様死亡時）'!H18/10000) | I18: =IF('CF表（ご主人様死亡時）'!I$3="","",'CF表（ご主人様死亡時）'!I18/10000) | ... CW18: =IF('CF表（ご主人様死亡時）'!CW$3="","",'CF表（ご主人様死亡時）'!CW18/10000)
A19: 収入
A20: 基本生活費 | B20: =IF('CF表（ご主人様死亡時）'!B$3="","",'CF表（ご主人様死亡時）'!B20/10000) | C20: =IF('CF表（ご主人様死亡時）'!C$3="","",'CF表（ご主人様死亡時）'!C20/10000) | D20: =IF('CF表（ご主人様死亡時）'!D$3="","",'CF表（ご主人様死亡時）'!D20/10000) | E20: =IF('CF表（ご主人様死亡時）'!E$3="","",'CF表（ご主人様死亡時）'!E20/10000) | F20: =IF('CF表（ご主人様死亡時）'!F$3="","",'CF表（ご主人様死亡時）'!F20/10000) | G20: =IF('CF表（ご主人様死亡時）'!G$3="","",'CF表（ご主人様死亡時）'!G20/10000) | H20: =IF('CF表（ご主人様死亡時）'!H$3="","",'CF表（ご主人様死亡時）'!H20/10000) | I20: =IF('CF表（ご主人様死亡時）'!I$3="","",'CF表（ご主人様死亡時）'!I20/10000) | ... CW20: =IF('CF表（ご主人様死亡時）'!CW$3="","",'CF表（ご主人様死亡時）'!CW20/10000)
A21: 住居費 | B21: =IF('CF表（ご主人様死亡時）'!B$3="","",'CF表（ご主人様死亡時）'!B21/10000) | C21: =IF('CF表（ご主人様死亡時）'!C$3="","",'CF表（ご主人様死亡時）'!C21/10000) | D21: =IF('CF表（ご主人様死亡時）'!D$3="","",'CF表（ご主人様死亡時）'!D21/10000) | E21: =IF('CF表（ご主人様死亡時）'!E$3="","",'CF表（ご主人様死亡時）'!E21/10000) | F21: =IF('CF表（ご主人様死亡時）'!F$3="","",'CF表（ご主人様死亡時）'!F21/10000) | G21: =IF('CF表（ご主人様死亡時）'!G$3="","",'CF表（ご主人様死亡時）'!G21/10000) | H21: =IF('CF表（ご主人様死亡時）'!H$3="","",'CF表（ご主人様死亡時）'!H21/10000) | I21: =IF('CF表（ご主人様死亡時）'!I$3="","",'CF表（ご主人様死亡時）'!I21/10000) | ... CW21: =IF('CF表（ご主人様死亡時）'!CW$3="","",'CF表（ご主人様死亡時）'!CW21/10000)
A22: 終身系保険料 | B22: =IF('CF表（ご主人様死亡時）'!B$3="","",'CF表（ご主人様死亡時）'!B22/10000) | C22: =IF('CF表（ご主人様死亡時）'!C$3="","",'CF表（ご主人様死亡時）'!C22/10000) | D22: =IF('CF表（ご主人様死亡時）'!D$3="","",'CF表（ご主人様死亡時）'!D22/10000) | E22: =IF('CF表（ご主人様死亡時）'!E$3="","",'CF表（ご主人様死亡時）'!E22/10000) | F22: =IF('CF表（ご主人様死亡時）'!F$3="","",'CF表（ご主人様死亡時）'!F22/10000) | G22: =IF('CF表（ご主人様死亡時）'!G$3="","",'CF表（ご主人様死亡時）'!G22/10000) | H22: =IF('CF表（ご主人様死亡時）'!H$3="","",'CF表（ご主人様死亡時）'!H22/10000) | I22: =IF('CF表（ご主人様死亡時）'!I$3="","",'CF表（ご主人様死亡時）'!I22/10000) | ... CW22: =IF('CF表（ご主人様死亡時）'!CW$3="","",'CF表（ご主人様死亡時）'!CW22/10000)
A23: 定期系保険料 | B23: =IF('CF表（ご主人様死亡時）'!B$3="","",'CF表（ご主人様死亡時）'!B23/10000) | C23: =IF('CF表（ご主人様死亡時）'!C$3="","",'CF表（ご主人様死亡時）'!C23/10000) | D23: =IF('CF表（ご主人様死亡時）'!D$3="","",'CF表（ご主人様死亡時）'!D23/10000) | E23: =IF('CF表（ご主人様死亡時）'!E$3="","",'CF表（ご主人様死亡時）'!E23/10000) | F23: =IF('CF表（ご主人様死亡時）'!F$3="","",'CF表（ご主人様死亡時）'!F23/10000) | G23: =IF('CF表（ご主人様死亡時）'!G$3="","",'CF表（ご主人様死亡時）'!G23/10000) | H23: =IF('CF表（ご主人様死亡時）'!H$3="","",'CF表（ご主人様死亡時）'!H23/10000) | I23: =IF('CF表（ご主人様死亡時）'!I$3="","",'CF表（ご主人様死亡時）'!I23/10000) | ... CW23: =IF('CF表（ご主人様死亡時）'!CW$3="","",'CF表（ご主人様死亡時）'!CW23/10000)
A24: 教育費 | B24: =IF('CF表（ご主人様死亡時）'!B$3="","",'CF表（ご主人様死亡時）'!B24/10000) | C24: =IF('CF表（ご主人様死亡時）'!C$3="","",'CF表（ご主人様死亡時）'!C24/10000) | D24: =IF('CF表（ご主人様死亡時）'!D$3="","",'CF表（ご主人様死亡時）'!D24/10000) | E24: =IF('CF表（ご主人様死亡時）'!E$3="","",'CF表（ご主人様死亡時）'!E24/10000) | F24: =IF('CF表（ご主人様死亡時）'!F$3="","",'CF表（ご主人様死亡時）'!F24/10000) | G24: =IF('CF表（ご主人様死亡時）'!G$3="","",'CF表（ご主人様死亡時）'!G24/10000) | H24: =IF('CF表（ご主人様死亡時）'!H$3="","",'CF表（ご主人様死亡時）'!H24/10000) | I24: =IF('CF表（ご主人様死亡時）'!I$3="","",'CF表（ご主人様死亡時）'!I24/10000) | ... CW24: =IF('CF表（ご主人様死亡時）'!CW$3="","",'CF表（ご主人様死亡時）'!CW24/10000)
A25: 車関連費 | B25: =IF('CF表（ご主人様死亡時）'!B$3="","",'CF表（ご主人様死亡時）'!B25/10000) | C25: =IF('CF表（ご主人様死亡時）'!C$3="","",'CF表（ご主人様死亡時）'!C25/10000) | D25: =IF('CF表（ご主人様死亡時）'!D$3="","",'CF表（ご主人様死亡時）'!D25/10000) | E25: =IF('CF表（ご主人様死亡時）'!E$3="","",'CF表（ご主人様死亡時）'!E25/10000) | F25: =IF('CF表（ご主人様死亡時）'!F$3="","",'CF表（ご主人様死亡時）'!F25/10000) | G25: =IF('CF表（ご主人様死亡時）'!G$3="","",'CF表（ご主人様死亡時）'!G25/10000) | H25: =IF('CF表（ご主人様死亡時）'!H$3="","",'CF表（ご主人様死亡時）'!H25/10000) | I25: =IF('CF表（ご主人様死亡時）'!I$3="","",'CF表（ご主人様死亡時）'!I25/10000) | ... CW25: =IF('CF表（ご主人様死亡時）'!CW$3="","",'CF表（ご主人様死亡時）'!CW25/10000)
A26: その他支出 | B26: =IF('CF表（ご主人様死亡時）'!B$3="","",'CF表（ご主人様死亡時）'!B26/10000) | C26: =IF('CF表（ご主人様死亡時）'!C$3="","",'CF表（ご主人様死亡時）'!C26/10000) | D26: =IF('CF表（ご主人様死亡時）'!D$3="","",'CF表（ご主人様死亡時）'!D26/10000) | E26: =IF('CF表（ご主人様死亡時）'!E$3="","",'CF表（ご主人様死亡時）'!E26/10000) | F26: =IF('CF表（ご主人様死亡時）'!F$3="","",'CF表（ご主人様死亡時）'!F26/10000) | G26: =IF('CF表（ご主人様死亡時）'!G$3="","",'CF表（ご主人様死亡時）'!G26/10000) | H26: =IF('CF表（ご主人様死亡時）'!H$3="","",'CF表（ご主人様死亡時）'!H26/10000) | I26: =IF('CF表（ご主人様死亡時）'!I$3="","",'CF表（ご主人様死亡時）'!I26/10000) | ... CW26: =IF('CF表（ご主人様死亡時）'!CW$3="","",'CF表（ご主人様死亡時）'!CW26/10000)
A27: 一時支出 | B27: =IF('CF表（ご主人様死亡時）'!B$3="","",'CF表（ご主人様死亡時）'!B27/10000) | C27: =IF('CF表（ご主人様死亡時）'!C$3="","",'CF表（ご主人様死亡時）'!C27/10000) | D27: =IF('CF表（ご主人様死亡時）'!D$3="","",'CF表（ご主人様死亡時）'!D27/10000) | E27: =IF('CF表（ご主人様死亡時）'!E$3="","",'CF表（ご主人様死亡時）'!E27/10000) | F27: =IF('CF表（ご主人様死亡時）'!F$3="","",'CF表（ご主人様死亡時）'!F27/10000) | G27: =IF('CF表（ご主人様死亡時）'!G$3="","",'CF表（ご主人様死亡時）'!G27/10000) | H27: =IF('CF表（ご主人様死亡時）'!H$3="","",'CF表（ご主人様死亡時）'!H27/10000) | I27: =IF('CF表（ご主人様死亡時）'!I$3="","",'CF表（ご主人様死亡時）'!I27/10000) | ... CW27: =IF('CF表（ご主人様死亡時）'!CW$3="","",'CF表（ご主人様死亡時）'!CW27/10000)
A28: 支出合計 | B28: =IF('CF表（ご主人様死亡時）'!B$3="","",'CF表（ご主人様死亡時）'!B28/10000) | C28: =IF('CF表（ご主人様死亡時）'!C$3="","",'CF表（ご主人様死亡時）'!C28/10000) | D28: =IF('CF表（ご主人様死亡時）'!D$3="","",'CF表（ご主人様死亡時）'!D28/10000) | E28: =IF('CF表（ご主人様死亡時）'!E$3="","",'CF表（ご主人様死亡時）'!E28/10000) | F28: =IF('CF表（ご主人様死亡時）'!F$3="","",'CF表（ご主人様死亡時）'!F28/10000) | G28: =IF('CF表（ご主人様死亡時）'!G$3="","",'CF表（ご主人様死亡時）'!G28/10000) | H28: =IF('CF表（ご主人様死亡時）'!H$3="","",'CF表（ご主人様死亡時）'!H28/10000) | I28: =IF('CF表（ご主人様死亡時）'!I$3="","",'CF表（ご主人様死亡時）'!I28/10000) | ... CW28: =IF('CF表（ご主人様死亡時）'!CW$3="","",'CF表（ご主人様死亡時）'!CW28/10000)
A29: 収支・資産 | B29: =IF('CF表（ご主人様死亡時）'!B$3="","",'CF表（ご主人様死亡時）'!B29/10000) | C29: =IF('CF表（ご主人様死亡時）'!C$3="","",'CF表（ご主人様死亡時）'!C29/10000) | D29: =IF('CF表（ご主人様死亡時）'!D$3="","",'CF表（ご主人様死亡時）'!D29/10000) | E29: =IF('CF表（ご主人様死亡時）'!E$3="","",'CF表（ご主人様死亡時）'!E29/10000) | F29: =IF('CF表（ご主人様死亡時）'!F$3="","",'CF表（ご主人様死亡時）'!F29/10000) | G29: =IF('CF表（ご主人様死亡時）'!G$3="","",'CF表（ご主人様死亡時）'!G29/10000) | H29: =IF('CF表（ご主人様死亡時）'!H$3="","",'CF表（ご主人様死亡時）'!H29/10000) | I29: =IF('CF表（ご主人様死亡時）'!I$3="","",'CF表（ご主人様死亡時）'!I29/10000) | ... CW29: =IF('CF表（ご主人様死亡時）'!CW$3="","",'CF表（ご主人様死亡時）'!CW29/10000)
A30: 年間収支 | B30: =IF('CF表（ご主人様死亡時）'!B$3="","",'CF表（ご主人様死亡時）'!B30/10000) | C30: =IF('CF表（ご主人様死亡時）'!C$3="","",'CF表（ご主人様死亡時）'!C30/10000) | D30: =IF('CF表（ご主人様死亡時）'!D$3="","",'CF表（ご主人様死亡時）'!D30/10000) | E30: =IF('CF表（ご主人様死亡時）'!E$3="","",'CF表（ご主人様死亡時）'!E30/10000) | F30: =IF('CF表（ご主人様死亡時）'!F$3="","",'CF表（ご主人様死亡時）'!F30/10000) | G30: =IF('CF表（ご主人様死亡時）'!G$3="","",'CF表（ご主人様死亡時）'!G30/10000) | H30: =IF('CF表（ご主人様死亡時）'!H$3="","",'CF表（ご主人様死亡時）'!H30/10000) | I30: =IF('CF表（ご主人様死亡時）'!I$3="","",'CF表（ご主人様死亡時）'!I30/10000) | ... CW30: =IF('CF表（ご主人様死亡時）'!CW$3="","",'CF表（ご主人様死亡時）'!CW30/10000)
A31: 預貯金残高 | B31: =IF('CF表（ご主人様死亡時）'!B$3="","",'CF表（ご主人様死亡時）'!B31/10000) | C31: =IF('CF表（ご主人様死亡時）'!C$3="","",'CF表（ご主人様死亡時）'!C31/10000) | D31: =IF('CF表（ご主人様死亡時）'!D$3="","",'CF表（ご主人様死亡時）'!D31/10000) | E31: =IF('CF表（ご主人様死亡時）'!E$3="","",'CF表（ご主人様死亡時）'!E31/10000) | F31: =IF('CF表（ご主人様死亡時）'!F$3="","",'CF表（ご主人様死亡時）'!F31/10000) | G31: =IF('CF表（ご主人様死亡時）'!G$3="","",'CF表（ご主人様死亡時）'!G31/10000) | H31: =IF('CF表（ご主人様死亡時）'!H$3="","",'CF表（ご主人様死亡時）'!H31/10000) | I31: =IF('CF表（ご主人様死亡時）'!I$3="","",'CF表（ご主人様死亡時）'!I31/10000) | ... CW31: =IF('CF表（ご主人様死亡時）'!CW$3="","",'CF表（ご主人様死亡時）'!CW31/10000)
... A45: 負債合計（参考） | B45: =IF('CF表（ご主人様死亡時）'!B$3="","",'CF表（ご主人様死亡時）'!B45/10000) | C45: =IF('CF表（ご主人様死亡時）'!C$3="","",'CF表（ご主人様死亡時）'!C45/10000) | D45: =IF('CF表（ご主人様死亡時）'!D$3="","",'CF表（ご主人様死亡時）'!D45/10000) | E45: =IF('CF表（ご主人様死亡時）'!E$3="","",'CF表（ご主人様死亡時）'!E45/10000) | F45: =IF('CF表（ご主人様死亡時）'!F$3="","",'CF表（ご主人様死亡時）'!F45/10000) | G45: =IF('CF表（ご主人様死亡時）'!G$3="","",'CF表（ご主人様死亡時）'!G45/10000) | H45: =IF('CF表（ご主人様死亡時）'!H$3="","",'CF表（ご主人様死亡時）'!H45/10000) | I45: =IF('CF表（ご主人様死亡時）'!I$3="","",'CF表（ご主人様死亡時）'!I45/10000) | ... CW45: =IF('CF表（ご主人様死亡時）'!CW$3="","",'CF表（ご主人様死亡時）'!CW45/10000)

Sheet CF表（奥様死亡時・万円表示）
A1: CF表（奥様死亡時・万円表示）
A2: 試算終了年 | B2: ='CF表（奥様死亡時）'!B2
A3: 年 | B3: =IF('CF表（奥様死亡時）'!B3="","",'CF表（奥様死亡時）'!B3) | C3: =IF('CF表（奥様死亡時）'!C3="","",'CF表（奥様死亡時）'!C3) | D3: =IF('CF表（奥様死亡時）'!D3="","",'CF表（奥様死亡時）'!D3) | E3: =IF('CF表（奥様死亡時）'!E3="","",'CF表（奥様死亡時）'!E3) | F3: =IF('CF表（奥様死亡時）'!F3="","",'CF表（奥様死亡時）'!F3) | G3: =IF('CF表（奥様死亡時）'!G3="","",'CF表（奥様死亡時）'!G3) | H3: =IF('CF表（奥様死亡時）'!H3="","",'CF表（奥様死亡時）'!H3) | I3: =IF('CF表（奥様死亡時）'!I3="","",'CF表（奥様死亡時）'!I3) | ... CW3: =IF('CF表（奥様死亡時）'!CW3="","",'CF表（奥様死亡時）'!CW3)
A4: ご主人様年齢 | B4: =IF('CF表（奥様死亡時）'!B4="","",'CF表（奥様死亡時）'!B4) | C4: =IF('CF表（奥様死亡時）'!C4="","",'CF表（奥様死亡時）'!C4) | D4: =IF('CF表（奥様死亡時）'!D4="","",'CF表（奥様死亡時）'!D4) | E4: =IF('CF表（奥様死亡時）'!E4="","",'CF表（奥様死亡時）'!E4) | F4: =IF('CF表（奥様死亡時）'!F4="","",'CF表（奥様死亡時）'!F4) | G4: =IF('CF表（奥様死亡時）'!G4="","",'CF表（奥様死亡時）'!G4) | H4: =IF('CF表（奥様死亡時）'!H4="","",'CF表（奥様死亡時）'!H4) | I4: =IF('CF表（奥様死亡時）'!I4="","",'CF表（奥様死亡時）'!I4) | ... CW4: =IF('CF表（奥様死亡時）'!CW4="","",'CF表（奥様死亡時）'!CW4)
A5: 奥様年齢 | B5: =IF('CF表（奥様死亡時）'!B5="","",'CF表（奥様死亡時）'!B5) | C5: =IF('CF表（奥様死亡時）'!C5="","",'CF表（奥様死亡時）'!C5) | D5: =IF('CF表（奥様死亡時）'!D5="","",'CF表（奥様死亡時）'!D5) | E5: =IF('CF表（奥様死亡時）'!E5="","",'CF表（奥様死亡時）'!E5) | F5: =IF('CF表（奥様死亡時）'!F5="","",'CF表（奥様死亡時）'!F5) | G5: =IF('CF表（奥様死亡時）'!G5="","",'CF表（奥様死亡時）'!G5) | H5: =IF('CF表（奥様死亡時）'!H5="","",'CF表（奥様死亡時）'!H5) | I5: =IF('CF表（奥様死亡時）'!I5="","",'CF表（奥様死亡時）'!I5) | ... CW5: =IF('CF表（奥様死亡時）'!CW5="","",'CF表（奥様死亡時）'!CW5)
A6: 子1年齢 | B6: =IF('CF表（奥様死亡時）'!B6="","",'CF表（奥様死亡時）'!B6) | C6: =IF('CF表（奥様死亡時）'!C6="","",'CF表（奥様死亡時）'!C6) | D6: =IF('CF表（奥様死亡時）'!D6="","",'CF表（奥様死亡時）'!D6) | E6: =IF('CF表（奥様死亡時）'!E6="","",'CF表（奥様死亡時）'!E6) | F6: =IF('CF表（奥様死亡時）'!F6="","",'CF表（奥様死亡時）'!F6) | G6: =IF('CF表（奥様死亡時）'!G6="","",'CF表（奥様死亡時）'!G6) | H6: =IF('CF表（奥様死亡時）'!H6="","",'CF表（奥様死亡時）'!H6) | I6: =IF('CF表（奥様死亡時）'!I6="","",'CF表（奥様死亡時）'!I6) | ... CW6: =IF('CF表（奥様死亡時）'!CW6="","",'CF表（奥様死亡時）'!CW6)
A7: 子2年齢 | B7: =IF('CF表（奥様死亡時）'!B7="","",'CF表（奥様死亡時）'!B7) | C7: =IF('CF表（奥様死亡時）'!C7="","",'CF表（奥様死亡時）'!C7) | D7: =IF('CF表（奥様死亡時）'!D7="","",'CF表（奥様死亡時）'!D7) | E7: =IF('CF表（奥様死亡時）'!E7="","",'CF表（奥様死亡時）'!E7) | F7: =IF('CF表（奥様死亡時）'!F7="","",'CF表（奥様死亡時）'!F7) | G7: =IF('CF表（奥様死亡時）'!G7="","",'CF表（奥様死亡時）'!G7) | H7: =IF('CF表（奥様死亡時）'!H7="","",'CF表（奥様死亡時）'!H7) | I7: =IF('CF表（奥様死亡時）'!I7="","",'CF表（奥様死亡時）'!I7) | ... CW7: =IF('CF表（奥様死亡時）'!CW7="","",'CF表（奥様死亡時）'!CW7)
A8: 子3年齢 | B8: =IF('CF表（奥様死亡時）'!B8="","",'CF表（奥様死亡時）'!B8) | C8: =IF('CF表（奥様死亡時）'!C8="","",'CF表（奥様死亡時）'!C8) | D8: =IF('CF表（奥様死亡時）'!D8="","",'CF表（奥様死亡時）'!D8) | E8: =IF('CF表（奥様死亡時）'!E8="","",'CF表（奥様死亡時）'!E8) | F8: =IF('CF表（奥様死亡時）'!F8="","",'CF表（奥様死亡時）'!F8) | G8: =IF('CF表（奥様死亡時）'!G8="","",'CF表（奥様死亡時）'!G8) | H8: =IF('CF表（奥様死亡時）'!H8="","",'CF表（奥様死亡時）'!H8) | I8: =IF('CF表（奥様死亡時）'!I8="","",'CF表（奥様死亡時）'!I8) | ... CW8: =IF('CF表（奥様死亡時）'!CW8="","",'CF表（奥様死亡時）'!CW8)
A9: 家族年齢
A10: ご主人様収入 | B10: =IF('CF表（奥様死亡時）'!B$3="","",'CF表（奥様死亡時）'!B10/10000) | C10: =IF('CF表（奥様死亡時）'!C$3="","",'CF表（奥様死亡時）'!C10/10000) | D10: =IF('CF表（奥様死亡時）'!D$3="","",'CF表（奥様死亡時）'!D10/10000) | E10: =IF('CF表（奥様死亡時）'!E$3="","",'CF表（奥様死亡時）'!E10/10000) | F10: =IF('CF表（奥様死亡時）'!F$3="","",'CF表（奥様死亡時）'!F10/10000) | G10: =IF('CF表（奥様死亡時）'!G$3="","",'CF表（奥様死亡時）'!G10/10000) | H10: =IF('CF表（奥様死亡時）'!H$3="","",'CF表（奥様死亡時）'!H10/10000) | I10: =IF('CF表（奥様死亡時）'!I$3="","",'CF表（奥様死亡時）'!I10/10000) | ... CW10: =IF('CF表（奥様死亡時）'!CW$3="","",'CF表（奥様死亡時）'!CW10/10000)
A11: 奥様収入 | B11: =IF('CF表（奥様死亡時）'!B$3="","",'CF表（奥様死亡時）'!B11/10000) | C11: =IF('CF表（奥様死亡時）'!C$3="","",'CF表（奥様死亡時）'!C11/10000) | D11: =IF('CF表（奥様死亡時）'!D$3="","",'CF表（奥様死亡時）'!D11/10000) | E11: =IF('CF表（奥様死亡時）'!E$3="","",'CF表（奥様死亡時）'!E11/10000) | F11: =IF('CF表（奥様死亡時）'!F$3="","",'CF表（奥様死亡時）'!F11/10000) | G11: =IF('CF表（奥様死亡時）'!G$3="","",'CF表（奥様死亡時）'!G11/10000) | H11: =IF('CF表（奥様死亡時）'!H$3="","",'CF表（奥様死亡時）'!H11/10000) | I11: =IF('CF表（奥様死亡時）'!I$3="","",'CF表（奥様死亡時）'!I11/10000) | ... CW11: =IF('CF表（奥様死亡時）'!CW$3="","",'CF表（奥様死亡時）'!CW11/10000)
A12: 児童手当 | B12: =IF('CF表（奥様死亡時）'!B$3="","",'CF表（奥様死亡時）'!B12/10000) | C12: =IF('CF表（奥様死亡時）'!C$3="","",'CF表（奥様死亡時）'!C12/10000) | D12: =IF('CF表（奥様死亡時）'!D$3="","",'CF表（奥様死亡時）'!D12/10000) | E12: =IF('CF表（奥様死亡時）'!E$3="","",'CF表（奥様死亡時）'!E12/10000) | F12: =IF('CF表（奥様死亡時）'!F$3="","",'CF表（奥様死亡時）'!F12/10000) | G12: =IF('CF表（奥様死亡時）'!G$3="","",'CF表（奥様死亡時）'!G12/10000) | H12: =IF('CF表（奥様死亡時）'!H$3="","",'CF表（奥様死亡時）'!H12/10000) | I12: =IF('CF表（奥様死亡時）'!I$3="","",'CF表（奥様死亡時）'!I12/10000) | ... CW12: =IF('CF表（奥様死亡時）'!CW$3="","",'CF表（奥様死亡時）'!CW12/10000)
A13: その他収入 | B13: =IF('CF表（奥様死亡時）'!B$3="","",'CF表（奥様死亡時）'!B13/10000) | C13: =IF('CF表（奥様死亡時）'!C$3="","",'CF表（奥様死亡時）'!C13/10000) | D13: =IF('CF表（奥様死亡時）'!D$3="","",'CF表（奥様死亡時）'!D13/10000) | E13: =IF('CF表（奥様死亡時）'!E$3="","",'CF表（奥様死亡時）'!E13/10000) | F13: =IF('CF表（奥様死亡時）'!F$3="","",'CF表（奥様死亡時）'!F13/10000) | G13: =IF('CF表（奥様死亡時）'!G$3="","",'CF表（奥様死亡時）'!G13/10000) | H13: =IF('CF表（奥様死亡時）'!H$3="","",'CF表（奥様死亡時）'!H13/10000) | I13: =IF('CF表（奥様死亡時）'!I$3="","",'CF表（奥様死亡時）'!I13/10000) | ... CW13: =IF('CF表（奥様死亡時）'!CW$3="","",'CF表（奥様死亡時）'!CW13/10000)
A14: ご主人様退職金 | B14: =IF('CF表（奥様死亡時）'!B$3="","",'CF表（奥様死亡時）'!B14/10000) | C14: =IF('CF表（奥様死亡時）'!C$3="","",'CF表（奥様死亡時）'!C14/10000) | D14: =IF('CF表（奥様死亡時）'!D$3="","",'CF表（奥様死亡時）'!D14/10000) | E14: =IF('CF表（奥様死亡時）'!E$3="","",'CF表（奥様死亡時）'!E14/10000) | F14: =IF('CF表（奥様死亡時）'!F$3="","",'CF表（奥様死亡時）'!F14/10000) | G14: =IF('CF表（奥様死亡時）'!G$3="","",'CF表（奥様死亡時）'!G14/10000) | H14: =IF('CF表（奥様死亡時）'!H$3="","",'CF表（奥様死亡時）'!H14/10000) | I14: =IF('CF表（奥様死亡時）'!I$3="","",'CF表（奥様死亡時）'!I14/10000) | ... CW14: =IF('CF表（奥様死亡時）'!CW$3="","",'CF表（奥様死亡時）'!CW14/10000)
A15: 奥様退職金 | B15: =IF('CF表（奥様死亡時）'!B$3="","",'CF表（奥様死亡時）'!B15/10000) | C15: =IF('CF表（奥様死亡時）'!C$3="","",'CF表（奥様死亡時）'!C15/10000) | D15: =IF('CF表（奥様死亡時）'!D$3="","",'CF表（奥様死亡時）'!D15/10000) | E15: =IF('CF表（奥様死亡時）'!E$3="","",'CF表（奥様死亡時）'!E15/10000) | F15: =IF('CF表（奥様死亡時）'!F$3="","",'CF表（奥様死亡時）'!F15/10000) | G15: =IF('CF表（奥様死亡時）'!G$3="","",'CF表（奥様死亡時）'!G15/10000) | H15: =IF('CF表（奥様死亡時）'!H$3="","",'CF表（奥様死亡時）'!H15/10000) | I15: =IF('CF表（奥様死亡時）'!I$3="","",'CF表（奥様死亡時）'!I15/10000) | ... CW15: =IF('CF表（奥様死亡時）'!CW$3="","",'CF表（奥様死亡時）'!CW15/10000)
A16: ご主人様年金収入 | B16: =IF('CF表（奥様死亡時）'!B$3="","",'CF表（奥様死亡時）'!B16/10000) | C16: =IF('CF表（奥様死亡時）'!C$3="","",'CF表（奥様死亡時）'!C16/10000) | D16: =IF('CF表（奥様死亡時）'!D$3="","",'CF表（奥様死亡時）'!D16/10000) | E16: =IF('CF表（奥様死亡時）'!E$3="","",'CF表（奥様死亡時）'!E16/10000) | F16: =IF('CF表（奥様死亡時）'!F$3="","",'CF表（奥様死亡時）'!F16/10000) | G16: =IF('CF表（奥様死亡時）'!G$3="","",'CF表（奥様死亡時）'!G16/10000) | H16: =IF('CF表（奥様死亡時）'!H$3="","",'CF表（奥様死亡時）'!H16/10000) | I16: =IF('CF表（奥様死亡時）'!I$3="","",'CF表（奥様死亡時）'!I16/10000) | ... CW16: =IF('CF表（奥様死亡時）'!CW$3="","",'CF表（奥様死亡時）'!CW16/10000)
A17: 奥様年金収入 | B17: =IF('CF表（奥様死亡時）'!B$3="","",'CF表（奥様死亡時）'!B17/10000) | C17: =IF('CF表（奥様死亡時）'!C$3="","",'CF表（奥様死亡時）'!C17/10000) | D17: =IF('CF表（奥様死亡時）'!D$3="","",'CF表（奥様死亡時）'!D17/10000) | E17: =IF('CF表（奥様死亡時）'!E$3="","",'CF表（奥様死亡時）'!E17/10000) | F17: =IF('CF表（奥様死亡時）'!F$3="","",'CF表（奥様死亡時）'!F17/10000) | G17: =IF('CF表（奥様死亡時）'!G$3="","",'CF表（奥様死亡時）'!G17/10000) | H17: =IF('CF表（奥様死亡時）'!H$3="","",'CF表（奥様死亡時）'!H17/10000) | I17: =IF('CF表（奥様死亡時）'!I$3="","",'CF表（奥様死亡時）'!I17/10000) | ... CW17: =IF('CF表（奥様死亡時）'!CW$3="","",'CF表（奥様死亡時）'!CW17/10000)
A18: 世帯収入合計 | B18: =IF('CF表（奥様死亡時）'!B$3="","",'CF表（奥様死亡時）'!B18/10000) | C18: =IF('CF表（奥様死亡時）'!C$3="","",'CF表（奥様死亡時）'!C18/10000) | D18: =IF('CF表（奥様死亡時）'!D$3="","",'CF表（奥様死亡時）'!D18/10000) | E18: =IF('CF表（奥様死亡時）'!E$3="","",'CF表（奥様死亡時）'!E18/10000) | F18: =IF('CF表（奥様死亡時）'!F$3="","",'CF表（奥様死亡時）'!F18/10000) | G18: =IF('CF表（奥様死亡時）'!G$3="","",'CF表（奥様死亡時）'!G18/10000) | H18: =IF('CF表（奥様死亡時）'!H$3="","",'CF表（奥様死亡時）'!H18/10000) | I18: =IF('CF表（奥様死亡時）'!I$3="","",'CF表（奥様死亡時）'!I18/10000) | ... CW18: =IF('CF表（奥様死亡時）'!CW$3="","",'CF表（奥様死亡時）'!CW18/10000)
A19: 収入
A20: 基本生活費 | B20: =IF('CF表（奥様死亡時）'!B$3="","",'CF表（奥様死亡時）'!B20/10000) | C20: =IF('CF表（奥様死亡時）'!C$3="","",'CF表（奥様死亡時）'!C20/10000) | D20: =IF('CF表（奥様死亡時）'!D$3="","",'CF表（奥様死亡時）'!D20/10000) | E20: =IF('CF表（奥様死亡時）'!E$3="","",'CF表（奥様死亡時）'!E20/10000) | F20: =IF('CF表（奥様死亡時）'!F$3="","",'CF表（奥様死亡時）'!F20/10000) | G20: =IF('CF表（奥様死亡時）'!G$3="","",'CF表（奥様死亡時）'!G20/10000) | H20: =IF('CF表（奥様死亡時）'!H$3="","",'CF表（奥様死亡時）'!H20/10000) | I20: =IF('CF表（奥様死亡時）'!I$3="","",'CF表（奥様死亡時）'!I20/10000) | ... CW20: =IF('CF表（奥様死亡時）'!CW$3="","",'CF表（奥様死亡時）'!CW20/10000)
A21: 住居費 | B21: =IF('CF表（奥様死亡時）'!B$3="","",'CF表（奥様死亡時）'!B21/10000) | C21: =IF('CF表（奥様死亡時）'!C$3="","",'CF表（奥様死亡時）'!C21/10000) | D21: =IF('CF表（奥様死亡時）'!D$3="","",'CF表（奥様死亡時）'!D21/10000) | E21: =IF('CF表（奥様死亡時）'!E$3="","",'CF表（奥様死亡時）'!E21/10000) | F21: =IF('CF表（奥様死亡時）'!F$3="","",'CF表（奥様死亡時）'!F21/10000) | G21: =IF('CF表（奥様死亡時）'!G$3="","",'CF表（奥様死亡時）'!G21/10000) | H21: =IF('CF表（奥様死亡時）'!H$3="","",'CF表（奥様死亡時）'!H21/10000) | I21: =IF('CF表（奥様死亡時）'!I$3="","",'CF表（奥様死亡時）'!I21/10000) | ... CW21: =IF('CF表（奥様死亡時）'!CW$3="","",'CF表（奥様死亡時）'!CW21/10000)
A22: 終身系保険料 | B22: =IF('CF表（奥様死亡時）'!B$3="","",'CF表（奥様死亡時）'!B22/10000) | C22: =IF('CF表（奥様死亡時）'!C$3="","",'CF表（奥様死亡時）'!C22/10000) | D22: =IF('CF表（奥様死亡時）'!D$3="","",'CF表（奥様死亡時）'!D22/10000) | E22: =IF('CF表（奥様死亡時）'!E$3="","",'CF表（奥様死亡時）'!E22/10000) | F22: =IF('CF表（奥様死亡時）'!F$3="","",'CF表（奥様死亡時）'!F22/10000) | G22: =IF('CF表（奥様死亡時）'!G$3="","",'CF表（奥様死亡時）'!G22/10000) | H22: =IF('CF表（奥様死亡時）'!H$3="","",'CF表（奥様死亡時）'!H22/10000) | I22: =IF('CF表（奥様死亡時）'!I$3="","",'CF表（奥様死亡時）'!I22/10000) | ... CW22: =IF('CF表（奥様死亡時）'!CW$3="","",'CF表（奥様死亡時）'!CW22/10000)
A23: 定期系保険料 | B23: =IF('CF表（奥様死亡時）'!B$3="","",'CF表（奥様死亡時）'!B23/10000) | C23: =IF('CF表（奥様死亡時）'!C$3="","",'CF表（奥様死亡時）'!C23/10000) | D23: =IF('CF表（奥様死亡時）'!D$3="","",'CF表（奥様死亡時）'!D23/10000) | E23: =IF('CF表（奥様死亡時）'!E$3="","",'CF表（奥様死亡時）'!E23/10000) | F23: =IF('CF表（奥様死亡時）'!F$3="","",'CF表（奥様死亡時）'!F23/10000) | G23: =IF('CF表（奥様死亡時）'!G$3="","",'CF表（奥様死亡時）'!G23/10000) | H23: =IF('CF表（奥様死亡時）'!H$3="","",'CF表（奥様死亡時）'!H23/10000) | I23: =IF('CF表（奥様死亡時）'!I$3="","",'CF表（奥様死亡時）'!I23/10000) | ... CW23: =IF('CF表（奥様死亡時）'!CW$3="","",'CF表（奥様死亡時）'!CW23/10000)
A24: 教育費 | B24: =IF('CF表（奥様死亡時）'!B$3="","",'CF表（奥様死亡時）'!B24/10000) | C24: =IF('CF表（奥様死亡時）'!C$3="","",'CF表（奥様死亡時）'!C24/10000) | D24: =IF('CF表（奥様死亡時）'!D$3="","",'CF表（奥様死亡時）'!D24/10000) | E24: =IF('CF表（奥様死亡時）'!E$3="","",'CF表（奥様死亡時）'!E24/10000) | F24: =IF('CF表（奥様死亡時）'!F$3="","",'CF表（奥様死亡時）'!F24/10000) | G24: =IF('CF表（奥様死亡時）'!G$3="","",'CF表（奥様死亡時）'!G24/10000) | H24: =IF('CF表（奥様死亡時）'!H$3="","",'CF表（奥様死亡時）'!H24/10000) | I24: =IF('CF表（奥様死亡時）'!I$3="","",'CF表（奥様死亡時）'!I24/10000) | ... CW24: =IF('CF表（奥様死亡時）'!CW$3="","",'CF表（奥様死亡時）'!CW24/10000)
A25: 車関連費 | B25: =IF('CF表（奥様死亡時）'!B$3="","",'CF表（奥様死亡時）'!B25/10000) | C25: =IF('CF表（奥様死亡時）'!C$3="","",'CF表（奥様死亡時）'!C25/10000) | D25: =IF('CF表（奥様死亡時）'!D$3="","",'CF表（奥様死亡時）'!D25/10000) | E25: =IF('CF表（奥様死亡時）'!E$3="","",'CF表（奥様死亡時）'!E25/10000) | F25: =IF('CF表（奥様死亡時）'!F$3="","",'CF表（奥様死亡時）'!F25/10000) | G25: =IF('CF表（奥様死亡時）'!G$3="","",'CF表（奥様死亡時）'!G25/10000) | H25: =IF('CF表（奥様死亡時）'!H$3="","",'CF表（奥様死亡時）'!H25/10000) | I25: =IF('CF表（奥様死亡時）'!I$3="","",'CF表（奥様死亡時）'!I25/10000) | ... CW25: =IF('CF表（奥様死亡時）'!CW$3="","",'CF表（奥様死亡時）'!CW25/10000)
A26: その他支出 | B26: =IF('CF表（奥様死亡時）'!B$3="","",'CF表（奥様死亡時）'!B26/10000) | C26: =IF('CF表（奥様死亡時）'!C$3="","",'CF表（奥様死亡時）'!C26/10000) | D26: =IF('CF表（奥様死亡時）'!D$3="","",'CF表（奥様死亡時）'!D26/10000) | E26: =IF('CF表（奥様死亡時）'!E$3="","",'CF表（奥様死亡時）'!E26/10000) | F26: =IF('CF表（奥様死亡時）'!F$3="","",'CF表（奥様死亡時）'!F26/10000) | G26: =IF('CF表（奥様死亡時）'!G$3="","",'CF表（奥様死亡時）'!G26/10000) | H26: =IF('CF表（奥様死亡時）'!H$3="","",'CF表（奥様死亡時）'!H26/10000) | I26: =IF('CF表（奥様死亡時）'!I$3="","",'CF表（奥様死亡時）'!I26/10000) | ... CW26: =IF('CF表（奥様死亡時）'!CW$3="","",'CF表（奥様死亡時）'!CW26/10000)
A27: 一時支出 | B27: =IF('CF表（奥様死亡時）'!B$3="","",'CF表（奥様死亡時）'!B27/10000) | C27: =IF('CF表（奥様死亡時）'!C$3="","",'CF表（奥様死亡時）'!C27/10000) | D27: =IF('CF表（奥様死亡時）'!D$3="","",'CF表（奥様死亡時）'!D27/10000) | E27: =IF('CF表（奥様死亡時）'!E$3="","",'CF表（奥様死亡時）'!E27/10000) | F27: =IF('CF表（奥様死亡時）'!F$3="","",'CF表（奥様死亡時）'!F27/10000) | G27: =IF('CF表（奥様死亡時）'!G$3="","",'CF表（奥様死亡時）'!G27/10000) | H27: =IF('CF表（奥様死亡時）'!H$3="","",'CF表（奥様死亡時）'!H27/10000) | I27: =IF('CF表（奥様死亡時）'!I$3="","",'CF表（奥様死亡時）'!I27/10000) | ... CW27: =IF('CF表（奥様死亡時）'!CW$3="","",'CF表（奥様死亡時）'!CW27/10000)
A28: 支出合計 | B28: =IF('CF表（奥様死亡時）'!B$3="","",'CF表（奥様死亡時）'!B28/10000) | C28: =IF('CF表（奥様死亡時）'!C$3="","",'CF表（奥様死亡時）'!C28/10000) | D28: =IF('CF表（奥様死亡時）'!D$3="","",'CF表（奥様死亡時）'!D28/10000) | E28: =IF('CF表（奥様死亡時）'!E$3="","",'CF表（奥様死亡時）'!E28/10000) | F28: =IF('CF表（奥様死亡時）'!F$3="","",'CF表（奥様死亡時）'!F28/10000) | G28: =IF('CF表（奥様死亡時）'!G$3="","",'CF表（奥様死亡時）'!G28/10000) | H28: =IF('CF表（奥様死亡時）'!H$3="","",'CF表（奥様死亡時）'!H28/10000) | I28: =IF('CF表（奥様死亡時）'!I$3="","",'CF表（奥様死亡時）'!I28/10000) | ... CW28: =IF('CF表（奥様死亡時）'!CW$3="","",'CF表（奥様死亡時）'!CW28/10000)
A29: 収支・資産 | B29: =IF('CF表（奥様死亡時）'!B$3="","",'CF表（奥様死亡時）'!B29/10000) | C29: =IF('CF表（奥様死亡時）'!C$3="","",'CF表（奥様死亡時）'!C29/10000) | D29: =IF('CF表（奥様死亡時）'!D$3="","",'CF表（奥様死亡時）'!D29/10000) | E29: =IF('CF表（奥様死亡時）'!E$3="","",'CF表（奥様死亡時）'!E29/10000) | F29: =IF('CF表（奥様死亡時）'!F$3="","",'CF表（奥様死亡時）'!F29/10000) | G29: =IF('CF表（奥様死亡時）'!G$3="","",'CF表（奥様死亡時）'!G29/10000) | H29: =IF('CF表（奥様死亡時）'!H$3="","",'CF表（奥様死亡時）'!H29/10000) | I29: =IF('CF表（奥様死亡時）'!I$3="","",'CF表（奥様死亡時）'!I29/10000) | ... CW29: =IF('CF表（奥様死亡時）'!CW$3="","",'CF表（奥様死亡時）'!CW29/10000)
A30: 年間収支 | B30: =IF('CF表（奥様死亡時）'!B$3="","",'CF表（奥様死亡時）'!B30/10000) | C30: =IF('CF表（奥様死亡時）'!C$3="","",'CF表（奥様死亡時）'!C30/10000) | D30: =IF('CF表（奥様死亡時）'!D$3="","",'CF表（奥様死亡時）'!D30/10000) | E30: =IF('CF表（奥様死亡時）'!E$3="","",'CF表（奥様死亡時）'!E30/10000) | F30: =IF('CF表（奥様死亡時）'!F$3="","",'CF表（奥様死亡時）'!F30/10000) | G30: =IF('CF表（奥様死亡時）'!G$3="","",'CF表（奥様死亡時）'!G30/10000) | H30: =IF('CF表（奥様死亡時）'!H$3="","",'CF表（奥様死亡時）'!H30/10000) | I30: =IF('CF表（奥様死亡時）'!I$3="","",'CF表（奥様死亡時）'!I30/10000) | ... CW30: =IF('CF表（奥様死亡時）'!CW$3="","",'CF表（奥様死亡時）'!CW30/10000)
A31: 預貯金残高 | B31: =IF('CF表（奥様死亡時）'!B$3="","",'CF表（奥様死亡時）'!B31/10000) | C31: =IF('CF表（奥様死亡時）'!C$3="","",'CF表（奥様死亡時）'!C31/10000) | D31: =IF('CF表（奥様死亡時）'!D$3="","",'CF表（奥様死亡時）'!D31/10000) | E31: =IF('CF表（奥様死亡時）'!E$3="","",'CF表（奥様死亡時）'!E31/10000) | F31: =IF('CF表（奥様死亡時）'!F$3="","",'CF表（奥様死亡時）'!F31/10000) | G31: =IF('CF表（奥様死亡時）'!G$3="","",'CF表（奥様死亡時）'!G31/10000) | H31: =IF('CF表（奥様死亡時）'!H$3="","",'CF表（奥様死亡時）'!H31/10000) | I31: =IF('CF表（奥様死亡時）'!I$3="","",'CF表（奥様死亡時）'!I31/10000) | ... CW31: =IF('CF表（奥様死亡時）'!CW$3="","",'CF表（奥様死亡時）'!CW31/10000)
... A45: 負債合計（参考） | B45: =IF('CF表（奥様死亡時）'!B$3="","",'CF表（奥様死亡時）'!B45/10000) | C45: =IF('CF表（奥様死亡時）'!C$3="","",'CF表（奥様死亡時）'!C45/10000) | D45: =IF('CF表（奥様死亡時）'!D$3="","",'CF表（奥様死亡時）'!D45/10000) | E45: =IF('CF表（奥様死亡時）'!E$3="","",'CF表（奥様死亡時）'!E45/10000) | F45: =IF('CF表（奥様死亡時）'!F$3="","",'CF表（奥様死亡時）'!F45/10000) | G45: =IF('CF表（奥様死亡時）'!G$3="","",'CF表（奥様死亡時）'!G45/10000) | H45: =IF('CF表（奥様死亡時）'!H$3="","",'CF表（奥様死亡時）'!H45/10000) | I45: =IF('CF表（奥様死亡時）'!I$3="","",'CF表（奥様死亡時）'!I45/10000) | ... CW45: =IF('CF表（奥様死亡時）'!CW$3="","",'CF表（奥様死亡時）'!CW45/10000)

Sheet リスク判定
A1: リスク判定
A3: テーマ | B3: 判定 | C3: 今見る数値
A4: 死亡時 | B4: =C11 | C4: =TEXT(C12,"#,##0")&" 円/年不足" | D4: =IF(B4="安心","今すぐの大きな不足は見えにくい状態です。",IF(B4="注意","一度点検しておきたい状態です。","直近不足または将来の資産不足が見えており、優先して備えを見直したい状態です。"))
A5: 働けない時 | B5: =C17 | C5: =TEXT(C18,"#,##0")&" 円/月不足" | D5: =IF(B5="安心","現状でも一定の備えがある状態です。",IF(B5="注意","働けない時の家計影響を確認したい状態です。","追加の備えを優先して検討したい状態です。"))
A6: 老後 | B6: =C23 | C6: =TEXT(C24,"#,##0")&" 円/年不足" | D6: =IF(B6="安心","現状前提では大きな不足が見えにくい状態です。",IF(B6="注意","積立や支出バランスを見直したい状態です。","今のうちから老後対策を強めたい状態です。"))
A8: 死亡時リスク
A9: 区分 | B9: 項目 | C9: 値
A10: 死亡時
B11: 判定結果 | C11: =IF(OR(MIN('CF表（ご主人様死亡時・万円表示）'!B35:CW35)<0,MIN('CF表（奥様死亡時・万円表示）'!B35:CW35)<0),"要対策",IF(C12=0,"安心",IF(C12<=500000,"注意","要対策")))
B12: 年間平均不足額 | C12: =ROUND(MAX(IFERROR(AVERAGE(FILTER(-'CF表（ご主人様死亡時・万円表示）'!B30:CW30,'CF表（ご主人様死亡時・万円表示）'!B30:CW30<0)),0)*10000,IFERROR(AVERAGE(FILTER(-'CF表（奥様死亡時・万円表示）'!B30:CW30,'CF表（奥様死亡時・万円表示）'!B30:CW30<0)),0)*10000),0)
B13: 必要保障額 | C13: =ROUND(C12*MAX(IF(N(CF表!B6)>0,MAX(22-N(CF表!B6),0),0),IF(N(CF表!B7)>0,MAX(22-N(CF表!B7),0),0),IF(N(CF表!B8)>0,MAX(22-N(CF表!B8),0),0),1),0)
B14: 現在の保障との差額 | C14: =MAX(0,C13-C52)
B15: 次の一手 | C15: =IF(OR(MIN('CF表（ご主人様死亡時・万円表示）'!B35:CW35)<0,MIN('CF表（奥様死亡時・万円表示）'!B35:CW35)<0),"直近だけでなく長期の資産不足が見えているため、年間平均不足額も踏まえて保障額・家計配分・備え方を優先して点検したいです。",IF(C14=0,"現在の保障で大枠はカバーできる可能性があります。","年間平均不足額を踏まえて、必要保障額・保険期間・遺族年金前提を点検したいです。"))
A16: 働けない時のリスク
A17: 働けない時 | B17: 判定結果 | C17: =IF(C18=0,"安心",IF(C18<=50000,"注意","要対策"))
B18: 毎月不足額 | C18: =MAX(0,MAX((N(CF表!B28)/12)-(N(入力データ!$C$30)+N(入力データ!$C$33)/12+N(入力データ!$C$34)+N(入力データ!$C$35)+N(前提条件!$C$55)),(N(CF表!B28)/12)-(N(入力データ!$C$29)+N(入力データ!$C$32)/12+N(入力データ!$C$34)+N(入力データ!$C$35)+N(前提条件!$C$56))))
B19: 必要備え額（65歳まで） | C19: =C18*12*IF(((N(CF表!B28)/12)-(N(入力データ!$C$30)+N(入力データ!$C$33)/12+N(入力データ!$C$34)+N(入力データ!$C$35)+N(前提条件!$C$55)))>=((N(CF表!B28)/12)-(N(入力データ!$C$29)+N(入力データ!$C$32)/12+N(入力データ!$C$34)+N(入力データ!$C$35)+N(前提条件!$C$56))),MAX(65-N(CF表!B4),0),MAX(65-N(CF表!B5),0))
B20: 現在の保障との差額 | C20: =MAX(0,C19-(N(C53)*12*IF(((N(CF表!B28)/12)-(N(入力データ!$C$30)+N(入力データ!$C$33)/12+N(入力データ!$C$34)+N(入力データ!$C$35)+N(前提条件!$C$55)))>=((N(CF表!B28)/12)-(N(入力データ!$C$29)+N(入力データ!$C$32)/12+N(入力データ!$C$34)+N(入力データ!$C$35)+N(前提条件!$C$56))),MAX(65-N(CF表!B4),0),MAX(65-N(CF表!B5),0))))
B21: 次の一手 | C21: =IF(C20=0,"今ある保障や資産で一定の対応余地があります。","就業不能保険・生活防衛資金・固定費の見直しを優先したいです。")
A22: 老後リスク
A23: 老後 | B23: 判定結果 | C23: =IF(C24=0,"安心",IF(C24<=1000000,"注意","要対策"))
B24: 年間不足見込額 | C24: =IFERROR(MAX(0,-MIN(filter(CF表!B30:CW30,(CF表!B4:CW4>=入力データ!$C$111)*(CF表!B5:CW5>=入力データ!$C$111)))),0)
B25: 不足が出始める年齢 | C25: =IF(C24=0,"不足なし",INDEX(filter(CF表!B4:CW4,(CF表!B4:CW4>=入力データ!$C$111)*(CF表!B5:CW5>=入力データ!$C$111)*(CF表!B30:CW30<0)),1)&"歳")
B26: 65歳時点の必要準備額 | C26: =IFERROR(SUM(filter(-CF表!B30:CW30,(CF表!B4:CW4>=65)*(CF表!B5:CW5>=65)*(CF表!B30:CW30<0))),0)
B27: 次の一手 | C27: =IF(C26=0,"現状前提では老後資金の準備余地があります。","積立額・退職時期・老後生活費の前提を一度見直したいです。")
B52: 現在死亡保障総額 | C52: =SUM(入力データ!O5:O20) | D52: 死亡保障の集計値（保険情報から入力ベース）
B53: 現在就業不能保障月額 | C53: =SUM(入力データ!P5:P20)

Sheet グラフ
A1: グラフ
A3: このシートで見ること
A4: ① 通常時・ご主人様死亡時・奥様死亡時の資産推移を比較 ② どのケースで資産が減りやすいかを確認 ③ 面談で優先して整理すべき論点を見つける
A7: ① 3つのケースの保有資産推移
A8: 見どころ：通常時と比べて、ご主人様死亡時・奥様死亡時でどの程度差が出るかを確認します。右肩下がりが続く場合は、保障や家計配分の見直し優先度が高いサインです。
A42: グラフ用データ（Googleスプレッドシートで壊れにくい表）
A43: 下の表をそのまま選択して「挿入 → グラフ」で折れ線グラフを作れます。 PDF用に整える時は、この表を元にCanvaへ反映します。
A46: 年 | B46: 通常時 保有資産合計 | C46: ご主人様死亡時 保有資産合計 | D46: 奥様死亡時 保有資産合計
A47: ='CF表（万円表示）'!B3 | B47: ='CF表（万円表示）'!B35 | C47: ='CF表（ご主人様死亡時・万円表示）'!B35 | D47: ='CF表（奥様死亡時・万円表示）'!B35
A48: ='CF表（万円表示）'!C3 | B48: ='CF表（万円表示）'!C35 | C48: ='CF表（ご主人様死亡時・万円表示）'!C35 | D48: ='CF表（奥様死亡時・万円表示）'!C35
A49: ='CF表（万円表示）'!D3 | B49: ='CF表（万円表示）'!D35 | C49: ='CF表（ご主人様死亡時・万円表示）'!D35 | D49: ='CF表（奥様死亡時・万円表示）'!D35
A50: ='CF表（万円表示）'!E3 | B50: ='CF表（万円表示）'!E35 | C50: ='CF表（ご主人様死亡時・万円表示）'!E35 | D50: ='CF表（奥様死亡時・万円表示）'!E35
A51: ='CF表（万円表示）'!F3 | B51: ='CF表（万円表示）'!F35 | C51: ='CF表（ご主人様死亡時・万円表示）'!F35 | D51: ='CF表（奥様死亡時・万円表示）'!F35
A52: ='CF表（万円表示）'!G3 | B52: ='CF表（万円表示）'!G35 | C52: ='CF表（ご主人様死亡時・万円表示）'!G35 | D52: ='CF表（奥様死亡時・万円表示）'!G35
A53: ='CF表（万円表示）'!H3 | B53: ='CF表（万円表示）'!H35 | C53: ='CF表（ご主人様死亡時・万円表示）'!H35 | D53: ='CF表（奥様死亡時・万円表示）'!H35
A54: ='CF表（万円表示）'!I3 | B54: ='CF表（万円表示）'!I35 | C54: ='CF表（ご主人様死亡時・万円表示）'!I35 | D54: ='CF表（奥様死亡時・万円表示）'!I35
A55: ='CF表（万円表示）'!J3 | B55: ='CF表（万円表示）'!J35 | C55: ='CF表（ご主人様死亡時・万円表示）'!J35 | D55: ='CF表（奥様死亡時・万円表示）'!J35
A56: ='CF表（万円表示）'!K3 | B56: ='CF表（万円表示）'!K35 | C56: ='CF表（ご主人様死亡時・万円表示）'!K35 | D56: ='CF表（奥様死亡時・万円表示）'!K35
A57: ='CF表（万円表示）'!L3 | B57: ='CF表（万円表示）'!L35 | C57: ='CF表（ご主人様死亡時・万円表示）'!L35 | D57: ='CF表（奥様死亡時・万円表示）'!L35
A58: ='CF表（万円表示）'!M3 | B58: ='CF表（万円表示）'!M35 | C58: ='CF表（ご主人様死亡時・万円表示）'!M35 | D58: ='CF表（奥様死亡時・万円表示）'!M35
A59: ='CF表（万円表示）'!N3 | B59: ='CF表（万円表示）'!N35 | C59: ='CF表（ご主人様死亡時・万円表示）'!N35 | D59: ='CF表（奥様死亡時・万円表示）'!N35
A60: ='CF表（万円表示）'!O3 | B60: ='CF表（万円表示）'!O35 | C60: ='CF表（ご主人様死亡時・万円表示）'!O35 | D60: ='CF表（奥様死亡時・万円表示）'!O35
A61: ='CF表（万円表示）'!P3 | B61: ='CF表（万円表示）'!P35 | C61: ='CF表（ご主人様死亡時・万円表示）'!P35 | D61: ='CF表（奥様死亡時・万円表示）'!P35
A62: ='CF表（万円表示）'!Q3 | B62: ='CF表（万円表示）'!Q35 | C62: ='CF表（ご主人様死亡時・万円表示）'!Q35 | D62: ='CF表（奥様死亡時・万円表示）'!Q35
A63: ='CF表（万円表示）'!R3 | B63: ='CF表（万円表示）'!R35 | C63: ='CF表（ご主人様死亡時・万円表示）'!R35 | D63: ='CF表（奥様死亡時・万円表示）'!R35
A64: ='CF表（万円表示）'!S3 | B64: ='CF表（万円表示）'!S35 | C64: ='CF表（ご主人様死亡時・万円表示）'!S35 | D64: ='CF表（奥様死亡時・万円表示）'!S35
A65: ='CF表（万円表示）'!T3 | B65: ='CF表（万円表示）'!T35 | C65: ='CF表（ご主人様死亡時・万円表示）'!T35 | D65: ='CF表（奥様死亡時・万円表示）'!T35
A66: ='CF表（万円表示）'!U3 | B66: ='CF表（万円表示）'!U35 | C66: ='CF表（ご主人様死亡時・万円表示）'!U35 | D66: ='CF表（奥様死亡時・万円表示）'!U35
A67: ='CF表（万円表示）'!V3 | B67: ='CF表（万円表示）'!V35 | C67: ='CF表（ご主人様死亡時・万円表示）'!V35 | D67: ='CF表（奥様死亡時・万円表示）'!V35
A68: ='CF表（万円表示）'!W3 | B68: ='CF表（万円表示）'!W35 | C68: ='CF表（ご主人様死亡時・万円表示）'!W35 | D68: ='CF表（奥様死亡時・万円表示）'!W35
A69: ='CF表（万円表示）'!X3 | B69: ='CF表（万円表示）'!X35 | C69: ='CF表（ご主人様死亡時・万円表示）'!X35 | D69: ='CF表（奥様死亡時・万円表示）'!X35
A70: ='CF表（万円表示）'!Y3 | B70: ='CF表（万円表示）'!Y35 | C70: ='CF表（ご主人様死亡時・万円表示）'!Y35 | D70: ='CF表（奥様死亡時・万円表示）'!Y35
A71: ='CF表（万円表示）'!Z3 | B71: ='CF表（万円表示）'!Z35 | C71: ='CF表（ご主人様死亡時・万円表示）'!Z35 | D71: ='CF表（奥様死亡時・万円表示）'!Z35
A72: ='CF表（万円表示）'!AA3 | B72: ='CF表（万円表示）'!AA35 | C72: ='CF表（ご主人様死亡時・万円表示）'!AA35 | D72: ='CF表（奥様死亡時・万円表示）'!AA35
A73: ='CF表（万円表示）'!AB3 | B73: ='CF表（万円表示）'!AB35 | C73: ='CF表（ご主人様死亡時・万円表示）'!AB35 | D73: ='CF表（奥様死亡時・万円表示）'!AB35
A74: ='CF表（万円表示）'!AC3 | B74: ='CF表（万円表示）'!AC35 | C74: ='CF表（ご主人様死亡時・万円表示）'!AC35 | D74: ='CF表（奥様死亡時・万円表示）'!AC35
A75: ='CF表（万円表示）'!AD3 | B75: ='CF表（万円表示）'!AD35 | C75: ='CF表（ご主人様死亡時・万円表示）'!AD35 | D75: ='CF表（奥様死亡時・万円表示）'!AD35
A76: ='CF表（万円表示）'!AE3 | B76: ='CF表（万円表示）'!AE35 | C76: ='CF表（ご主人様死亡時・万円表示）'!AE35 | D76: ='CF表（奥様死亡時・万円表示）'!AE35
A77: ='CF表（万円表示）'!AF3 | B77: ='CF表（万円表示）'!AF35 | C77: ='CF表（ご主人様死亡時・万円表示）'!AF35 | D77: ='CF表（奥様死亡時・万円表示）'!AF35
A78: ='CF表（万円表示）'!AG3 | B78: ='CF表（万円表示）'!AG35 | C78: ='CF表（ご主人様死亡時・万円表示）'!AG35 | D78: ='CF表（奥様死亡時・万円表示）'!AG35
A79: ='CF表（万円表示）'!AH3 | B79: ='CF表（万円表示）'!AH35 | C79: ='CF表（ご主人様死亡時・万円表示）'!AH35 | D79: ='CF表（奥様死亡時・万円表示）'!AH35
A80: ='CF表（万円表示）'!AI3 | B80: ='CF表（万円表示）'!AI35 | C80: ='CF表（ご主人様死亡時・万円表示）'!AI35 | D80: ='CF表（奥様死亡時・万円表示）'!AI35
A81: ='CF表（万円表示）'!AJ3 | B81: ='CF表（万円表示）'!AJ35 | C81: ='CF表（ご主人様死亡時・万円表示）'!AJ35 | D81: ='CF表（奥様死亡時・万円表示）'!AJ35
A82: ='CF表（万円表示）'!AK3 | B82: ='CF表（万円表示）'!AK35 | C82: ='CF表（ご主人様死亡時・万円表示）'!AK35 | D82: ='CF表（奥様死亡時・万円表示）'!AK35
A83: ='CF表（万円表示）'!AL3 | B83: ='CF表（万円表示）'!AL35 | C83: ='CF表（ご主人様死亡時・万円表示）'!AL35 | D83: ='CF表（奥様死亡時・万円表示）'!AL35
A84: ='CF表（万円表示）'!AM3 | B84: ='CF表（万円表示）'!AM35 | C84: ='CF表（ご主人様死亡時・万円表示）'!AM35 | D84: ='CF表（奥様死亡時・万円表示）'!AM35
A85: ='CF表（万円表示）'!AN3 | B85: ='CF表（万円表示）'!AN35 | C85: ='CF表（ご主人様死亡時・万円表示）'!AN35 | D85: ='CF表（奥様死亡時・万円表示）'!AN35
A86: ='CF表（万円表示）'!AO3 | B86: ='CF表（万円表示）'!AO35 | C86: ='CF表（ご主人様死亡時・万円表示）'!AO35 | D86: ='CF表（奥様死亡時・万円表示）'!AO35
A87: ='CF表（万円表示）'!AP3 | B87: ='CF表（万円表示）'!AP35 | C87: ='CF表（ご主人様死亡時・万円表示）'!AP35 | D87: ='CF表（奥様死亡時・万円表示）'!AP35
A88: ='CF表（万円表示）'!AQ3 | B88: ='CF表（万円表示）'!AQ35 | C88: ='CF表（ご主人様死亡時・万円表示）'!AQ35 | D88: ='CF表（奥様死亡時・万円表示）'!AQ35
A89: ='CF表（万円表示）'!AR3 | B89: ='CF表（万円表示）'!AR35 | C89: ='CF表（ご主人様死亡時・万円表示）'!AR35 | D89: ='CF表（奥様死亡時・万円表示）'!AR35
A90: ='CF表（万円表示）'!AS3 | B90: ='CF表（万円表示）'!AS35 | C90: ='CF表（ご主人様死亡時・万円表示）'!AS35 | D90: ='CF表（奥様死亡時・万円表示）'!AS35
A91: ='CF表（万円表示）'!AT3 | B91: ='CF表（万円表示）'!AT35 | C91: ='CF表（ご主人様死亡時・万円表示）'!AT35 | D91: ='CF表（奥様死亡時・万円表示）'!AT35
A92: ='CF表（万円表示）'!AU3 | B92: ='CF表（万円表示）'!AU35 | C92: ='CF表（ご主人様死亡時・万円表示）'!AU35 | D92: ='CF表（奥様死亡時・万円表示）'!AU35
A93: ='CF表（万円表示）'!AV3 | B93: ='CF表（万円表示）'!AV35 | C93: ='CF表（ご主人様死亡時・万円表示）'!AV35 | D93: ='CF表（奥様死亡時・万円表示）'!AV35
A94: ='CF表（万円表示）'!AW3 | B94: ='CF表（万円表示）'!AW35 | C94: ='CF表（ご主人様死亡時・万円表示）'!AW35 | D94: ='CF表（奥様死亡時・万円表示）'!AW35
A95: ='CF表（万円表示）'!AX3 | B95: ='CF表（万円表示）'!AX35 | C95: ='CF表（ご主人様死亡時・万円表示）'!AX35 | D95: ='CF表（奥様死亡時・万円表示）'!AX35
A96: ='CF表（万円表示）'!AY3 | B96: ='CF表（万円表示）'!AY35 | C96: ='CF表（ご主人様死亡時・万円表示）'!AY35 | D96: ='CF表（奥様死亡時・万円表示）'!AY35
A97: ='CF表（万円表示）'!AZ3 | B97: ='CF表（万円表示）'!AZ35 | C97: ='CF表（ご主人様死亡時・万円表示）'!AZ35 | D97: ='CF表（奥様死亡時・万円表示）'!AZ35
A98: ='CF表（万円表示）'!BA3 | B98: ='CF表（万円表示）'!BA35 | C98: ='CF表（ご主人様死亡時・万円表示）'!BA35 | D98: ='CF表（奥様死亡時・万円表示）'!BA35
A99: ='CF表（万円表示）'!BB3 | B99: ='CF表（万円表示）'!BB35 | C99: ='CF表（ご主人様死亡時・万円表示）'!BB35 | D99: ='CF表（奥様死亡時・万円表示）'!BB35
A100: ='CF表（万円表示）'!BC3 | B100: ='CF表（万円表示）'!BC35 | C100: ='CF表（ご主人様死亡時・万円表示）'!BC35 | D100: ='CF表（奥様死亡時・万円表示）'!BC35
A101: ='CF表（万円表示）'!BD3 | B101: ='CF表（万円表示）'!BD35 | C101: ='CF表（ご主人様死亡時・万円表示）'!BD35 | D101: ='CF表（奥様死亡時・万円表示）'!BD35
A102: ='CF表（万円表示）'!BE3 | B102: ='CF表（万円表示）'!BE35 | C102: ='CF表（ご主人様死亡時・万円表示）'!BE35 | D102: ='CF表（奥様死亡時・万円表示）'!BE35
A103: ='CF表（万円表示）'!BF3 | B103: ='CF表（万円表示）'!BF35 | C103: ='CF表（ご主人様死亡時・万円表示）'!BF35 | D103: ='CF表（奥様死亡時・万円表示）'!BF35
A104: ='CF表（万円表示）'!BG3 | B104: ='CF表（万円表示）'!BG35 | C104: ='CF表（ご主人様死亡時・万円表示）'!BG35 | D104: ='CF表（奥様死亡時・万円表示）'!BG35
A105: ='CF表（万円表示）'!BH3 | B105: ='CF表（万円表示）'!BH35 | C105: ='CF表（ご主人様死亡時・万円表示）'!BH35 | D105: ='CF表（奥様死亡時・万円表示）'!BH35
A106: ='CF表（万円表示）'!BI3 | B106: ='CF表（万円表示）'!BI35 | C106: ='CF表（ご主人様死亡時・万円表示）'!BI35 | D106: ='CF表（奥様死亡時・万円表示）'!BI35
A107: ='CF表（万円表示）'!BJ3 | B107: ='CF表（万円表示）'!BJ35 | C107: ='CF表（ご主人様死亡時・万円表示）'!BJ35 | D107: ='CF表（奥様死亡時・万円表示）'!BJ35
A108: ='CF表（万円表示）'!BK3 | B108: ='CF表（万円表示）'!BK35 | C108: ='CF表（ご主人様死亡時・万円表示）'!BK35 | D108: ='CF表（奥様死亡時・万円表示）'!BK35
A109: ='CF表（万円表示）'!BL3 | B109: ='CF表（万円表示）'!BL35 | C109: ='CF表（ご主人様死亡時・万円表示）'!BL35 | D109: ='CF表（奥様死亡時・万円表示）'!BL35
A110: ='CF表（万円表示）'!BM3 | B110: ='CF表（万円表示）'!BM35 | C110: ='CF表（ご主人様死亡時・万円表示）'!BM35 | D110: ='CF表（奥様死亡時・万円表示）'!BM35
A111: ='CF表（万円表示）'!BN3 | B111: ='CF表（万円表示）'!BN35 | C111: ='CF表（ご主人様死亡時・万円表示）'!BN35 | D111: ='CF表（奥様死亡時・万円表示）'!BN35
A112: ='CF表（万円表示）'!BO3 | B112: ='CF表（万円表示）'!BO35 | C112: ='CF表（ご主人様死亡時・万円表示）'!BO35 | D112: ='CF表（奥様死亡時・万円表示）'!BO35
A113: ='CF表（万円表示）'!BP3 | B113: ='CF表（万円表示）'!BP35 | C113: ='CF表（ご主人様死亡時・万円表示）'!BP35 | D113: ='CF表（奥様死亡時・万円表示）'!BP35
A114: ='CF表（万円表示）'!BQ3 | B114: ='CF表（万円表示）'!BQ35 | C114: ='CF表（ご主人様死亡時・万円表示）'!BQ35 | D114: ='CF表（奥様死亡時・万円表示）'!BQ35
A115: ='CF表（万円表示）'!BR3 | B115: ='CF表（万円表示）'!BR35 | C115: ='CF表（ご主人様死亡時・万円表示）'!BR35 | D115: ='CF表（奥様死亡時・万円表示）'!BR35
A116: ='CF表（万円表示）'!BS3 | B116: ='CF表（万円表示）'!BS35 | C116: ='CF表（ご主人様死亡時・万円表示）'!BS35 | D116: ='CF表（奥様死亡時・万円表示）'!BS35
A117: ='CF表（万円表示）'!BT3 | B117: ='CF表（万円表示）'!BT35 | C117: ='CF表（ご主人様死亡時・万円表示）'!BT35 | D117: ='CF表（奥様死亡時・万円表示）'!BT35
A118: ='CF表（万円表示）'!BU3 | B118: ='CF表（万円表示）'!BU35 | C118: ='CF表（ご主人様死亡時・万円表示）'!BU35 | D118: ='CF表（奥様死亡時・万円表示）'!BU35
A119: ='CF表（万円表示）'!BV3 | B119: ='CF表（万円表示）'!BV35 | C119: ='CF表（ご主人様死亡時・万円表示）'!BV35 | D119: ='CF表（奥様死亡時・万円表示）'!BV35
A120: ='CF表（万円表示）'!BW3 | B120: ='CF表（万円表示）'!BW35 | C120: ='CF表（ご主人様死亡時・万円表示）'!BW35 | D120: ='CF表（奥様死亡時・万円表示）'!BW35
A121: ='CF表（万円表示）'!BX3 | B121: ='CF表（万円表示）'!BX35 | C121: ='CF表（ご主人様死亡時・万円表示）'!BX35 | D121: ='CF表（奥様死亡時・万円表示）'!BX35
A122: ='CF表（万円表示）'!BY3 | B122: ='CF表（万円表示）'!BY35 | C122: ='CF表（ご主人様死亡時・万円表示）'!BY35 | D122: ='CF表（奥様死亡時・万円表示）'!BY35
A123: ='CF表（万円表示）'!BZ3 | B123: ='CF表（万円表示）'!BZ35 | C123: ='CF表（ご主人様死亡時・万円表示）'!BZ35 | D123: ='CF表（奥様死亡時・万円表示）'!BZ35
A124: ='CF表（万円表示）'!CA3 | B124: ='CF表（万円表示）'!CA35 | C124: ='CF表（ご主人様死亡時・万円表示）'!CA35 | D124: ='CF表（奥様死亡時・万円表示）'!CA35
A125: ='CF表（万円表示）'!CB3 | B125: ='CF表（万円表示）'!CB35 | C125: ='CF表（ご主人様死亡時・万円表示）'!CB35 | D125: ='CF表（奥様死亡時・万円表示）'!CB35
A126: ='CF表（万円表示）'!CC3 | B126: ='CF表（万円表示）'!CC35 | C126: ='CF表（ご主人様死亡時・万円表示）'!CC35 | D126: ='CF表（奥様死亡時・万円表示）'!CC35
A127: ='CF表（万円表示）'!CD3 | B127: ='CF表（万円表示）'!CD35 | C127: ='CF表（ご主人様死亡時・万円表示）'!CD35 | D127: ='CF表（奥様死亡時・万円表示）'!CD35
A128: ='CF表（万円表示）'!CE3 | B128: ='CF表（万円表示）'!CE35 | C128: ='CF表（ご主人様死亡時・万円表示）'!CE35 | D128: ='CF表（奥様死亡時・万円表示）'!CE35
A129: ='CF表（万円表示）'!CF3 | B129: ='CF表（万円表示）'!CF35 | C129: ='CF表（ご主人様死亡時・万円表示）'!CF35 | D129: ='CF表（奥様死亡時・万円表示）'!CF35
A130: ='CF表（万円表示）'!CG3 | B130: ='CF表（万円表示）'!CG35 | C130: ='CF表（ご主人様死亡時・万円表示）'!CG35 | D130: ='CF表（奥様死亡時・万円表示）'!CG35
A131: ='CF表（万円表示）'!CH3 | B131: ='CF表（万円表示）'!CH35 | C131: ='CF表（ご主人様死亡時・万円表示）'!CH35 | D131: ='CF表（奥様死亡時・万円表示）'!CH35
A132: ='CF表（万円表示）'!CI3 | B132: ='CF表（万円表示）'!CI35 | C132: ='CF表（ご主人様死亡時・万円表示）'!CI35 | D132: ='CF表（奥様死亡時・万円表示）'!CI35
A133: ='CF表（万円表示）'!CJ3 | B133: ='CF表（万円表示）'!CJ35 | C133: ='CF表（ご主人様死亡時・万円表示）'!CJ35 | D133: ='CF表（奥様死亡時・万円表示）'!CJ35
A134: ='CF表（万円表示）'!CK3 | B134: ='CF表（万円表示）'!CK35 | C134: ='CF表（ご主人様死亡時・万円表示）'!CK35 | D134: ='CF表（奥様死亡時・万円表示）'!CK35
A135: ='CF表（万円表示）'!CL3 | B135: ='CF表（万円表示）'!CL35 | C135: ='CF表（ご主人様死亡時・万円表示）'!CL35 | D135: ='CF表（奥様死亡時・万円表示）'!CL35
A136: ='CF表（万円表示）'!CM3 | B136: ='CF表（万円表示）'!CM35 | C136: ='CF表（ご主人様死亡時・万円表示）'!CM35 | D136: ='CF表（奥様死亡時・万円表示）'!CM35
A137: ='CF表（万円表示）'!CN3 | B137: ='CF表（万円表示）'!CN35 | C137: ='CF表（ご主人様死亡時・万円表示）'!CN35 | D137: ='CF表（奥様死亡時・万円表示）'!CN35
A138: ='CF表（万円表示）'!CO3 | B138: ='CF表（万円表示）'!CO35 | C138: ='CF表（ご主人様死亡時・万円表示）'!CO35 | D138: ='CF表（奥様死亡時・万円表示）'!CO35
...

Sheet AI出力用
A1: AI出力用
A3: 1ページ目｜全体サマリー | F3: そのままAIに渡す要約
A4: 区分 | B4: 項目名 | C4: 値 | D4: AI用補足
A5: 1ページ目 | B5: 家庭名 | C5: =入力データ!C6
A6: 1ページ目 | B6: 家族構成 | C6: =IF(入力データ!C17=0,"ご夫婦",IF(入力データ!C17=1,"ご夫婦＋子ども1人","ご夫婦＋子ども"&入力データ!C17&"人"))
A7: 1ページ目 | B7: 住まい区分 | C7: =入力データ!C13
A8: 1ページ目 | B8: 世帯月収 | C8: =入力データ!C29+入力データ!C30+入力データ!C34+入力データ!C35
A9: 1ページ目 | B9: 月間支出 | C9: =CF表!B28/12
A10: 1ページ目 | B10: 現在貯蓄額 | C10: =入力データ!C88+入力データ!C89
A11: 1ページ目 | B11: 保有資産残高 | C11: =CF表!B35
A12: 1ページ目 | B12: 住宅ローン残高 | C12: =入力データ!C95
A13: 1ページ目 | B13: 全体サマリー文 | C13: =IF(CF表!B30>=0,"現状の家計は一定の安定感があります。今後は万一の事態や将来の支出に向けて、備えの優先順位を整理する段階です。","現状の家計は見直し余地があります。まずは日常の収支を整えながら、将来のリスクへの備え方を整理する段階です。")
A14: 1ページ目 | B14: 家計の強み | C14: =IF(CF表!B35>=10000000,"一定の資産があり、今後の選択肢を持ちやすい状態です。","現時点で家計の状況が整理できており、早めに打ち手を考えやすい状態です。")
A15: 1ページ目 | B15: 注意ポイント | C15: =IF(OR(リスク判定!B4="要対策",リスク判定!B5="要対策",リスク判定!B6="要対策"),"万一の収入減少や生活変化が起きた際に、家計負担が大きくなりやすい可能性があります。優先順位をつけて備えを整理することが重要です。","大きな破綻は見えにくいものの、死亡時・働けない時・老後への備えを早めに確認しておくと安心です。")
A17: 2ページ目｜リスクとCFの要点
A18: 区分 | B18: 項目名 | C18: 値 | D18: AI用補足
A19: 2ページ目 | B19: 年間収支 | C19: =CF表!B30
A20: 2ページ目 | B20: 通常時CFの要点 | C20: =IF(CF表!B30>=0,"通常時の家計は大きく崩れておらず、土台は保たれています。","通常時から年間収支に課題があり、まずは家計の整え方を確認したい状態です。")
A21: 2ページ目 | B21: ご主人様死亡時CFの要点 | C21: =IF('CF表（ご主人様死亡時）'!B35<0,"ご主人様に万一のことがあった場合、家計の継続に向けた備えを確認したい状態です。","ご主人様に万一のことがあっても、直ちに大きく崩れにくい見通しです。")
A22: 2ページ目 | B22: 奥様死亡時CFの要点 | C22: =IF('CF表（奥様死亡時）'!B35<0,"奥様に万一のことがあった場合、家計の継続に向けた備えを確認したい状態です。","奥様に万一のことがあっても、直ちに大きく崩れにくい見通しです。")
A23: 2ページ目
A24: 2ページ目 | B24: 死亡時リスク判定 | C24: =リスク判定!B4
A25: 2ページ目 | B25: 働けない時リスク判定 | C25: =リスク判定!B5
A26: 2ページ目 | B26: 老後リスク判定 | C26: =リスク判定!B6
A27: 2ページ目 | B27: 死亡時主要数値 | C27: =リスク判定!C4
A28: 2ページ目 | B28: 働けない時主要数値 | C28: =リスク判定!C5
A29: 2ページ目 | B29: 老後主要数値 | C29: =リスク判定!C6
A30: 2ページ目 | B30: リスク要約文 | C30: =IF(OR(リスク判定!B4="要対策",リスク判定!B5="要対策",リスク判定!B6="要対策"),"通常時は見えにくくても、万一や将来の場面では家計負担が重くなる可能性があります。どこから整えるかを決めることが大切です。","現時点では大きな破綻は見えにくいものの、今のうちに備え方を整理しておくと安心につながります。")
A34: 3ページ目｜改善アクション
A35: 区分 | B35: 項目名 | C35: 値 | D35: AI用補足
A36: 3ページ目 | B36: 優先アクション1 | C36: =IF(リスク判定!B4="要対策","死亡時に家計が崩れやすい部分を先に整理する",IF(リスク判定!B5="要対策","働けない時に備える優先順位を整理する",IF(CF表!B30<0,"通常時の家計収支を整える","将来に向けた備えの優先順位を整理する")))
A37: 3ページ目 | B37: 優先アクション2 | C37: =IF(CF表!B30<0,"固定費と毎月の支出配分を見直す",IF(リスク判定!B5="要対策","就業不能時の備え方を確認する","手元資金と保障のバランスを整える"))
A38: 3ページ目 | B38: 優先アクション3 | C38: =IF(リスク判定!B6="要対策","老後に向けた準備方針を決める",IF(入力データ!C95>0,"住宅ローンと保障のバランスを確認する","積立と貯蓄の役割分担を整える"))
A39: 3ページ目 | B39: 優先順位 | C39: ="1. 今の家計を守る / 2. 大きなリスクに備える / 3. 将来への準備を整える"
A40: 3ページ目 | B40: 進め方の考え方 | C40: =IF(CF表!B30<0,"まずは通常時の赤字要因を整理し、固定費・支出配分・保障内容の順で整えていく進め方が合っています。","現状の家計は大きく崩れていないため、万一の場面で弱くなりやすい部分から順に整えていく進め方が合っています。")
A41: 3ページ目 | B41: FPと一緒に考えること | C41: =IF(入力データ!C95>0,"住宅ローン、保障内容、手元資金のバランスをどう整えるかを一緒に確認します。","家計改善・保障・積立配分をどの順番で整えるかを一緒に確認します。")
A42: 3ページ目 | B42: 面談で確認したいこと | C42: ="今いちばん気になっている不安、見直したい支出、これから優先したいことを確認したいです。"

Sheet 入力データ
A1: 情報入力
A2: 入力ルール：黄色セルを中心に入力 / CF表は左→右に年が進みます / 未使用項目は空欄でOK
A3: 基本情報 | F3: 保険情報（複数行入力）
A4: 大項目 | B4: 項目名 | C4: 入力値 | D4: 補足 | F4: 保険種類 | G4: 対象者 | H4: 被保険者 | I4: 保険会社 | J4: 保険始期 | K4: 保険終期 | L4: 月額保険料 | M4: 受取人 | N4: 払込期間 | O4: 死亡保険金 | P4: 就業不能給付金 | Q4: 入院給付金 | R4: 解約返戻金 | S4: 備考
A5: 基本情報 | B5: 作成日 | C5: =情報入力!C5 | E5: ・未使用項目は空欄でOK | F5: =情報入力!A94 | G5: =情報入力!B94 | H5: =情報入力!C94 | I5: =情報入力!D94 | J5: =情報入力!E94 | K5: =情報入力!F94 | L5: =情報入力!G94 | M5: =情報入力!H94 | N5: 60歳満了 | O5: 30000000 | P5: 0 | Q5: 0 | R5: 0 | S5: 月払
B6: 家庭名 | C6: =情報入力!C6 | E6: ・CF表は左→右に年が進みます | F6: =情報入力!A95 | G6: =情報入力!B95 | H6: =情報入力!C95 | I6: =情報入力!D95 | J6: =情報入力!E95 | K6: =情報入力!F95 | L6: =情報入力!G95 | M6: =情報入力!H95 | N6: 終身払 | O6: 5000000 | P6: 0 | Q6: 0 | R6: 300000 | S6: 死亡保障
B7: 担当者名 | C7: =情報入力!C7 | F7: =情報入力!A96 | G7: =情報入力!B96 | H7: =情報入力!C96 | I7: =情報入力!D96 | J7: =情報入力!E96 | K7: =情報入力!F96 | L7: =情報入力!G96 | M7: =情報入力!H96 | N7: 65歳満了 | O7: 0 | P7: 100000 | Q7: 0 | R7: 0 | S7: 月10万円
B8: ご主人様氏名 | C8: =情報入力!C8 | F8: =情報入力!A97 | G8: =情報入力!B97 | H8: =情報入力!C97 | I8: =情報入力!D97 | J8: =情報入力!E97 | K8: =情報入力!F97 | L8: =情報入力!G97 | M8: =情報入力!H97 | N8: 終身払 | O8: 0 | P8: 0 | Q8: 5000 | R8: 0 | S8: 入院給付金
B9: 奥様氏名 | C9: =情報入力!C9 | F9: =情報入力!A98 | G9: =情報入力!B98 | H9: =情報入力!C98 | I9: =情報入力!D98 | J9: =情報入力!E98 | K9: =情報入力!F98 | L9: =情報入力!G98 | M9: =情報入力!H98
B10: ご主人様生年月日 | C10: =情報入力!C10 | F10: =情報入力!A99 | G10: =情報入力!B99 | H10: =情報入力!C99 | I10: =情報入力!D99 | J10: =情報入力!E99 | K10: =情報入力!F99 | L10: =情報入力!G99 | M10: =情報入力!H99
B11: 奥様生年月日 | C11: =情報入力!C11 | F11: =情報入力!A100 | G11: =情報入力!B100 | H11: =情報入力!C100 | I11: =情報入力!D100 | J11: =情報入力!E100 | K11: =情報入力!F100 | L11: =情報入力!G100 | M11: =情報入力!H100
B12: 都道府県 | C12: =情報入力!C12 | F12: =情報入力!A101 | G12: =情報入力!B101 | H12: =情報入力!C101 | I12: =情報入力!D101 | J12: =情報入力!E101 | K12: =情報入力!F101 | L12: =情報入力!G101 | M12: =情報入力!H101
B13: 住まい区分 | C13: =情報入力!C13
A15: 家族情報
A16: 大項目 | B16: 項目名 | C16: 入力値 | D16: 補足
A17: 家族情報 | B17: 子ども人数 | C17: =情報入力!C17
B18: 子1氏名 | C18: =情報入力!C18
B19: 子1生年月日 | C19: =情報入力!C19
B20: 子2氏名 | C20: =情報入力!C20
B21: 子2生年月日 | C21: =情報入力!C21
B22: 子3氏名 | C22: =情報入力!C22
A23: 教育費情報（複数行入力） | F23: 教育費情報（子ども別）
F24: 子ども名 | G24: 幼稚園区分 | H24: 小学校区分 | I24: 中学校区分 | J24: 高校区分 | K24: 大学区分 | L24: 大学通学
A25: 収入情報 | F25: =情報入力!A106 | G25: =情報入力!B106 | H25: =情報入力!C106 | I25: =情報入力!D106 | J25: =情報入力!E106 | K25: =情報入力!F106 | L25: =情報入力!G106
A26: 大項目 | B26: 項目名 | C26: 入力値 | D26: 補足 | F26: =情報入力!A107 | G26: =情報入力!B107 | H26: =情報入力!C107 | I26: =情報入力!D107 | J26: =情報入力!E107 | K26: =情報入力!F107 | L26: =情報入力!G107
A27: 収入情報 | B27: ご主人様勤務形態 | C27: =情報入力!C26 | F27: =情報入力!A108 | G27: =情報入力!B108 | H27: =情報入力!C108 | I27: =情報入力!D108 | J27: =情報入力!E108 | K27: =情報入力!F108 | L27: =情報入力!G108
B28: 奥様勤務形態 | C28: =情報入力!C27 | F28: =情報入力!A109 | G28: =情報入力!B109 | H28: =情報入力!C109 | I28: =情報入力!D109 | J28: =情報入力!E109 | K28: =情報入力!F109 | L28: =情報入力!G109
B29: ご主人様手取り月収 | C29: =情報入力!C28
B30: 奥様手取り月収 | C30: =情報入力!C29
B31: ボーナス有無 | C31: =情報入力!C30
B32: ご主人様年間賞与手取 | C32: =情報入力!C31
B33: 奥様年間賞与手取 | C33: =情報入力!C32
B34: 児童手当月額 | C34: =IFERROR(ROUND((IF($C$17>=1,IF(YEAR(DATE(YEAR($C$5),12,31))-YEAR($C$19)-IF(DATE(YEAR($C$5),12,31)<DATE(YEAR($C$5),MONTH($C$19),DAY($C$19)),1,0)<3,15000,10000),0)+IF($C$17>=2,IF(2>=3,30000,IF(YEAR(DATE(YEAR($C$5),12,31))-YEAR($C$21)-IF(DATE(YEAR($C$5),12,31)<DATE(YEAR($C$5),MONTH($C$21),DAY($C$21)),1,0)<3,15000,10000)),0)+IF($C$17>=3,30000,0))/MAX($C$17,1),0),0)
B35: その他定期収入月額 | C35: =IF(情報入力!C34="",0,情報入力!C34)
B36: ご主人様退職金見込額 | C36: =IF(情報入力!C35="",0,情報入力!C35)
B37: 奥様退職金見込額 | C37: =IF(情報入力!C36="",0,情報入力!C36)
A39: 支出情報（月額）
A40: 大項目 | B40: 項目名 | C40: 入力値 | D40: 補足
A41: 支出情報（月額） | B41: 食費 | C41: =情報入力!C40
B42: 日用品費 | C42: =情報入力!C41
B43: 水道光熱費 | C43: =情報入力!C42
B44: 通信費 | C44: =情報入力!C43
B45: 被服費 | C45: 10000
B46: 美容費 | C46: 8000
B47: 医療費 | C47: 6000
B48: 交際費 | C48: 12000
B49: 娯楽費 | C49: 20000
B50: ご主人様こづかい | C50: 30000
B51: 奥様こづかい | C51: 15000
B52: その他生活費 | C52: 10000
B53: 住居費月額 | C53: =情報入力!C44
B54: 管理修繕費月額 | C54: =情報入力!C45
B55: 火災保険月額 | C55: 2000
B56: その他住居費月額 | C56: 0
B57: 住宅ローン団信有無 | C57: =情報入力!C46
B58: 習い事費月額 | C58: =情報入力!C47
B59: 学校関連費月額 | C59: 0
B60: 塾費月額 | C60: 0
B61: その他教育費月額 | C61: 0
B62: 生命保険料月額 | C62: =情報入力!C48
B63: 医療保険料月額 | C63: =情報入力!C49
B64: 学資保険料月額 | C64: 0
B65: その他保険料月額 | C65: 0
B66: 駐車場代月額 | C66: 0
B67: ガソリン代月額 | C67: 0
B68: 自動車保険料月額 | C68: 0
B69: 車維持費月額 | C69: =情報入力!C50
B70: その他車費月額 | C70: 0
B71: サブスク月額 | C71: 5000
B72: 仕送り月額 | C72: 0
B73: 借入返済月額 | C73: 0
B74: その他固定費月額 | C74: =情報入力!C51
A76: 特別支出（年額）
A77: 大項目 | B77: 項目名 | C77: 入力値 | D77: 補足
A78: 特別支出（年額） | B78: 旅行年額 | C78: 0
B79: 帰省年額 | C79: 0
B80: 冠婚葬祭年額 | C80: 0
B81: 家電買替年額 | C81: 0
B82: その他特別支出年額 | C82: 0
B83: 固定資産税年額 | C83: 0
B84: 賃貸更新料年額 | C84: 0
A86: 資産・負債情報
A87: 大項目 | B87: 項目名 | C87: 入力値 | D87: 補足
A88: 資産・負債情報 | B88: 今ある預貯金（普通預金） | C88: =情報入力!C71
A89: 資産・負債情報 | B89: 今ある預貯金（定期預金） | C89: =情報入力!C72
A90: 資産・負債情報 | B90: 今ある投資残高（積立投資） | C90: =情報入力!C73
A91: 資産・負債情報 | B91: 今ある投資残高（NISA） | C91: =情報入力!C74
A92: 資産・負債情報 | B92: 今ある投資残高（iDeCo） | C92: =情報入力!C75
A93: 資産・負債情報 | B93: 今ある返戻金見込（学資保険など） | C93: =情報入力!C76
A94: 資産・負債情報 | B94: その他金融資産残高 | C94: 0
A95: 資産・負債情報 | B95: 住宅ローン残高（参考） | C95: =情報入力!C77
A96: 資産・負債情報 | B96: 自動車ローン残高 | C96: 0
A97: 資産・負債情報 | B97: その他借入残高 | C97: 0
A99: 資産形成情報
A100: 大項目 | B100: 項目名 | C100: 入力値 | D100: 補足
A101: 資産形成情報 | B101: 毎月のNISA積立額 | C101: =情報入力!C63
B102: 毎月のiDeCo積立額 | C102: =情報入力!C64
B103: 毎月の特定口座積立額 | C103: =情報入力!C65
B104: 毎月の変額保険・積立保険額 | C104: =情報入力!C66
B105: 毎月のその他投資積立額 | C105: =情報入力!C67
...

Sheet CF表
A1: CF表（年次CF / 左→右に年が進む）
A2: 試算終了年 | B2: =MAX(IF(入力データ!$C$10<>"",YEAR(入力データ!$C$10)+100,0),IF(入力データ!$C$11<>"",YEAR(入力データ!$C$11)+100,0))
A3: 年 | B3: =IF(YEAR(入力データ!$C$5)>$B$2,"",YEAR(入力データ!$C$5)) | C3: =IF(B3="","",IF(B3+1>$B$2,"",B3+1)) | D3: =IF(C3="","",IF(C3+1>$B$2,"",C3+1)) | E3: =IF(D3="","",IF(D3+1>$B$2,"",D3+1)) | F3: =IF(E3="","",IF(E3+1>$B$2,"",E3+1)) | G3: =IF(F3="","",IF(F3+1>$B$2,"",F3+1)) | H3: =IF(G3="","",IF(G3+1>$B$2,"",G3+1)) | I3: =IF(H3="","",IF(H3+1>$B$2,"",H3+1)) | J3: =IF(I3="","",IF(I3+1>$B$2,"",I3+1)) | ... CW3: =IF(CV3="","",IF(CV3+1>$B$2,"",CV3+1))
A4: ご主人様年齢 | B4: =IF(B$3="","",IF(入力データ!$C$10="","",YEAR(DATE(B$3,12,31))-YEAR(入力データ!$C$10)-IF(DATE(B$3,12,31)<DATE(B$3,MONTH(入力データ!$C$10),DAY(入力データ!$C$10)),1,0))) | C4: =IF(C$3="","",IF(入力データ!$C$10="","",YEAR(DATE(C$3,12,31))-YEAR(入力データ!$C$10)-IF(DATE(C$3,12,31)<DATE(C$3,MONTH(入力データ!$C$10),DAY(入力データ!$C$10)),1,0))) | D4: =IF(D$3="","",IF(入力データ!$C$10="","",YEAR(DATE(D$3,12,31))-YEAR(入力データ!$C$10)-IF(DATE(D$3,12,31)<DATE(D$3,MONTH(入力データ!$C$10),DAY(入力データ!$C$10)),1,0))) | E4: =IF(E$3="","",IF(入力データ!$C$10="","",YEAR(DATE(E$3,12,31))-YEAR(入力データ!$C$10)-IF(DATE(E$3,12,31)<DATE(E$3,MONTH(入力データ!$C$10),DAY(入力データ!$C$10)),1,0))) | F4: =IF(F$3="","",IF(入力データ!$C$10="","",YEAR(DATE(F$3,12,31))-YEAR(入力データ!$C$10)-IF(DATE(F$3,12,31)<DATE(F$3,MONTH(入力データ!$C$10),DAY(入力データ!$C$10)),1,0))) | G4: =IF(G$3="","",IF(入力データ!$C$10="","",YEAR(DATE(G$3,12,31))-YEAR(入力データ!$C$10)-IF(DATE(G$3,12,31)<DATE(G$3,MONTH(入力データ!$C$10),DAY(入力データ!$C$10)),1,0))) | H4: =IF(H$3="","",IF(入力データ!$C$10="","",YEAR(DATE(H$3,12,31))-YEAR(入力データ!$C$10)-IF(DATE(H$3,12,31)<DATE(H$3,MONTH(入力データ!$C$10),DAY(入力データ!$C$10)),1,0))) | I4: =IF(I$3="","",IF(入力データ!$C$10="","",YEAR(DATE(I$3,12,31))-YEAR(入力データ!$C$10)-IF(DATE(I$3,12,31)<DATE(I$3,MONTH(入力データ!$C$10),DAY(入力データ!$C$10)),1,0))) | ... CW4: =IF(CW$3="","",IF(入力データ!$C$10="","",YEAR(DATE(CW$3,12,31))-YEAR(入力データ!$C$10)-IF(DATE(CW$3,12,31)<DATE(CW$3,MONTH(入力データ!$C$10),DAY(入力データ!$C$10)),1,0)))
A5: 奥様年齢 | B5: =IF(B$3="","",IF(入力データ!$C$11="","",YEAR(DATE(B$3,12,31))-YEAR(入力データ!$C$11)-IF(DATE(B$3,12,31)<DATE(B$3,MONTH(入力データ!$C$11),DAY(入力データ!$C$11)),1,0))) | C5: =IF(C$3="","",IF(入力データ!$C$11="","",YEAR(DATE(C$3,12,31))-YEAR(入力データ!$C$11)-IF(DATE(C$3,12,31)<DATE(C$3,MONTH(入力データ!$C$11),DAY(入力データ!$C$11)),1,0))) | D5: =IF(D$3="","",IF(入力データ!$C$11="","",YEAR(DATE(D$3,12,31))-YEAR(入力データ!$C$11)-IF(DATE(D$3,12,31)<DATE(D$3,MONTH(入力データ!$C$11),DAY(入力データ!$C$11)),1,0))) | E5: =IF(E$3="","",IF(入力データ!$C$11="","",YEAR(DATE(E$3,12,31))-YEAR(入力データ!$C$11)-IF(DATE(E$3,12,31)<DATE(E$3,MONTH(入力データ!$C$11),DAY(入力データ!$C$11)),1,0))) | F5: =IF(F$3="","",IF(入力データ!$C$11="","",YEAR(DATE(F$3,12,31))-YEAR(入力データ!$C$11)-IF(DATE(F$3,12,31)<DATE(F$3,MONTH(入力データ!$C$11),DAY(入力データ!$C$11)),1,0))) | G5: =IF(G$3="","",IF(入力データ!$C$11="","",YEAR(DATE(G$3,12,31))-YEAR(入力データ!$C$11)-IF(DATE(G$3,12,31)<DATE(G$3,MONTH(入力データ!$C$11),DAY(入力データ!$C$11)),1,0))) | H5: =IF(H$3="","",IF(入力データ!$C$11="","",YEAR(DATE(H$3,12,31))-YEAR(入力データ!$C$11)-IF(DATE(H$3,12,31)<DATE(H$3,MONTH(入力データ!$C$11),DAY(入力データ!$C$11)),1,0))) | I5: =IF(I$3="","",IF(入力データ!$C$11="","",YEAR(DATE(I$3,12,31))-YEAR(入力データ!$C$11)-IF(DATE(I$3,12,31)<DATE(I$3,MONTH(入力データ!$C$11),DAY(入力データ!$C$11)),1,0))) | ... CW5: =IF(CW$3="","",IF(入力データ!$C$11="","",YEAR(DATE(CW$3,12,31))-YEAR(入力データ!$C$11)-IF(DATE(CW$3,12,31)<DATE(CW$3,MONTH(入力データ!$C$11),DAY(入力データ!$C$11)),1,0)))
A6: 子1年齢 | B6: =IF(B$3="","",IF(入力データ!$C$19="","",YEAR(DATE(B$3,12,31))-YEAR(入力データ!$C$19)-IF(DATE(B$3,12,31)<DATE(B$3,MONTH(入力データ!$C$19),DAY(入力データ!$C$19)),1,0))) | C6: =IF(C$3="","",IF(入力データ!$C$19="","",YEAR(DATE(C$3,12,31))-YEAR(入力データ!$C$19)-IF(DATE(C$3,12,31)<DATE(C$3,MONTH(入力データ!$C$19),DAY(入力データ!$C$19)),1,0))) | D6: =IF(D$3="","",IF(入力データ!$C$19="","",YEAR(DATE(D$3,12,31))-YEAR(入力データ!$C$19)-IF(DATE(D$3,12,31)<DATE(D$3,MONTH(入力データ!$C$19),DAY(入力データ!$C$19)),1,0))) | E6: =IF(E$3="","",IF(入力データ!$C$19="","",YEAR(DATE(E$3,12,31))-YEAR(入力データ!$C$19)-IF(DATE(E$3,12,31)<DATE(E$3,MONTH(入力データ!$C$19),DAY(入力データ!$C$19)),1,0))) | F6: =IF(F$3="","",IF(入力データ!$C$19="","",YEAR(DATE(F$3,12,31))-YEAR(入力データ!$C$19)-IF(DATE(F$3,12,31)<DATE(F$3,MONTH(入力データ!$C$19),DAY(入力データ!$C$19)),1,0))) | G6: =IF(G$3="","",IF(入力データ!$C$19="","",YEAR(DATE(G$3,12,31))-YEAR(入力データ!$C$19)-IF(DATE(G$3,12,31)<DATE(G$3,MONTH(入力データ!$C$19),DAY(入力データ!$C$19)),1,0))) | H6: =IF(H$3="","",IF(入力データ!$C$19="","",YEAR(DATE(H$3,12,31))-YEAR(入力データ!$C$19)-IF(DATE(H$3,12,31)<DATE(H$3,MONTH(入力データ!$C$19),DAY(入力データ!$C$19)),1,0))) | I6: =IF(I$3="","",IF(入力データ!$C$19="","",YEAR(DATE(I$3,12,31))-YEAR(入力データ!$C$19)-IF(DATE(I$3,12,31)<DATE(I$3,MONTH(入力データ!$C$19),DAY(入力データ!$C$19)),1,0))) | ... CW6: =IF(CW$3="","",IF(入力データ!$C$19="","",YEAR(DATE(CW$3,12,31))-YEAR(入力データ!$C$19)-IF(DATE(CW$3,12,31)<DATE(CW$3,MONTH(入力データ!$C$19),DAY(入力データ!$C$19)),1,0)))
A7: 子2年齢 | B7: =IF(B$3="","",IF(入力データ!$C$21="","",YEAR(DATE(B$3,12,31))-YEAR(入力データ!$C$21)-IF(DATE(B$3,12,31)<DATE(B$3,MONTH(入力データ!$C$21),DAY(入力データ!$C$21)),1,0))) | C7: =IF(C$3="","",IF(入力データ!$C$21="","",YEAR(DATE(C$3,12,31))-YEAR(入力データ!$C$21)-IF(DATE(C$3,12,31)<DATE(C$3,MONTH(入力データ!$C$21),DAY(入力データ!$C$21)),1,0))) | D7: =IF(D$3="","",IF(入力データ!$C$21="","",YEAR(DATE(D$3,12,31))-YEAR(入力データ!$C$21)-IF(DATE(D$3,12,31)<DATE(D$3,MONTH(入力データ!$C$21),DAY(入力データ!$C$21)),1,0))) | E7: =IF(E$3="","",IF(入力データ!$C$21="","",YEAR(DATE(E$3,12,31))-YEAR(入力データ!$C$21)-IF(DATE(E$3,12,31)<DATE(E$3,MONTH(入力データ!$C$21),DAY(入力データ!$C$21)),1,0))) | F7: =IF(F$3="","",IF(入力データ!$C$21="","",YEAR(DATE(F$3,12,31))-YEAR(入力データ!$C$21)-IF(DATE(F$3,12,31)<DATE(F$3,MONTH(入力データ!$C$21),DAY(入力データ!$C$21)),1,0))) | G7: =IF(G$3="","",IF(入力データ!$C$21="","",YEAR(DATE(G$3,12,31))-YEAR(入力データ!$C$21)-IF(DATE(G$3,12,31)<DATE(G$3,MONTH(入力データ!$C$21),DAY(入力データ!$C$21)),1,0))) | H7: =IF(H$3="","",IF(入力データ!$C$21="","",YEAR(DATE(H$3,12,31))-YEAR(入力データ!$C$21)-IF(DATE(H$3,12,31)<DATE(H$3,MONTH(入力データ!$C$21),DAY(入力データ!$C$21)),1,0))) | I7: =IF(I$3="","",IF(入力データ!$C$21="","",YEAR(DATE(I$3,12,31))-YEAR(入力データ!$C$21)-IF(DATE(I$3,12,31)<DATE(I$3,MONTH(入力データ!$C$21),DAY(入力データ!$C$21)),1,0))) | ... CW7: =IF(CW$3="","",IF(入力データ!$C$21="","",YEAR(DATE(CW$3,12,31))-YEAR(入力データ!$C$21)-IF(DATE(CW$3,12,31)<DATE(CW$3,MONTH(入力データ!$C$21),DAY(入力データ!$C$21)),1,0)))
A8: 子3年齢 | B8: =IF(B$3="","",IF(情報入力!$C$23="","",YEAR(DATE(B$3,12,31))-YEAR(情報入力!$C$23)-IF(DATE(B$3,12,31)<DATE(B$3,MONTH(情報入力!$C$23),DAY(情報入力!$C$23)),1,0))) | C8: =IF(C$3="","",IF(情報入力!$C$23="","",YEAR(DATE(C$3,12,31))-YEAR(情報入力!$C$23)-IF(DATE(C$3,12,31)<DATE(C$3,MONTH(情報入力!$C$23),DAY(情報入力!$C$23)),1,0))) | D8: =IF(D$3="","",IF(情報入力!$C$23="","",YEAR(DATE(D$3,12,31))-YEAR(情報入力!$C$23)-IF(DATE(D$3,12,31)<DATE(D$3,MONTH(情報入力!$C$23),DAY(情報入力!$C$23)),1,0))) | E8: =IF(E$3="","",IF(情報入力!$C$23="","",YEAR(DATE(E$3,12,31))-YEAR(情報入力!$C$23)-IF(DATE(E$3,12,31)<DATE(E$3,MONTH(情報入力!$C$23),DAY(情報入力!$C$23)),1,0))) | F8: =IF(F$3="","",IF(情報入力!$C$23="","",YEAR(DATE(F$3,12,31))-YEAR(情報入力!$C$23)-IF(DATE(F$3,12,31)<DATE(F$3,MONTH(情報入力!$C$23),DAY(情報入力!$C$23)),1,0))) | G8: =IF(G$3="","",IF(情報入力!$C$23="","",YEAR(DATE(G$3,12,31))-YEAR(情報入力!$C$23)-IF(DATE(G$3,12,31)<DATE(G$3,MONTH(情報入力!$C$23),DAY(情報入力!$C$23)),1,0))) | H8: =IF(H$3="","",IF(情報入力!$C$23="","",YEAR(DATE(H$3,12,31))-YEAR(情報入力!$C$23)-IF(DATE(H$3,12,31)<DATE(H$3,MONTH(情報入力!$C$23),DAY(情報入力!$C$23)),1,0))) | I8: =IF(I$3="","",IF(情報入力!$C$23="","",YEAR(DATE(I$3,12,31))-YEAR(情報入力!$C$23)-IF(DATE(I$3,12,31)<DATE(I$3,MONTH(情報入力!$C$23),DAY(情報入力!$C$23)),1,0))) | ... CW8: =IF(CW$3="","",IF(情報入力!$C$23="","",YEAR(DATE(CW$3,12,31))-YEAR(情報入力!$C$23)-IF(DATE(CW$3,12,31)<DATE(CW$3,MONTH(情報入力!$C$23),DAY(情報入力!$C$23)),1,0)))
A9: 家族年齢
A10: ご主人様収入 | B10: =IF(B$3="","",IF(B4<入力データ!$C$109,((入力データ!$C$29*12)+IF(入力データ!$C$31="あり",入力データ!$C$32,0))*(1+前提条件!$C$5)^(B$3-$B$3),0)) | C10: =IF(C$3="","",IF(C4<入力データ!$C$109,((入力データ!$C$29*12)+IF(入力データ!$C$31="あり",入力データ!$C$32,0))*(1+前提条件!$C$5)^(C$3-$B$3),0)) | D10: =IF(D$3="","",IF(D4<入力データ!$C$109,((入力データ!$C$29*12)+IF(入力データ!$C$31="あり",入力データ!$C$32,0))*(1+前提条件!$C$5)^(D$3-$B$3),0)) | E10: =IF(E$3="","",IF(E4<入力データ!$C$109,((入力データ!$C$29*12)+IF(入力データ!$C$31="あり",入力データ!$C$32,0))*(1+前提条件!$C$5)^(E$3-$B$3),0)) | F10: =IF(F$3="","",IF(F4<入力データ!$C$109,((入力データ!$C$29*12)+IF(入力データ!$C$31="あり",入力データ!$C$32,0))*(1+前提条件!$C$5)^(F$3-$B$3),0)) | G10: =IF(G$3="","",IF(G4<入力データ!$C$109,((入力データ!$C$29*12)+IF(入力データ!$C$31="あり",入力データ!$C$32,0))*(1+前提条件!$C$5)^(G$3-$B$3),0)) | H10: =IF(H$3="","",IF(H4<入力データ!$C$109,((入力データ!$C$29*12)+IF(入力データ!$C$31="あり",入力データ!$C$32,0))*(1+前提条件!$C$5)^(H$3-$B$3),0)) | I10: =IF(I$3="","",IF(I4<入力データ!$C$109,((入力データ!$C$29*12)+IF(入力データ!$C$31="あり",入力データ!$C$32,0))*(1+前提条件!$C$5)^(I$3-$B$3),0)) | ... CW10: =IF(CW$3="","",IF(CW4<入力データ!$C$109,((入力データ!$C$29*12)+IF(入力データ!$C$31="あり",入力データ!$C$32,0))*(1+前提条件!$C$5)^(CW$3-$B$3),0))
A11: 奥様収入 | B11: =IF(B$3="","",IF(B5<入力データ!$C$110,((入力データ!$C$30*12)+IF(入力データ!$C$31="あり",入力データ!$C$33,0))*(1+前提条件!$C$6)^(B$3-$B$3),0)) | C11: =IF(C$3="","",IF(C5<入力データ!$C$110,((入力データ!$C$30*12)+IF(入力データ!$C$31="あり",入力データ!$C$33,0))*(1+前提条件!$C$6)^(C$3-$B$3),0)) | D11: =IF(D$3="","",IF(D5<入力データ!$C$110,((入力データ!$C$30*12)+IF(入力データ!$C$31="あり",入力データ!$C$33,0))*(1+前提条件!$C$6)^(D$3-$B$3),0)) | E11: =IF(E$3="","",IF(E5<入力データ!$C$110,((入力データ!$C$30*12)+IF(入力データ!$C$31="あり",入力データ!$C$33,0))*(1+前提条件!$C$6)^(E$3-$B$3),0)) | F11: =IF(F$3="","",IF(F5<入力データ!$C$110,((入力データ!$C$30*12)+IF(入力データ!$C$31="あり",入力データ!$C$33,0))*(1+前提条件!$C$6)^(F$3-$B$3),0)) | G11: =IF(G$3="","",IF(G5<入力データ!$C$110,((入力データ!$C$30*12)+IF(入力データ!$C$31="あり",入力データ!$C$33,0))*(1+前提条件!$C$6)^(G$3-$B$3),0)) | H11: =IF(H$3="","",IF(H5<入力データ!$C$110,((入力データ!$C$30*12)+IF(入力データ!$C$31="あり",入力データ!$C$33,0))*(1+前提条件!$C$6)^(H$3-$B$3),0)) | I11: =IF(I$3="","",IF(I5<入力データ!$C$110,((入力データ!$C$30*12)+IF(入力データ!$C$31="あり",入力データ!$C$33,0))*(1+前提条件!$C$6)^(I$3-$B$3),0)) | ... CW11: =IF(CW$3="","",IF(CW5<入力データ!$C$110,((入力データ!$C$30*12)+IF(入力データ!$C$31="あり",入力データ!$C$33,0))*(1+前提条件!$C$6)^(CW$3-$B$3),0))
A12: 児童手当 | B12: =IF(B$3="","",IF(AND(B6<>"",B6<=前提条件!$C$8),IF(1>=3,30000,IF(B6<3,15000,10000))*6,0)+IF(AND(B7<>"",B7<=前提条件!$C$8),IF(2>=3,30000,IF(B7<3,15000,10000))*6,0)+IF(AND(B8<>"",B8<=前提条件!$C$8),30000*6,0)) | C12: =IF(C$3="","",IF(AND(C6<>"",C6<=前提条件!$C$8),IF(1>=3,30000,IF(C6<3,15000,10000))*6,0)+IF(AND(C7<>"",C7<=前提条件!$C$8),IF(2>=3,30000,IF(C7<3,15000,10000))*6,0)+IF(AND(C8<>"",C8<=前提条件!$C$8),30000*6,0)) | D12: =IF(D$3="","",IF(AND(D6<>"",D6<=前提条件!$C$8),IF(1>=3,30000,IF(D6<3,15000,10000))*6,0)+IF(AND(D7<>"",D7<=前提条件!$C$8),IF(2>=3,30000,IF(D7<3,15000,10000))*6,0)+IF(AND(D8<>"",D8<=前提条件!$C$8),30000*6,0)) | E12: =IF(E$3="","",IF(AND(E6<>"",E6<=前提条件!$C$8),IF(1>=3,30000,IF(E6<3,15000,10000))*6,0)+IF(AND(E7<>"",E7<=前提条件!$C$8),IF(2>=3,30000,IF(E7<3,15000,10000))*6,0)+IF(AND(E8<>"",E8<=前提条件!$C$8),30000*6,0)) | F12: =IF(F$3="","",IF(AND(F6<>"",F6<=前提条件!$C$8),IF(1>=3,30000,IF(F6<3,15000,10000))*6,0)+IF(AND(F7<>"",F7<=前提条件!$C$8),IF(2>=3,30000,IF(F7<3,15000,10000))*6,0)+IF(AND(F8<>"",F8<=前提条件!$C$8),30000*6,0)) | G12: =IF(G$3="","",IF(AND(G6<>"",G6<=前提条件!$C$8),IF(1>=3,30000,IF(G6<3,15000,10000))*6,0)+IF(AND(G7<>"",G7<=前提条件!$C$8),IF(2>=3,30000,IF(G7<3,15000,10000))*6,0)+IF(AND(G8<>"",G8<=前提条件!$C$8),30000*6,0)) | H12: =IF(H$3="","",IF(AND(H6<>"",H6<=前提条件!$C$8),IF(1>=3,30000,IF(H6<3,15000,10000))*6,0)+IF(AND(H7<>"",H7<=前提条件!$C$8),IF(2>=3,30000,IF(H7<3,15000,10000))*6,0)+IF(AND(H8<>"",H8<=前提条件!$C$8),30000*6,0)) | I12: =IF(I$3="","",IF(AND(I6<>"",I6<=前提条件!$C$8),IF(1>=3,30000,IF(I6<3,15000,10000))*6,0)+IF(AND(I7<>"",I7<=前提条件!$C$8),IF(2>=3,30000,IF(I7<3,15000,10000))*6,0)+IF(AND(I8<>"",I8<=前提条件!$C$8),30000*6,0)) | ... CV12: =IF(CV$3="","",IF(AND(CV6<>"",CV6<=前提条件!$C$8),IF(1>=3,30000,IF(CV6<3,15000,10000))*6,0)+IF(AND(CV7<>"",CV7<=前提条件!$C$8),IF(2>=3,30000,IF(CV7<3,15000,10000))*6,0)+IF(AND(CV8<>"",CV8<=前提条件!$C$8),30000*6,0)) | CW12: =IF(CW$3="","",IF(AND(CW6<>"",CW6<=前提条件!$C$8),入力データ!$C$34*6,0)+IF(AND(CW7<>"",CW7<=前提条件!$C$8),入力データ!$C$34*6,0)+IF(AND(CW8<>"",CW8<=前提条件!$C$8),入力データ!$C$34*6,0))
A13: その他収入 | B13: =IF(B$3="","",入力データ!$C$35*12) | C13: =IF(C$3="","",入力データ!$C$35*12) | D13: =IF(D$3="","",入力データ!$C$35*12) | E13: =IF(E$3="","",入力データ!$C$35*12) | F13: =IF(F$3="","",入力データ!$C$35*12) | G13: =IF(G$3="","",入力データ!$C$35*12) | H13: =IF(H$3="","",入力データ!$C$35*12) | I13: =IF(I$3="","",入力データ!$C$35*12) | ... CW13: =IF(CW$3="","",入力データ!$C$35*12)
A14: ご主人様退職金 | B14: =IF(B$3="","",IF(B4=入力データ!$C$109,入力データ!$C$36,0)) | C14: =IF(C$3="","",IF(C4=入力データ!$C$109,入力データ!$C$36,0)) | D14: =IF(D$3="","",IF(D4=入力データ!$C$109,入力データ!$C$36,0)) | E14: =IF(E$3="","",IF(E4=入力データ!$C$109,入力データ!$C$36,0)) | F14: =IF(F$3="","",IF(F4=入力データ!$C$109,入力データ!$C$36,0)) | G14: =IF(G$3="","",IF(G4=入力データ!$C$109,入力データ!$C$36,0)) | H14: =IF(H$3="","",IF(H4=入力データ!$C$109,入力データ!$C$36,0)) | I14: =IF(I$3="","",IF(I4=入力データ!$C$109,入力データ!$C$36,0)) | ... CW14: =IF(CW$3="","",IF(CW4=入力データ!$C$109,入力データ!$C$36,0))
A15: 奥様退職金 | B15: =IF(B$3="","",IF(B5=入力データ!$C$110,入力データ!$C$37,0)) | C15: =IF(C$3="","",IF(C5=入力データ!$C$110,入力データ!$C$37,0)) | D15: =IF(D$3="","",IF(D5=入力データ!$C$110,入力データ!$C$37,0)) | E15: =IF(E$3="","",IF(E5=入力データ!$C$110,入力データ!$C$37,0)) | F15: =IF(F$3="","",IF(F5=入力データ!$C$110,入力データ!$C$37,0)) | G15: =IF(G$3="","",IF(G5=入力データ!$C$110,入力データ!$C$37,0)) | H15: =IF(H$3="","",IF(H5=入力データ!$C$110,入力データ!$C$37,0)) | I15: =IF(I$3="","",IF(I5=入力データ!$C$110,入力データ!$C$37,0)) | ... CW15: =IF(CW$3="","",IF(CW5=入力データ!$C$110,入力データ!$C$37,0))
A16: ご主人様年金収入 | B16: =IF(B$3="","",IF(B4>=前提条件!$C$37,前提条件!$C$39*12,0)) | C16: =IF(C$3="","",IF(C4>=前提条件!$C$37,前提条件!$C$39*12,0)) | D16: =IF(D$3="","",IF(D4>=前提条件!$C$37,前提条件!$C$39*12,0)) | E16: =IF(E$3="","",IF(E4>=前提条件!$C$37,前提条件!$C$39*12,0)) | F16: =IF(F$3="","",IF(F4>=前提条件!$C$37,前提条件!$C$39*12,0)) | G16: =IF(G$3="","",IF(G4>=前提条件!$C$37,前提条件!$C$39*12,0)) | H16: =IF(H$3="","",IF(H4>=前提条件!$C$37,前提条件!$C$39*12,0)) | I16: =IF(I$3="","",IF(I4>=前提条件!$C$37,前提条件!$C$39*12,0)) | ... CW16: =IF(CW$3="","",IF(CW4>=前提条件!$C$37,前提条件!$C$39*12,0))
A17: 奥様年金収入 | B17: =IF(B$3="","",IF(B5>=前提条件!$C$38,前提条件!$C$40*12,0)) | C17: =IF(C$3="","",IF(C5>=前提条件!$C$38,前提条件!$C$40*12,0)) | D17: =IF(D$3="","",IF(D5>=前提条件!$C$38,前提条件!$C$40*12,0)) | E17: =IF(E$3="","",IF(E5>=前提条件!$C$38,前提条件!$C$40*12,0)) | F17: =IF(F$3="","",IF(F5>=前提条件!$C$38,前提条件!$C$40*12,0)) | G17: =IF(G$3="","",IF(G5>=前提条件!$C$38,前提条件!$C$40*12,0)) | H17: =IF(H$3="","",IF(H5>=前提条件!$C$38,前提条件!$C$40*12,0)) | I17: =IF(I$3="","",IF(I5>=前提条件!$C$38,前提条件!$C$40*12,0)) | ... CW17: =IF(CW$3="","",IF(CW5>=前提条件!$C$38,前提条件!$C$40*12,0))
A18: 世帯収入合計 | B18: =IF(B$3="","",SUM(B10:B17)) | C18: =IF(C$3="","",SUM(C10:C17)) | D18: =IF(D$3="","",SUM(D10:D17)) | E18: =IF(E$3="","",SUM(E10:E17)) | F18: =IF(F$3="","",SUM(F10:F17)) | G18: =IF(G$3="","",SUM(G10:G17)) | H18: =IF(H$3="","",SUM(H10:H17)) | I18: =IF(I$3="","",SUM(I10:I17)) | ... CW18: =IF(CW$3="","",SUM(CW10:CW17))
A19: 収入
A20: 基本生活費 | B20: =IF(B$3="","",IF(MIN(B4,B5)>=入力データ!$C$111,入力データ!$C$112*12*(1+前提条件!$C$14)^(B$3-$B$3),SUM(入力データ!$C$41:$C$52)*12*(1+前提条件!$C$12)^(B$3-$B$3))) | C20: =IF(C$3="","",IF(MIN(C4,C5)>=入力データ!$C$111,入力データ!$C$112*12*(1+前提条件!$C$14)^(C$3-$B$3),SUM(入力データ!$C$41:$C$52)*12*(1+前提条件!$C$12)^(C$3-$B$3))) | D20: =IF(D$3="","",IF(MIN(D4,D5)>=入力データ!$C$111,入力データ!$C$112*12*(1+前提条件!$C$14)^(D$3-$B$3),SUM(入力データ!$C$41:$C$52)*12*(1+前提条件!$C$12)^(D$3-$B$3))) | E20: =IF(E$3="","",IF(MIN(E4,E5)>=入力データ!$C$111,入力データ!$C$112*12*(1+前提条件!$C$14)^(E$3-$B$3),SUM(入力データ!$C$41:$C$52)*12*(1+前提条件!$C$12)^(E$3-$B$3))) | F20: =IF(F$3="","",IF(MIN(F4,F5)>=入力データ!$C$111,入力データ!$C$112*12*(1+前提条件!$C$14)^(F$3-$B$3),SUM(入力データ!$C$41:$C$52)*12*(1+前提条件!$C$12)^(F$3-$B$3))) | G20: =IF(G$3="","",IF(MIN(G4,G5)>=入力データ!$C$111,入力データ!$C$112*12*(1+前提条件!$C$14)^(G$3-$B$3),SUM(入力データ!$C$41:$C$52)*12*(1+前提条件!$C$12)^(G$3-$B$3))) | H20: =IF(H$3="","",IF(MIN(H4,H5)>=入力データ!$C$111,入力データ!$C$112*12*(1+前提条件!$C$14)^(H$3-$B$3),SUM(入力データ!$C$41:$C$52)*12*(1+前提条件!$C$12)^(H$3-$B$3))) | I20: =IF(I$3="","",IF(MIN(I4,I5)>=入力データ!$C$111,入力データ!$C$112*12*(1+前提条件!$C$14)^(I$3-$B$3),SUM(入力データ!$C$41:$C$52)*12*(1+前提条件!$C$12)^(I$3-$B$3))) | ... CW20: =IF(CW$3="","",IF(MIN(CW4,CW5)>=入力データ!$C$111,入力データ!$C$112*12*(1+前提条件!$C$14)^(CW$3-$B$3),SUM(入力データ!$C$41:$C$52)*12*(1+前提条件!$C$12)^(CW$3-$B$3)))
A21: 住居費 | B21: =IF(B$3="","",((IF(入力データ!$C$13="持ち家",IF(B4<=前提条件!$C$44,入力データ!$C$53,0),入力データ!$C$53)+入力データ!$C$54+入力データ!$C$55+入力データ!$C$56)*12+IF(入力データ!$C$13="持ち家",入力データ!$C$83+前提条件!$C$47,入力データ!$C$84+前提条件!$C$48))*(1+前提条件!$C$15)^(B$3-$B$3)) | C21: =IF(C$3="","",((IF(入力データ!$C$13="持ち家",IF(C4<=前提条件!$C$44,入力データ!$C$53,0),入力データ!$C$53)+入力データ!$C$54+入力データ!$C$55+入力データ!$C$56)*12+IF(入力データ!$C$13="持ち家",入力データ!$C$83+前提条件!$C$47,入力データ!$C$84+前提条件!$C$48))*(1+前提条件!$C$15)^(C$3-$B$3)) | D21: =IF(D$3="","",((IF(入力データ!$C$13="持ち家",IF(D4<=前提条件!$C$44,入力データ!$C$53,0),入力データ!$C$53)+入力データ!$C$54+入力データ!$C$55+入力データ!$C$56)*12+IF(入力データ!$C$13="持ち家",入力データ!$C$83+前提条件!$C$47,入力データ!$C$84+前提条件!$C$48))*(1+前提条件!$C$15)^(D$3-$B$3)) | E21: =IF(E$3="","",((IF(入力データ!$C$13="持ち家",IF(E4<=前提条件!$C$44,入力データ!$C$53,0),入力データ!$C$53)+入力データ!$C$54+入力データ!$C$55+入力データ!$C$56)*12+IF(入力データ!$C$13="持ち家",入力データ!$C$83+前提条件!$C$47,入力データ!$C$84+前提条件!$C$48))*(1+前提条件!$C$15)^(E$3-$B$3)) | F21: =IF(F$3="","",((IF(入力データ!$C$13="持ち家",IF(F4<=前提条件!$C$44,入力データ!$C$53,0),入力データ!$C$53)+入力データ!$C$54+入力データ!$C$55+入力データ!$C$56)*12+IF(入力データ!$C$13="持ち家",入力データ!$C$83+前提条件!$C$47,入力データ!$C$84+前提条件!$C$48))*(1+前提条件!$C$15)^(F$3-$B$3)) | G21: =IF(G$3="","",((IF(入力データ!$C$13="持ち家",IF(G4<=前提条件!$C$44,入力データ!$C$53,0),入力データ!$C$53)+入力データ!$C$54+入力データ!$C$55+入力データ!$C$56)*12+IF(入力データ!$C$13="持ち家",入力データ!$C$83+前提条件!$C$47,入力データ!$C$84+前提条件!$C$48))*(1+前提条件!$C$15)^(G$3-$B$3)) | H21: =IF(H$3="","",((IF(入力データ!$C$13="持ち家",IF(H4<=前提条件!$C$44,入力データ!$C$53,0),入力データ!$C$53)+入力データ!$C$54+入力データ!$C$55+入力データ!$C$56)*12+IF(入力データ!$C$13="持ち家",入力データ!$C$83+前提条件!$C$47,入力データ!$C$84+前提条件!$C$48))*(1+前提条件!$C$15)^(H$3-$B$3)) | I21: =IF(I$3="","",((IF(入力データ!$C$13="持ち家",IF(I4<=前提条件!$C$44,入力データ!$C$53,0),入力データ!$C$53)+入力データ!$C$54+入力データ!$C$55+入力データ!$C$56)*12+IF(入力データ!$C$13="持ち家",入力データ!$C$83+前提条件!$C$47,入力データ!$C$84+前提条件!$C$48))*(1+前提条件!$C$15)^(I$3-$B$3)) | ... CW21: =IF(CW$3="","",((IF(入力データ!$C$13="持ち家",IF(CW4<=前提条件!$C$44,入力データ!$C$53,0),入力データ!$C$53)+入力データ!$C$54+入力データ!$C$55+入力データ!$C$56)*12+IF(入力データ!$C$13="持ち家",入力データ!$C$83+前提条件!$C$47,入力データ!$C$84+前提条件!$C$48))*(1+前提条件!$C$15)^(CW$3-$B$3))
A22: 終身系保険料 | B22: =IF(B$3="","",SUMPRODUCT(--ISNUMBER(SEARCH("終身",入力データ!$F$5:$F$20)),--(IFERROR(YEAR(入力データ!$J$5:$J$20),0)<=B$3),--(IFERROR(YEAR(入力データ!$K$5:$K$20),9999)>=B$3),入力データ!$M$5:$M$20)*12) | C22: =IF(C$3="","",SUMPRODUCT(--ISNUMBER(SEARCH("終身",入力データ!$F$5:$F$20)),--(IFERROR(YEAR(入力データ!$J$5:$J$20),0)<=C$3),--(IFERROR(YEAR(入力データ!$K$5:$K$20),9999)>=C$3),入力データ!$M$5:$M$20)*12) | D22: =IF(D$3="","",SUMPRODUCT(--ISNUMBER(SEARCH("終身",入力データ!$F$5:$F$20)),--(IFERROR(YEAR(入力データ!$J$5:$J$20),0)<=D$3),--(IFERROR(YEAR(入力データ!$K$5:$K$20),9999)>=D$3),入力データ!$M$5:$M$20)*12) | E22: =IF(E$3="","",SUMPRODUCT(--ISNUMBER(SEARCH("終身",入力データ!$F$5:$F$20)),--(IFERROR(YEAR(入力データ!$J$5:$J$20),0)<=E$3),--(IFERROR(YEAR(入力データ!$K$5:$K$20),9999)>=E$3),入力データ!$M$5:$M$20)*12) | F22: =IF(F$3="","",SUMPRODUCT(--ISNUMBER(SEARCH("終身",入力データ!$F$5:$F$20)),--(IFERROR(YEAR(入力データ!$J$5:$J$20),0)<=F$3),--(IFERROR(YEAR(入力データ!$K$5:$K$20),9999)>=F$3),入力データ!$M$5:$M$20)*12) | G22: =IF(G$3="","",SUMPRODUCT(--ISNUMBER(SEARCH("終身",入力データ!$F$5:$F$20)),--(IFERROR(YEAR(入力データ!$J$5:$J$20),0)<=G$3),--(IFERROR(YEAR(入力データ!$K$5:$K$20),9999)>=G$3),入力データ!$M$5:$M$20)*12) | H22: =IF(H$3="","",SUMPRODUCT(--ISNUMBER(SEARCH("終身",入力データ!$F$5:$F$20)),--(IFERROR(YEAR(入力データ!$J$5:$J$20),0)<=H$3),--(IFERROR(YEAR(入力データ!$K$5:$K$20),9999)>=H$3),入力データ!$M$5:$M$20)*12) | I22: =IF(I$3="","",SUMPRODUCT(--ISNUMBER(SEARCH("終身",入力データ!$F$5:$F$20)),--(IFERROR(YEAR(入力データ!$J$5:$J$20),0)<=I$3),--(IFERROR(YEAR(入力データ!$K$5:$K$20),9999)>=I$3),入力データ!$M$5:$M$20)*12) | ... CW22: =IF(CW$3="","",SUMPRODUCT(--ISNUMBER(SEARCH("終身",入力データ!$F$5:$F$20)),--(IFERROR(YEAR(入力データ!$J$5:$J$20),0)<=CW$3),--(IFERROR(YEAR(入力データ!$K$5:$K$20),9999)>=CW$3),入力データ!$M$5:$M$20)*12)
A23: 定期系保険料 | B23: =IF(B$3="","",SUMPRODUCT(--ISERROR(SEARCH("終身",入力データ!$F$5:$F$20)),--(IFERROR(YEAR(入力データ!$J$5:$J$20),0)<=B$3),--(IFERROR(YEAR(入力データ!$K$5:$K$20),9999)>=B$3),入力データ!$M$5:$M$20)*12) | C23: =IF(C$3="","",SUMPRODUCT(--ISERROR(SEARCH("終身",入力データ!$F$5:$F$20)),--(IFERROR(YEAR(入力データ!$J$5:$J$20),0)<=C$3),--(IFERROR(YEAR(入力データ!$K$5:$K$20),9999)>=C$3),入力データ!$M$5:$M$20)*12) | D23: =IF(D$3="","",SUMPRODUCT(--ISERROR(SEARCH("終身",入力データ!$F$5:$F$20)),--(IFERROR(YEAR(入力データ!$J$5:$J$20),0)<=D$3),--(IFERROR(YEAR(入力データ!$K$5:$K$20),9999)>=D$3),入力データ!$M$5:$M$20)*12) | E23: =IF(E$3="","",SUMPRODUCT(--ISERROR(SEARCH("終身",入力データ!$F$5:$F$20)),--(IFERROR(YEAR(入力データ!$J$5:$J$20),0)<=E$3),--(IFERROR(YEAR(入力データ!$K$5:$K$20),9999)>=E$3),入力データ!$M$5:$M$20)*12) | F23: =IF(F$3="","",SUMPRODUCT(--ISERROR(SEARCH("終身",入力データ!$F$5:$F$20)),--(IFERROR(YEAR(入力データ!$J$5:$J$20),0)<=F$3),--(IFERROR(YEAR(入力データ!$K$5:$K$20),9999)>=F$3),入力データ!$M$5:$M$20)*12) | G23: =IF(G$3="","",SUMPRODUCT(--ISERROR(SEARCH("終身",入力データ!$F$5:$F$20)),--(IFERROR(YEAR(入力データ!$J$5:$J$20),0)<=G$3),--(IFERROR(YEAR(入力データ!$K$5:$K$20),9999)>=G$3),入力データ!$M$5:$M$20)*12) | H23: =IF(H$3="","",SUMPRODUCT(--ISERROR(SEARCH("終身",入力データ!$F$5:$F$20)),--(IFERROR(YEAR(入力データ!$J$5:$J$20),0)<=H$3),--(IFERROR(YEAR(入力データ!$K$5:$K$20),9999)>=H$3),入力データ!$M$5:$M$20)*12) | I23: =IF(I$3="","",SUMPRODUCT(--ISERROR(SEARCH("終身",入力データ!$F$5:$F$20)),--(IFERROR(YEAR(入力データ!$J$5:$J$20),0)<=I$3),--(IFERROR(YEAR(入力データ!$K$5:$K$20),9999)>=I$3),入力データ!$M$5:$M$20)*12) | ... CW23: =IF(CW$3="","",SUMPRODUCT(--ISERROR(SEARCH("終身",入力データ!$F$5:$F$20)),--(IFERROR(YEAR(入力データ!$J$5:$J$20),0)<=CW$3),--(IFERROR(YEAR(入力データ!$K$5:$K$20),9999)>=CW$3),入力データ!$M$5:$M$20)*12)
A24: 教育費 | B24: =IF(B$3="","",IF(入力データ!$C$17<=0,0,IF(B$3="","",((SUM(入力データ!$C$58:$C$61)*12)+IF(B6="",0,IF(B6<=5,IF(入力データ!$G$25="私立",前提条件!$C$22,前提条件!$C$21),IF(B6<=11,IF(入力データ!$H$25="私立",前提条件!$C$24,前提条件!$C$23),IF(B6<=14,IF(入力データ!$I$25="私立",前提条件!$C$26,前提条件!$C$25),IF(B6<=17,IF(入力データ!$J$25="私立",前提条件!$C$28,前提条件!$C$27),IF(B6<=21,IF(入力データ!$K$25="国公立",前提条件!$C$29,IF(入力データ!$K$25="私立理系",前提条件!$C$31,前提条件!$C$30))+IF(入力データ!$L$25="下宿",前提条件!$C$32,0)+IF(B6=18,前提条件!$C$33,0),0))))))+IF(B7="",0,IF(B7<=5,IF(入力データ!$G$26="私立",前提条件!$C$22,前提条件!$C$21),IF(B7<=11,IF(入力データ!$H$26="私立",前提条件!$C$24,前提条件!$C$23),IF(B7<=14,IF(入力データ!$I$26="私立",前提条件!$C$26,前提条件!$C$25),IF(B7<=17,IF(入力データ!$J$26="私立",前提条件!$C$28,前提条件!$C$27),IF(B7<=21,IF(入力データ!$K$26="国公立",前提条件!$C$29,IF(入力データ!$K$26="私立理系",前提条件!$C$31,前提条件!$C$30))+IF(入力データ!$L$26="下宿",前提条件!$C$32,0)+IF(B7=18,前提条件!$C$33,0),0))))))+IF(B8="",0,IF(B8<=5,IF(入力データ!$G$27="私立",前提条件!$C$22,前提条件!$C$21),IF(B8<=11,IF(入力データ!$H$27="私立",前提条件!$C$24,前提条件!$C$23),IF(B8<=14,IF(入力データ!$I$27="私立",前提条件!$C$26,前提条件!$C$25),IF(B8<=17,IF(入力データ!$J$27="私立",前提条件!$C$28,前提条件!$C$27),IF(B8<=21,IF(入力データ!$K$27="国公立",前提条件!$C$29,IF(入力データ!$K$27="私立理系",前提条件!$C$31,前提条件!$C$30))+IF(入力データ!$L$27="下宿",前提条件!$C$32,0)+IF(B8=18,前提条件!$C$33,0),0)))))))*(1+前提条件!$C$13)^(B$3-$B$3)))) | C24: =IF(C$3="","",IF(入力データ!$C$17<=0,0,IF(C$3="","",((SUM(入力データ!$C$58:$C$61)*12)+IF(C6="",0,IF(C6<=5,IF(入力データ!$G$25="私立",前提条件!$C$22,前提条件!$C$21),IF(C6<=11,IF(入力データ!$H$25="私立",前提条件!$C$24,前提条件!$C$23),IF(C6<=14,IF(入力データ!$I$25="私立",前提条件!$C$26,前提条件!$C$25),IF(C6<=17,IF(入力データ!$J$25="私立",前提条件!$C$28,前提条件!$C$27),IF(C6<=21,IF(入力データ!$K$25="国公立",前提条件!$C$29,IF(入力データ!$K$25="私立理系",前提条件!$C$31,前提条件!$C$30))+IF(入力データ!$L$25="下宿",前提条件!$C$32,0)+IF(C6=18,前提条件!$C$33,0),0))))))+IF(C7="",0,IF(C7<=5,IF(入力データ!$G$26="私立",前提条件!$C$22,前提条件!$C$21),IF(C7<=11,IF(入力データ!$H$26="私立",前提条件!$C$24,前提条件!$C$23),IF(C7<=14,IF(入力データ!$I$26="私立",前提条件!$C$26,前提条件!$C$25),IF(C7<=17,IF(入力データ!$J$26="私立",前提条件!$C$28,前提条件!$C$27),IF(C7<=21,IF(入力データ!$K$26="国公立",前提条件!$C$29,IF(入力データ!$K$26="私立理系",前提条件!$C$31,前提条件!$C$30))+IF(入力データ!$L$26="下宿",前提条件!$C$32,0)+IF(C7=18,前提条件!$C$33,0),0))))))+IF(C8="",0,IF(C8<=5,IF(入力データ!$G$27="私立",前提条件!$C$22,前提条件!$C$21),IF(C8<=11,IF(入力データ!$H$27="私立",前提条件!$C$24,前提条件!$C$23),IF(C8<=14,IF(入力データ!$I$27="私立",前提条件!$C$26,前提条件!$C$25),IF(C8<=17,IF(入力データ!$J$27="私立",前提条件!$C$28,前提条件!$C$27),IF(C8<=21,IF(入力データ!$K$27="国公立",前提条件!$C$29,IF(入力データ!$K$27="私立理系",前提条件!$C$31,前提条件!$C$30))+IF(入力データ!$L$27="下宿",前提条件!$C$32,0)+IF(C8=18,前提条件!$C$33,0),0)))))))*(1+前提条件!$C$13)^(C$3-$B$3)))) | D24: =IF(D$3="","",IF(入力データ!$C$17<=0,0,IF(D$3="","",((SUM(入力データ!$C$58:$C$61)*12)+IF(D6="",0,IF(D6<=5,IF(入力データ!$G$25="私立",前提条件!$C$22,前提条件!$C$21),IF(D6<=11,IF(入力データ!$H$25="私立",前提条件!$C$24,前提条件!$C$23),IF(D6<=14,IF(入力データ!$I$25="私立",前提条件!$C$26,前提条件!$C$25),IF(D6<=17,IF(入力データ!$J$25="私立",前提条件!$C$28,前提条件!$C$27),IF(D6<=21,IF(入力データ!$K$25="国公立",前提条件!$C$29,IF(入力データ!$K$25="私立理系",前提条件!$C$31,前提条件!$C$30))+IF(入力データ!$L$25="下宿",前提条件!$C$32,0)+IF(D6=18,前提条件!$C$33,0),0))))))+IF(D7="",0,IF(D7<=5,IF(入力データ!$G$26="私立",前提条件!$C$22,前提条件!$C$21),IF(D7<=11,IF(入力データ!$H$26="私立",前提条件!$C$24,前提条件!$C$23),IF(D7<=14,IF(入力データ!$I$26="私立",前提条件!$C$26,前提条件!$C$25),IF(D7<=17,IF(入力データ!$J$26="私立",前提条件!$C$28,前提条件!$C$27),IF(D7<=21,IF(入力データ!$K$26="国公立",前提条件!$C$29,IF(入力データ!$K$26="私立理系",前提条件!$C$31,前提条件!$C$30))+IF(入力データ!$L$26="下宿",前提条件!$C$32,0)+IF(D7=18,前提条件!$C$33,0),0))))))+IF(D8="",0,IF(D8<=5,IF(入力データ!$G$27="私立",前提条件!$C$22,前提条件!$C$21),IF(D8<=11,IF(入力データ!$H$27="私立",前提条件!$C$24,前提条件!$C$23),IF(D8<=14,IF(入力データ!$I$27="私立",前提条件!$C$26,前提条件!$C$25),IF(D8<=17,IF(入力データ!$J$27="私立",前提条件!$C$28,前提条件!$C$27),IF(D8<=21,IF(入力データ!$K$27="国公立",前提条件!$C$29,IF(入力データ!$K$27="私立理系",前提条件!$C$31,前提条件!$C$30))+IF(入力データ!$L$27="下宿",前提条件!$C$32,0)+IF(D8=18,前提条件!$C$33,0),0)))))))*(1+前提条件!$C$13)^(D$3-$B$3)))) | E24: =IF(E$3="","",IF(入力データ!$C$17<=0,0,IF(E$3="","",((SUM(入力データ!$C$58:$C$61)*12)+IF(E6="",0,IF(E6<=5,IF(入力データ!$G$25="私立",前提条件!$C$22,前提条件!$C$21),IF(E6<=11,IF(入力データ!$H$25="私立",前提条件!$C$24,前提条件!$C$23),IF(E6<=14,IF(入力データ!$I$25="私立",前提条件!$C$26,前提条件!$C$25),IF(E6<=17,IF(入力データ!$J$25="私立",前提条件!$C$28,前提条件!$C$27),IF(E6<=21,IF(入力データ!$K$25="国公立",前提条件!$C$29,IF(入力データ!$K$25="私立理系",前提条件!$C$31,前提条件!$C$30))+IF(入力データ!$L$25="下宿",前提条件!$C$32,0)+IF(E6=18,前提条件!$C$33,0),0))))))+IF(E7="",0,IF(E7<=5,IF(入力データ!$G$26="私立",前提条件!$C$22,前提条件!$C$21),IF(E7<=11,IF(入力データ!$H$26="私立",前提条件!$C$24,前提条件!$C$23),IF(E7<=14,IF(入力データ!$I$26="私立",前提条件!$C$26,前提条件!$C$25),IF(E7<=17,IF(入力データ!$J$26="私立",前提条件!$C$28,前提条件!$C$27),IF(E7<=21,IF(入力データ!$K$26="国公立",前提条件!$C$29,IF(入力データ!$K$26="私立理系",前提条件!$C$31,前提条件!$C$30))+IF(入力データ!$L$26="下宿",前提条件!$C$32,0)+IF(E7=18,前提条件!$C$33,0),0))))))+IF(E8="",0,IF(E8<=5,IF(入力データ!$G$27="私立",前提条件!$C$22,前提条件!$C$21),IF(E8<=11,IF(入力データ!$H$27="私立",前提条件!$C$24,前提条件!$C$23),IF(E8<=14,IF(入力データ!$I$27="私立",前提条件!$C$26,前提条件!$C$25),IF(E8<=17,IF(入力データ!$J$27="私立",前提条件!$C$28,前提条件!$C$27),IF(E8<=21,IF(入力データ!$K$27="国公立",前提条件!$C$29,IF(入力データ!$K$27="私立理系",前提条件!$C$31,前提条件!$C$30))+IF(入力データ!$L$27="下宿",前提条件!$C$32,0)+IF(E8=18,前提条件!$C$33,0),0)))))))*(1+前提条件!$C$13)^(E$3-$B$3)))) | F24: =IF(F$3="","",IF(入力データ!$C$17<=0,0,IF(F$3="","",((SUM(入力データ!$C$58:$C$61)*12)+IF(F6="",0,IF(F6<=5,IF(入力データ!$G$25="私立",前提条件!$C$22,前提条件!$C$21),IF(F6<=11,IF(入力データ!$H$25="私立",前提条件!$C$24,前提条件!$C$23),IF(F6<=14,IF(入力データ!$I$25="私立",前提条件!$C$26,前提条件!$C$25),IF(F6<=17,IF(入力データ!$J$25="私立",前提条件!$C$28,前提条件!$C$27),IF(F6<=21,IF(入力データ!$K$25="国公立",前提条件!$C$29,IF(入力データ!$K$25="私立理系",前提条件!$C$31,前提条件!$C$30))+IF(入力データ!$L$25="下宿",前提条件!$C$32,0)+IF(F6=18,前提条件!$C$33,0),0))))))+IF(F7="",0,IF(F7<=5,IF(入力データ!$G$26="私立",前提条件!$C$22,前提条件!$C$21),IF(F7<=11,IF(入力データ!$H$26="私立",前提条件!$C$24,前提条件!$C$23),IF(F7<=14,IF(入力データ!$I$26="私立",前提条件!$C$26,前提条件!$C$25),IF(F7<=17,IF(入力データ!$J$26="私立",前提条件!$C$28,前提条件!$C$27),IF(F7<=21,IF(入力データ!$K$26="国公立",前提条件!$C$29,IF(入力データ!$K$26="私立理系",前提条件!$C$31,前提条件!$C$30))+IF(入力データ!$L$26="下宿",前提条件!$C$32,0)+IF(F7=18,前提条件!$C$33,0),0))))))+IF(F8="",0,IF(F8<=5,IF(入力データ!$G$27="私立",前提条件!$C$22,前提条件!$C$21),IF(F8<=11,IF(入力データ!$H$27="私立",前提条件!$C$24,前提条件!$C$23),IF(F8<=14,IF(入力データ!$I$27="私立",前提条件!$C$26,前提条件!$C$25),IF(F8<=17,IF(入力データ!$J$27="私立",前提条件!$C$28,前提条件!$C$27),IF(F8<=21,IF(入力データ!$K$27="国公立",前提条件!$C$29,IF(入力データ!$K$27="私立理系",前提条件!$C$31,前提条件!$C$30))+IF(入力データ!$L$27="下宿",前提条件!$C$32,0)+IF(F8=18,前提条件!$C$33,0),0)))))))*(1+前提条件!$C$13)^(F$3-$B$3)))) | G24: =IF(G$3="","",IF(入力データ!$C$17<=0,0,IF(G$3="","",((SUM(入力データ!$C$58:$C$61)*12)+IF(G6="",0,IF(G6<=5,IF(入力データ!$G$25="私立",前提条件!$C$22,前提条件!$C$21),IF(G6<=11,IF(入力データ!$H$25="私立",前提条件!$C$24,前提条件!$C$23),IF(G6<=14,IF(入力データ!$I$25="私立",前提条件!$C$26,前提条件!$C$25),IF(G6<=17,IF(入力データ!$J$25="私立",前提条件!$C$28,前提条件!$C$27),IF(G6<=21,IF(入力データ!$K$25="国公立",前提条件!$C$29,IF(入力データ!$K$25="私立理系",前提条件!$C$31,前提条件!$C$30))+IF(入力データ!$L$25="下宿",前提条件!$C$32,0)+IF(G6=18,前提条件!$C$33,0),0))))))+IF(G7="",0,IF(G7<=5,IF(入力データ!$G$26="私立",前提条件!$C$22,前提条件!$C$21),IF(G7<=11,IF(入力データ!$H$26="私立",前提条件!$C$24,前提条件!$C$23),IF(G7<=14,IF(入力データ!$I$26="私立",前提条件!$C$26,前提条件!$C$25),IF(G7<=17,IF(入力データ!$J$26="私立",前提条件!$C$28,前提条件!$C$27),IF(G7<=21,IF(入力データ!$K$26="国公立",前提条件!$C$29,IF(入力データ!$K$26="私立理系",前提条件!$C$31,前提条件!$C$30))+IF(入力データ!$L$26="下宿",前提条件!$C$32,0)+IF(G7=18,前提条件!$C$33,0),0))))))+IF(G8="",0,IF(G8<=5,IF(入力データ!$G$27="私立",前提条件!$C$22,前提条件!$C$21),IF(G8<=11,IF(入力データ!$H$27="私立",前提条件!$C$24,前提条件!$C$23),IF(G8<=14,IF(入力データ!$I$27="私立",前提条件!$C$26,前提条件!$C$25),IF(G8<=17,IF(入力データ!$J$27="私立",前提条件!$C$28,前提条件!$C$27),IF(G8<=21,IF(入力データ!$K$27="国公立",前提条件!$C$29,IF(入力データ!$K$27="私立理系",前提条件!$C$31,前提条件!$C$30))+IF(入力データ!$L$27="下宿",前提条件!$C$32,0)+IF(G8=18,前提条件!$C$33,0),0)))))))*(1+前提条件!$C$13)^(G$3-$B$3)))) | H24: =IF(H$3="","",IF(入力データ!$C$17<=0,0,IF(H$3="","",((SUM(入力データ!$C$58:$C$61)*12)+IF(H6="",0,IF(H6<=5,IF(入力データ!$G$25="私立",前提条件!$C$22,前提条件!$C$21),IF(H6<=11,IF(入力データ!$H$25="私立",前提条件!$C$24,前提条件!$C$23),IF(H6<=14,IF(入力データ!$I$25="私立",前提条件!$C$26,前提条件!$C$25),IF(H6<=17,IF(入力データ!$J$25="私立",前提条件!$C$28,前提条件!$C$27),IF(H6<=21,IF(入力データ!$K$25="国公立",前提条件!$C$29,IF(入力データ!$K$25="私立理系",前提条件!$C$31,前提条件!$C$30))+IF(入力データ!$L$25="下宿",前提条件!$C$32,0)+IF(H6=18,前提条件!$C$33,0),0))))))+IF(H7="",0,IF(H7<=5,IF(入力データ!$G$26="私立",前提条件!$C$22,前提条件!$C$21),IF(H7<=11,IF(入力データ!$H$26="私立",前提条件!$C$24,前提条件!$C$23),IF(H7<=14,IF(入力データ!$I$26="私立",前提条件!$C$26,前提条件!$C$25),IF(H7<=17,IF(入力データ!$J$26="私立",前提条件!$C$28,前提条件!$C$27),IF(H7<=21,IF(入力データ!$K$26="国公立",前提条件!$C$29,IF(入力データ!$K$26="私立理系",前提条件!$C$31,前提条件!$C$30))+IF(入力データ!$L$26="下宿",前提条件!$C$32,0)+IF(H7=18,前提条件!$C$33,0),0))))))+IF(H8="",0,IF(H8<=5,IF(入力データ!$G$27="私立",前提条件!$C$22,前提条件!$C$21),IF(H8<=11,IF(入力データ!$H$27="私立",前提条件!$C$24,前提条件!$C$23),IF(H8<=14,IF(入力データ!$I$27="私立",前提条件!$C$26,前提条件!$C$25),IF(H8<=17,IF(入力データ!$J$27="私立",前提条件!$C$28,前提条件!$C$27),IF(H8<=21,IF(入力データ!$K$27="国公立",前提条件!$C$29,IF(入力データ!$K$27="私立理系",前提条件!$C$31,前提条件!$C$30))+IF(入力データ!$L$27="下宿",前提条件!$C$32,0)+IF(H8=18,前提条件!$C$33,0),0)))))))*(1+前提条件!$C$13)^(H$3-$B$3)))) | I24: =IF(I$3="","",IF(入力データ!$C$17<=0,0,IF(I$3="","",((SUM(入力データ!$C$58:$C$61)*12)+IF(I6="",0,IF(I6<=5,IF(入力データ!$G$25="私立",前提条件!$C$22,前提条件!$C$21),IF(I6<=11,IF(入力データ!$H$25="私立",前提条件!$C$24,前提条件!$C$23),IF(I6<=14,IF(入力データ!$I$25="私立",前提条件!$C$26,前提条件!$C$25),IF(I6<=17,IF(入力データ!$J$25="私立",前提条件!$C$28,前提条件!$C$27),IF(I6<=21,IF(入力データ!$K$25="国公立",前提条件!$C$29,IF(入力データ!$K$25="私立理系",前提条件!$C$31,前提条件!$C$30))+IF(入力データ!$L$25="下宿",前提条件!$C$32,0)+IF(I6=18,前提条件!$C$33,0),0))))))+IF(I7="",0,IF(I7<=5,IF(入力データ!$G$26="私立",前提条件!$C$22,前提条件!$C$21),IF(I7<=11,IF(入力データ!$H$26="私立",前提条件!$C$24,前提条件!$C$23),IF(I7<=14,IF(入力データ!$I$26="私立",前提条件!$C$26,前提条件!$C$25),IF(I7<=17,IF(入力データ!$J$26="私立",前提条件!$C$28,前提条件!$C$27),IF(I7<=21,IF(入力データ!$K$26="国公立",前提条件!$C$29,IF(入力データ!$K$26="私立理系",前提条件!$C$31,前提条件!$C$30))+IF(入力データ!$L$26="下宿",前提条件!$C$32,0)+IF(I7=18,前提条件!$C$33,0),0))))))+IF(I8="",0,IF(I8<=5,IF(入力データ!$G$27="私立",前提条件!$C$22,前提条件!$C$21),IF(I8<=11,IF(入力データ!$H$27="私立",前提条件!$C$24,前提条件!$C$23),IF(I8<=14,IF(入力データ!$I$27="私立",前提条件!$C$26,前提条件!$C$25),IF(I8<=17,IF(入力データ!$J$27="私立",前提条件!$C$28,前提条件!$C$27),IF(I8<=21,IF(入力データ!$K$27="国公立",前提条件!$C$29,IF(入力データ!$K$27="私立理系",前提条件!$C$31,前提条件!$C$30))+IF(入力データ!$L$27="下宿",前提条件!$C$32,0)+IF(I8=18,前提条件!$C$33,0),0)))))))*(1+前提条件!$C$13)^(I$3-$B$3)))) | ... CW24: =IF(CW$3="","",IF(入力データ!$C$17<=0,0,IF(CW$3="","",((SUM(入力データ!$C$58:$C$61)*12)+IF(CW6="",0,IF(CW6<=5,IF(入力データ!$G$25="私立",前提条件!$C$22,前提条件!$C$21),IF(CW6<=11,IF(入力データ!$H$25="私立",前提条件!$C$24,前提条件!$C$23),IF(CW6<=14,IF(入力データ!$I$25="私立",前提条件!$C$26,前提条件!$C$25),IF(CW6<=17,IF(入力データ!$J$25="私立",前提条件!$C$28,前提条件!$C$27),IF(CW6<=21,IF(入力データ!$K$25="国公立",前提条件!$C$29,IF(入力データ!$K$25="私立理系",前提条件!$C$31,前提条件!$C$30))+IF(入力データ!$L$25="下宿",前提条件!$C$32,0)+IF(CW6=18,前提条件!$C$33,0),0))))))+IF(CW7="",0,IF(CW7<=5,IF(入力データ!$G$26="私立",前提条件!$C$22,前提条件!$C$21),IF(CW7<=11,IF(入力データ!$H$26="私立",前提条件!$C$24,前提条件!$C$23),IF(CW7<=14,IF(入力データ!$I$26="私立",前提条件!$C$26,前提条件!$C$25),IF(CW7<=17,IF(入力データ!$J$26="私立",前提条件!$C$28,前提条件!$C$27),IF(CW7<=21,IF(入力データ!$K$26="国公立",前提条件!$C$29,IF(入力データ!$K$26="私立理系",前提条件!$C$31,前提条件!$C$30))+IF(入力データ!$L$26="下宿",前提条件!$C$32,0)+IF(CW7=18,前提条件!$C$33,0),0))))))+IF(CW8="",0,IF(CW8<=5,IF(入力データ!$G$27="私立",前提条件!$C$22,前提条件!$C$21),IF(CW8<=11,IF(入力データ!$H$27="私立",前提条件!$C$24,前提条件!$C$23),IF(CW8<=14,IF(入力データ!$I$27="私立",前提条件!$C$26,前提条件!$C$25),IF(CW8<=17,IF(入力データ!$J$27="私立",前提条件!$C$28,前提条件!$C$27),IF(CW8<=21,IF(入力データ!$K$27="国公立",前提条件!$C$29,IF(入力データ!$K$27="私立理系",前提条件!$C$31,前提条件!$C$30))+IF(入力データ!$L$27="下宿",前提条件!$C$32,0)+IF(CW8=18,前提条件!$C$33,0),0)))))))*(1+前提条件!$C$13)^(CW$3-$B$3))))
A25: 車関連費 | B25: =IF(B$3="","",N(入力データ!$C$69)*12*(1+前提条件!$C$12)^(B$3-$B$3)) | C25: =IF(C$3="","",N(入力データ!$C$69)*12*(1+前提条件!$C$12)^(C$3-$B$3)) | D25: =IF(D$3="","",N(入力データ!$C$69)*12*(1+前提条件!$C$12)^(D$3-$B$3)) | E25: =IF(E$3="","",N(入力データ!$C$69)*12*(1+前提条件!$C$12)^(E$3-$B$3)) | F25: =IF(F$3="","",N(入力データ!$C$69)*12*(1+前提条件!$C$12)^(F$3-$B$3)) | G25: =IF(G$3="","",N(入力データ!$C$69)*12*(1+前提条件!$C$12)^(G$3-$B$3)) | H25: =IF(H$3="","",N(入力データ!$C$69)*12*(1+前提条件!$C$12)^(H$3-$B$3)) | I25: =IF(I$3="","",N(入力データ!$C$69)*12*(1+前提条件!$C$12)^(I$3-$B$3)) | ... CW25: =IF(CW$3="","",N(入力データ!$C$69)*12*(1+前提条件!$C$12)^(CW$3-$B$3))
A26: その他支出 | B26: =IF(B$3="","",SUM(入力データ!$C$71:$C$74)*12*(1+前提条件!$C$12)^(B$3-$B$3)) | C26: =IF(C$3="","",SUM(入力データ!$C$71:$C$74)*12*(1+前提条件!$C$12)^(C$3-$B$3)) | D26: =IF(D$3="","",SUM(入力データ!$C$71:$C$74)*12*(1+前提条件!$C$12)^(D$3-$B$3)) | E26: =IF(E$3="","",SUM(入力データ!$C$71:$C$74)*12*(1+前提条件!$C$12)^(E$3-$B$3)) | F26: =IF(F$3="","",SUM(入力データ!$C$71:$C$74)*12*(1+前提条件!$C$12)^(F$3-$B$3)) | G26: =IF(G$3="","",SUM(入力データ!$C$71:$C$74)*12*(1+前提条件!$C$12)^(G$3-$B$3)) | H26: =IF(H$3="","",SUM(入力データ!$C$71:$C$74)*12*(1+前提条件!$C$12)^(H$3-$B$3)) | I26: =IF(I$3="","",SUM(入力データ!$C$71:$C$74)*12*(1+前提条件!$C$12)^(I$3-$B$3)) | ... CW26: =IF(CW$3="","",SUM(入力データ!$C$71:$C$74)*12*(1+前提条件!$C$12)^(CW$3-$B$3))
A27: 一時支出 | B27: =IF(B$3="","",SUM(入力データ!$C$78:$C$82)) | C27: =IF(C$3="","",SUM(入力データ!$C$78:$C$82)) | D27: =IF(D$3="","",SUM(入力データ!$C$78:$C$82)) | E27: =IF(E$3="","",SUM(入力データ!$C$78:$C$82)) | F27: =IF(F$3="","",SUM(入力データ!$C$78:$C$82)) | G27: =IF(G$3="","",SUM(入力データ!$C$78:$C$82)) | H27: =IF(H$3="","",SUM(入力データ!$C$78:$C$82)) | I27: =IF(I$3="","",SUM(入力データ!$C$78:$C$82)) | ... CW27: =IF(CW$3="","",SUM(入力データ!$C$78:$C$82))
A28: 支出合計 | B28: =IF(B$3="","",SUM(B20:B27)) | C28: =IF(C$3="","",SUM(C20:C27)) | D28: =IF(D$3="","",SUM(D20:D27)) | E28: =IF(E$3="","",SUM(E20:E27)) | F28: =IF(F$3="","",SUM(F20:F27)) | G28: =IF(G$3="","",SUM(G20:G27)) | H28: =IF(H$3="","",SUM(H20:H27)) | I28: =IF(I$3="","",SUM(I20:I27)) | ... CW28: =IF(CW$3="","",SUM(CW20:CW27))
A29: 収支・資産
A30: 年間収支 | B30: =IF(B$3="","",B18-B28) | C30: =IF(C$3="","",C18-C28) | D30: =IF(D$3="","",D18-D28) | E30: =IF(E$3="","",E18-E28) | F30: =IF(F$3="","",F18-F28) | G30: =IF(G$3="","",G18-G28) | H30: =IF(H$3="","",H18-H28) | I30: =IF(I$3="","",I18-I28) | ... CW30: =IF(CW$3="","",CW18-CW28)
A31: 預貯金残高 | B31: =IF(B$3="","",MAX(0,B38)) | C31: =IF(C$3="","",MAX(0,C38)) | D31: =IF(D$3="","",MAX(0,D38)) | E31: =IF(E$3="","",MAX(0,E38)) | F31: =IF(F$3="","",MAX(0,F38)) | G31: =IF(G$3="","",MAX(0,G38)) | H31: =IF(H$3="","",MAX(0,H38)) | I31: =IF(I$3="","",MAX(0,I38)) | ... CW31: =IF(CW$3="","",MAX(0,CW38))
A32: 投資資産残高 | B32: =IF(B$3="","",MAX(0,(SUM(入力データ!$C$90:$C$92,入力データ!$C$94)*(1+前提条件!$C$60))+B36-B39)) | C32: =IF(C$3="","",MAX(0,(B32*(1+前提条件!$C$60))+C36-C39)) | D32: =IF(D$3="","",MAX(0,(C32*(1+前提条件!$C$60))+D36-D39)) | E32: =IF(E$3="","",MAX(0,(D32*(1+前提条件!$C$60))+E36-E39)) | F32: =IF(F$3="","",MAX(0,(E32*(1+前提条件!$C$60))+F36-F39)) | G32: =IF(G$3="","",MAX(0,(F32*(1+前提条件!$C$60))+G36-G39)) | H32: =IF(H$3="","",MAX(0,(G32*(1+前提条件!$C$60))+H36-H39)) | I32: =IF(I$3="","",MAX(0,(H32*(1+前提条件!$C$60))+I36-I39)) | J32: =IF(J$3="","",MAX(0,(I32*(1+前提条件!$C$60))+J36-J39)) | ... CW32: =IF(CW$3="","",MAX(0,(CV32*(1+前提条件!$C$60))+CW36-CW39))
A33: 解約返戻金残高 | B33: =IF(B$3="","",MAX(0,(入力データ!$C$93*(1+前提条件!$C$61))+B37-B40)) | C33: =IF(C$3="","",MAX(0,(B33*(1+前提条件!$C$61))+C37-C40)) | D33: =IF(D$3="","",MAX(0,(C33*(1+前提条件!$C$61))+D37-D40)) | E33: =IF(E$3="","",MAX(0,(D33*(1+前提条件!$C$61))+E37-E40)) | F33: =IF(F$3="","",MAX(0,(E33*(1+前提条件!$C$61))+F37-F40)) | G33: =IF(G$3="","",MAX(0,(F33*(1+前提条件!$C$61))+G37-G40)) | H33: =IF(H$3="","",MAX(0,(G33*(1+前提条件!$C$61))+H37-H40)) | I33: =IF(I$3="","",MAX(0,(H33*(1+前提条件!$C$61))+I37-I40)) | J33: =IF(J$3="","",MAX(0,(I33*(1+前提条件!$C$61))+J37-J40)) | ... CW33: =IF(CW$3="","",MAX(0,(CV33*(1+前提条件!$C$61))+CW37-CW40))
A34: 住宅ローン残高 | B34: =IF(B$3="","",MAX(入力データ!$C$95-B41,0)) | C34: =IF(C$3="","",MAX(B34-C41,0)) | D34: =IF(D$3="","",MAX(C34-D41,0)) | E34: =IF(E$3="","",MAX(D34-E41,0)) | F34: =IF(F$3="","",MAX(E34-F41,0)) | G34: =IF(G$3="","",MAX(F34-G41,0)) | H34: =IF(H$3="","",MAX(G34-H41,0)) | I34: =IF(I$3="","",MAX(H34-I41,0)) | J34: =IF(J$3="","",MAX(I34-J41,0)) | ... CW34: =IF(CW$3="","",MAX(CV34-CW41,0))
A35: 保有資産合計（ローン除く） | B35: =IF(B$3="","",B31+B32+B33) | C35: =IF(C$3="","",C31+C32+C33) | D35: =IF(D$3="","",D31+D32+D33) | E35: =IF(E$3="","",E31+E32+E33) | F35: =IF(F$3="","",F31+F32+F33) | G35: =IF(G$3="","",G31+G32+G33) | H35: =IF(H$3="","",H31+H32+H33) | I35: =IF(I$3="","",I31+I32+I33) | ... CW35: =IF(CW$3="","",CW31+CW32+CW33)
A36: 投資積立年額(補助) | B36: =IF(B$3="","",SUM(入力データ!$C$101:$C$103,入力データ!$C$105)*12) | C36: =IF(C$3="","",SUM(入力データ!$C$101:$C$103,入力データ!$C$105)*12) | D36: =IF(D$3="","",SUM(入力データ!$C$101:$C$103,入力データ!$C$105)*12) | E36: =IF(E$3="","",SUM(入力データ!$C$101:$C$103,入力データ!$C$105)*12) | F36: =IF(F$3="","",SUM(入力データ!$C$101:$C$103,入力データ!$C$105)*12) | G36: =IF(G$3="","",SUM(入力データ!$C$101:$C$103,入力データ!$C$105)*12) | H36: =IF(H$3="","",SUM(入力データ!$C$101:$C$103,入力データ!$C$105)*12) | I36: =IF(I$3="","",SUM(入力データ!$C$101:$C$103,入力データ!$C$105)*12) | ... CW36: =IF(CW$3="","",SUM(入力データ!$C$101:$C$103,入力データ!$C$105)*12)
A37: 返戻金積立年額(補助) | B37: =IF(B$3="","",入力データ!$C$104*12) | C37: =IF(C$3="","",入力データ!$C$104*12) | D37: =IF(D$3="","",入力データ!$C$104*12) | E37: =IF(E$3="","",入力データ!$C$104*12) | F37: =IF(F$3="","",入力データ!$C$104*12) | G37: =IF(G$3="","",入力データ!$C$104*12) | H37: =IF(H$3="","",入力データ!$C$104*12) | I37: =IF(I$3="","",入力データ!$C$104*12) | ... CW37: =IF(CW$3="","",入力データ!$C$104*12)
A38: 預貯金前年差引前(補助) | B38: =IF(B$3="","",SUM(入力データ!$C$88:$C$89)+B30-B36-B37) | C38: =IF(C$3="","",B31+C30-C36-C37) | D38: =IF(D$3="","",C31+D30-D36-D37) | E38: =IF(E$3="","",D31+E30-E36-E37) | F38: =IF(F$3="","",E31+F30-F36-F37) | G38: =IF(G$3="","",F31+G30-G36-G37) | H38: =IF(H$3="","",G31+H30-H36-H37) | I38: =IF(I$3="","",H31+I30-I36-I37) | J38: =IF(J$3="","",I31+J30-J36-J37) | ... CW38: =IF(CW$3="","",CV31+CW30-CW36-CW37)
A39: 投資取り崩し額(補助) | B39: =IF(B$3="","",MAX(0,-B38)) | C39: =IF(C$3="","",MAX(0,-C38)) | D39: =IF(D$3="","",MAX(0,-D38)) | E39: =IF(E$3="","",MAX(0,-E38)) | F39: =IF(F$3="","",MAX(0,-F38)) | G39: =IF(G$3="","",MAX(0,-G38)) | H39: =IF(H$3="","",MAX(0,-H38)) | I39: =IF(I$3="","",MAX(0,-I38)) | ... CW39: =IF(CW$3="","",MAX(0,-CW38))
A40: 返戻金取り崩し額(補助) | B40: =IF(B$3="","",MAX(0,B39-((SUM(入力データ!$C$90:$C$92,入力データ!$C$94)*(1+前提条件!$C$60))+B36))) | C40: =IF(C$3="","",MAX(0,C39-((B32*(1+前提条件!$C$60))+C36))) | D40: =IF(D$3="","",MAX(0,D39-((C32*(1+前提条件!$C$60))+D36))) | E40: =IF(E$3="","",MAX(0,E39-((D32*(1+前提条件!$C$60))+E36))) | F40: =IF(F$3="","",MAX(0,F39-((E32*(1+前提条件!$C$60))+F36))) | G40: =IF(G$3="","",MAX(0,G39-((F32*(1+前提条件!$C$60))+G36))) | H40: =IF(H$3="","",MAX(0,H39-((G32*(1+前提条件!$C$60))+H36))) | I40: =IF(I$3="","",MAX(0,I39-((H32*(1+前提条件!$C$60))+I36))) | J40: =IF(J$3="","",MAX(0,J39-((I32*(1+前提条件!$C$60))+J36))) | ... CW40: =IF(CW$3="","",MAX(0,CW39-((CV32*(1+前提条件!$C$60))+CW36)))
A41: 年間住宅ローン元本返済(補助) | B41: =IF(B$3="","",IF(AND(B4<>"",B4<=前提条件!$C$44,入力データ!$C$95>0),入力データ!$C$95/MAX(1,前提条件!$C$44-B4+1),0)) | C41: =IF(C$3="","",IF(C4<=前提条件!$C$44,$B$41,0)) | D41: =IF(D$3="","",IF(D4<=前提条件!$C$44,$B$41,0)) | E41: =IF(E$3="","",IF(E4<=前提条件!$C$44,$B$41,0)) | F41: =IF(F$3="","",IF(F4<=前提条件!$C$44,$B$41,0)) | G41: =IF(G$3="","",IF(G4<=前提条件!$C$44,$B$41,0)) | H41: =IF(H$3="","",IF(H4<=前提条件!$C$44,$B$41,0)) | I41: =IF(I$3="","",IF(I4<=前提条件!$C$44,$B$41,0)) | J41: =IF(J$3="","",IF(J4<=前提条件!$C$44,$B$41,0)) | ... CW41: =IF(CW$3="","",IF(CW4<=前提条件!$C$44,$B$41,0))
A42: 老後期フラグ(補助) | B42: =IF(B$3="","",IF(AND(B4>=入力データ!$C$111,B5>=入力データ!$C$111),1,0)) | C42: =IF(C$3="","",IF(AND(C4>=入力データ!$C$111,C5>=入力データ!$C$111),1,0)) | D42: =IF(D$3="","",IF(AND(D4>=入力データ!$C$111,D5>=入力データ!$C$111),1,0)) | E42: =IF(E$3="","",IF(AND(E4>=入力データ!$C$111,E5>=入力データ!$C$111),1,0)) | F42: =IF(F$3="","",IF(AND(F4>=入力データ!$C$111,F5>=入力データ!$C$111),1,0)) | G42: =IF(G$3="","",IF(AND(G4>=入力データ!$C$111,G5>=入力データ!$C$111),1,0)) | H42: =IF(H$3="","",IF(AND(H4>=入力データ!$C$111,H5>=入力データ!$C$111),1,0)) | I42: =IF(I$3="","",IF(AND(I4>=入力データ!$C$111,I5>=入力データ!$C$111),1,0)) | ... CW42: =IF(CW$3="","",IF(AND(CW4>=入力データ!$C$111,CW5>=入力データ!$C$111),1,0))
A43: 老後不足額(補助) | B43: =IF(B$3="","",IF(B42=1,MAX(0,-B30),0)) | C43: =IF(C$3="","",IF(C42=1,MAX(0,-C30),0)) | D43: =IF(D$3="","",IF(D42=1,MAX(0,-D30),0)) | E43: =IF(E$3="","",IF(E42=1,MAX(0,-E30),0)) | F43: =IF(F$3="","",IF(F42=1,MAX(0,-F30),0)) | G43: =IF(G$3="","",IF(G42=1,MAX(0,-G30),0)) | H43: =IF(H$3="","",IF(H42=1,MAX(0,-H30),0)) | I43: =IF(I$3="","",IF(I42=1,MAX(0,-I30),0)) | ... CW43: =IF(CW$3="","",IF(CW42=1,MAX(0,-CW30),0))
A44: 保有資産合計（参考） | B44: =IF(B$3="","",B31+B32+B33) | C44: =IF(C$3="","",C31+C32+C33) | D44: =IF(D$3="","",D31+D32+D33) | E44: =IF(E$3="","",E31+E32+E33) | F44: =IF(F$3="","",F31+F32+F33) | G44: =IF(G$3="","",G31+G32+G33) | H44: =IF(H$3="","",H31+H32+H33) | I44: =IF(I$3="","",I31+I32+I33) | ... CW44: =IF(CW$3="","",CW31+CW32+CW33)
A45: 負債合計（参考） | B45: =IF(B$3="","",B34) | C45: =IF(C$3="","",C34) | D45: =IF(D$3="","",D34) | E45: =IF(E$3="","",E34) | F45: =IF(F$3="","",F34) | G45: =IF(G$3="","",G34) | H45: =IF(H$3="","",H34) | I45: =IF(I$3="","",I34) | ... CW45: =IF(CW$3="","",CW34)

Sheet CF表（ご主人様死亡時）
A1: CF表（ご主人様死亡時 / 年次CF / 左→右に年が進む）
A2: 試算終了年 | B2: =MAX(IF(入力データ!$C$10<>"",YEAR(入力データ!$C$10)+100,0),IF(入力データ!$C$11<>"",YEAR(入力データ!$C$11)+100,0))
A3: 年 | B3: =IF(YEAR(入力データ!$C$5)>$B$2,"",YEAR(入力データ!$C$5)) | C3: =IF(B3="","",IF(B3+1>$B$2,"",B3+1)) | D3: =IF(C3="","",IF(C3+1>$B$2,"",C3+1)) | E3: =IF(D3="","",IF(D3+1>$B$2,"",D3+1)) | F3: =IF(E3="","",IF(E3+1>$B$2,"",E3+1)) | G3: =IF(F3="","",IF(F3+1>$B$2,"",F3+1)) | H3: =IF(G3="","",IF(G3+1>$B$2,"",G3+1)) | I3: =IF(H3="","",IF(H3+1>$B$2,"",H3+1)) | J3: =IF(I3="","",IF(I3+1>$B$2,"",I3+1)) | ... CW3: =IF(CV3="","",IF(CV3+1>$B$2,"",CV3+1))
A4: ご主人様年齢 | B4: =IF(B$3="","",IF(入力データ!$C$10="","",YEAR(DATE(B$3,12,31))-YEAR(入力データ!$C$10)-IF(DATE(B$3,12,31)<DATE(B$3,MONTH(入力データ!$C$10),DAY(入力データ!$C$10)),1,0))) | C4: =IF(C$3="","",IF(入力データ!$C$10="","",YEAR(DATE(C$3,12,31))-YEAR(入力データ!$C$10)-IF(DATE(C$3,12,31)<DATE(C$3,MONTH(入力データ!$C$10),DAY(入力データ!$C$10)),1,0))) | D4: =IF(D$3="","",IF(入力データ!$C$10="","",YEAR(DATE(D$3,12,31))-YEAR(入力データ!$C$10)-IF(DATE(D$3,12,31)<DATE(D$3,MONTH(入力データ!$C$10),DAY(入力データ!$C$10)),1,0))) | E4: =IF(E$3="","",IF(入力データ!$C$10="","",YEAR(DATE(E$3,12,31))-YEAR(入力データ!$C$10)-IF(DATE(E$3,12,31)<DATE(E$3,MONTH(入力データ!$C$10),DAY(入力データ!$C$10)),1,0))) | F4: =IF(F$3="","",IF(入力データ!$C$10="","",YEAR(DATE(F$3,12,31))-YEAR(入力データ!$C$10)-IF(DATE(F$3,12,31)<DATE(F$3,MONTH(入力データ!$C$10),DAY(入力データ!$C$10)),1,0))) | G4: =IF(G$3="","",IF(入力データ!$C$10="","",YEAR(DATE(G$3,12,31))-YEAR(入力データ!$C$10)-IF(DATE(G$3,12,31)<DATE(G$3,MONTH(入力データ!$C$10),DAY(入力データ!$C$10)),1,0))) | H4: =IF(H$3="","",IF(入力データ!$C$10="","",YEAR(DATE(H$3,12,31))-YEAR(入力データ!$C$10)-IF(DATE(H$3,12,31)<DATE(H$3,MONTH(入力データ!$C$10),DAY(入力データ!$C$10)),1,0))) | I4: =IF(I$3="","",IF(入力データ!$C$10="","",YEAR(DATE(I$3,12,31))-YEAR(入力データ!$C$10)-IF(DATE(I$3,12,31)<DATE(I$3,MONTH(入力データ!$C$10),DAY(入力データ!$C$10)),1,0))) | ... CW4: =IF(CW$3="","",IF(入力データ!$C$10="","",YEAR(DATE(CW$3,12,31))-YEAR(入力データ!$C$10)-IF(DATE(CW$3,12,31)<DATE(CW$3,MONTH(入力データ!$C$10),DAY(入力データ!$C$10)),1,0)))
A5: 奥様年齢 | B5: =IF(B$3="","",IF(入力データ!$C$11="","",YEAR(DATE(B$3,12,31))-YEAR(入力データ!$C$11)-IF(DATE(B$3,12,31)<DATE(B$3,MONTH(入力データ!$C$11),DAY(入力データ!$C$11)),1,0))) | C5: =IF(C$3="","",IF(入力データ!$C$11="","",YEAR(DATE(C$3,12,31))-YEAR(入力データ!$C$11)-IF(DATE(C$3,12,31)<DATE(C$3,MONTH(入力データ!$C$11),DAY(入力データ!$C$11)),1,0))) | D5: =IF(D$3="","",IF(入力データ!$C$11="","",YEAR(DATE(D$3,12,31))-YEAR(入力データ!$C$11)-IF(DATE(D$3,12,31)<DATE(D$3,MONTH(入力データ!$C$11),DAY(入力データ!$C$11)),1,0))) | E5: =IF(E$3="","",IF(入力データ!$C$11="","",YEAR(DATE(E$3,12,31))-YEAR(入力データ!$C$11)-IF(DATE(E$3,12,31)<DATE(E$3,MONTH(入力データ!$C$11),DAY(入力データ!$C$11)),1,0))) | F5: =IF(F$3="","",IF(入力データ!$C$11="","",YEAR(DATE(F$3,12,31))-YEAR(入力データ!$C$11)-IF(DATE(F$3,12,31)<DATE(F$3,MONTH(入力データ!$C$11),DAY(入力データ!$C$11)),1,0))) | G5: =IF(G$3="","",IF(入力データ!$C$11="","",YEAR(DATE(G$3,12,31))-YEAR(入力データ!$C$11)-IF(DATE(G$3,12,31)<DATE(G$3,MONTH(入力データ!$C$11),DAY(入力データ!$C$11)),1,0))) | H5: =IF(H$3="","",IF(入力データ!$C$11="","",YEAR(DATE(H$3,12,31))-YEAR(入力データ!$C$11)-IF(DATE(H$3,12,31)<DATE(H$3,MONTH(入力データ!$C$11),DAY(入力データ!$C$11)),1,0))) | I5: =IF(I$3="","",IF(入力データ!$C$11="","",YEAR(DATE(I$3,12,31))-YEAR(入力データ!$C$11)-IF(DATE(I$3,12,31)<DATE(I$3,MONTH(入力データ!$C$11),DAY(入力データ!$C$11)),1,0))) | ... CW5: =IF(CW$3="","",IF(入力データ!$C$11="","",YEAR(DATE(CW$3,12,31))-YEAR(入力データ!$C$11)-IF(DATE(CW$3,12,31)<DATE(CW$3,MONTH(入力データ!$C$11),DAY(入力データ!$C$11)),1,0)))
A6: 子1年齢 | B6: =IF(B$3="","",IF(入力データ!$C$19="","",YEAR(DATE(B$3,12,31))-YEAR(入力データ!$C$19)-IF(DATE(B$3,12,31)<DATE(B$3,MONTH(入力データ!$C$19),DAY(入力データ!$C$19)),1,0))) | C6: =IF(C$3="","",IF(入力データ!$C$19="","",YEAR(DATE(C$3,12,31))-YEAR(入力データ!$C$19)-IF(DATE(C$3,12,31)<DATE(C$3,MONTH(入力データ!$C$19),DAY(入力データ!$C$19)),1,0))) | D6: =IF(D$3="","",IF(入力データ!$C$19="","",YEAR(DATE(D$3,12,31))-YEAR(入力データ!$C$19)-IF(DATE(D$3,12,31)<DATE(D$3,MONTH(入力データ!$C$19),DAY(入力データ!$C$19)),1,0))) | E6: =IF(E$3="","",IF(入力データ!$C$19="","",YEAR(DATE(E$3,12,31))-YEAR(入力データ!$C$19)-IF(DATE(E$3,12,31)<DATE(E$3,MONTH(入力データ!$C$19),DAY(入力データ!$C$19)),1,0))) | F6: =IF(F$3="","",IF(入力データ!$C$19="","",YEAR(DATE(F$3,12,31))-YEAR(入力データ!$C$19)-IF(DATE(F$3,12,31)<DATE(F$3,MONTH(入力データ!$C$19),DAY(入力データ!$C$19)),1,0))) | G6: =IF(G$3="","",IF(入力データ!$C$19="","",YEAR(DATE(G$3,12,31))-YEAR(入力データ!$C$19)-IF(DATE(G$3,12,31)<DATE(G$3,MONTH(入力データ!$C$19),DAY(入力データ!$C$19)),1,0))) | H6: =IF(H$3="","",IF(入力データ!$C$19="","",YEAR(DATE(H$3,12,31))-YEAR(入力データ!$C$19)-IF(DATE(H$3,12,31)<DATE(H$3,MONTH(入力データ!$C$19),DAY(入力データ!$C$19)),1,0))) | I6: =IF(I$3="","",IF(入力データ!$C$19="","",YEAR(DATE(I$3,12,31))-YEAR(入力データ!$C$19)-IF(DATE(I$3,12,31)<DATE(I$3,MONTH(入力データ!$C$19),DAY(入力データ!$C$19)),1,0))) | ... CW6: =IF(CW$3="","",IF(入力データ!$C$19="","",YEAR(DATE(CW$3,12,31))-YEAR(入力データ!$C$19)-IF(DATE(CW$3,12,31)<DATE(CW$3,MONTH(入力データ!$C$19),DAY(入力データ!$C$19)),1,0)))
A7: 子2年齢 | B7: =IF(B$3="","",IF(入力データ!$C$21="","",YEAR(DATE(B$3,12,31))-YEAR(入力データ!$C$21)-IF(DATE(B$3,12,31)<DATE(B$3,MONTH(入力データ!$C$21),DAY(入力データ!$C$21)),1,0))) | C7: =IF(C$3="","",IF(入力データ!$C$21="","",YEAR(DATE(C$3,12,31))-YEAR(入力データ!$C$21)-IF(DATE(C$3,12,31)<DATE(C$3,MONTH(入力データ!$C$21),DAY(入力データ!$C$21)),1,0))) | D7: =IF(D$3="","",IF(入力データ!$C$21="","",YEAR(DATE(D$3,12,31))-YEAR(入力データ!$C$21)-IF(DATE(D$3,12,31)<DATE(D$3,MONTH(入力データ!$C$21),DAY(入力データ!$C$21)),1,0))) | E7: =IF(E$3="","",IF(入力データ!$C$21="","",YEAR(DATE(E$3,12,31))-YEAR(入力データ!$C$21)-IF(DATE(E$3,12,31)<DATE(E$3,MONTH(入力データ!$C$21),DAY(入力データ!$C$21)),1,0))) | F7: =IF(F$3="","",IF(入力データ!$C$21="","",YEAR(DATE(F$3,12,31))-YEAR(入力データ!$C$21)-IF(DATE(F$3,12,31)<DATE(F$3,MONTH(入力データ!$C$21),DAY(入力データ!$C$21)),1,0))) | G7: =IF(G$3="","",IF(入力データ!$C$21="","",YEAR(DATE(G$3,12,31))-YEAR(入力データ!$C$21)-IF(DATE(G$3,12,31)<DATE(G$3,MONTH(入力データ!$C$21),DAY(入力データ!$C$21)),1,0))) | H7: =IF(H$3="","",IF(入力データ!$C$21="","",YEAR(DATE(H$3,12,31))-YEAR(入力データ!$C$21)-IF(DATE(H$3,12,31)<DATE(H$3,MONTH(入力データ!$C$21),DAY(入力データ!$C$21)),1,0))) | I7: =IF(I$3="","",IF(入力データ!$C$21="","",YEAR(DATE(I$3,12,31))-YEAR(入力データ!$C$21)-IF(DATE(I$3,12,31)<DATE(I$3,MONTH(入力データ!$C$21),DAY(入力データ!$C$21)),1,0))) | ... CW7: =IF(CW$3="","",IF(入力データ!$C$21="","",YEAR(DATE(CW$3,12,31))-YEAR(入力データ!$C$21)-IF(DATE(CW$3,12,31)<DATE(CW$3,MONTH(入力データ!$C$21),DAY(入力データ!$C$21)),1,0)))
A8: 子3年齢 | B8: =IF(B$3="","",IF(情報入力!$C$23="","",YEAR(DATE(B$3,12,31))-YEAR(情報入力!$C$23)-IF(DATE(B$3,12,31)<DATE(B$3,MONTH(情報入力!$C$23),DAY(情報入力!$C$23)),1,0))) | C8: =IF(C$3="","",IF(情報入力!$C$23="","",YEAR(DATE(C$3,12,31))-YEAR(情報入力!$C$23)-IF(DATE(C$3,12,31)<DATE(C$3,MONTH(情報入力!$C$23),DAY(情報入力!$C$23)),1,0))) | D8: =IF(D$3="","",IF(情報入力!$C$23="","",YEAR(DATE(D$3,12,31))-YEAR(情報入力!$C$23)-IF(DATE(D$3,12,31)<DATE(D$3,MONTH(情報入力!$C$23),DAY(情報入力!$C$23)),1,0))) | E8: =IF(E$3="","",IF(情報入力!$C$23="","",YEAR(DATE(E$3,12,31))-YEAR(情報入力!$C$23)-IF(DATE(E$3,12,31)<DATE(E$3,MONTH(情報入力!$C$23),DAY(情報入力!$C$23)),1,0))) | F8: =IF(F$3="","",IF(情報入力!$C$23="","",YEAR(DATE(F$3,12,31))-YEAR(情報入力!$C$23)-IF(DATE(F$3,12,31)<DATE(F$3,MONTH(情報入力!$C$23),DAY(情報入力!$C$23)),1,0))) | G8: =IF(G$3="","",IF(情報入力!$C$23="","",YEAR(DATE(G$3,12,31))-YEAR(情報入力!$C$23)-IF(DATE(G$3,12,31)<DATE(G$3,MONTH(情報入力!$C$23),DAY(情報入力!$C$23)),1,0))) | H8: =IF(H$3="","",IF(情報入力!$C$23="","",YEAR(DATE(H$3,12,31))-YEAR(情報入力!$C$23)-IF(DATE(H$3,12,31)<DATE(H$3,MONTH(情報入力!$C$23),DAY(情報入力!$C$23)),1,0))) | I8: =IF(I$3="","",IF(情報入力!$C$23="","",YEAR(DATE(I$3,12,31))-YEAR(情報入力!$C$23)-IF(DATE(I$3,12,31)<DATE(I$3,MONTH(情報入力!$C$23),DAY(情報入力!$C$23)),1,0))) | ... CW8: =IF(CW$3="","",IF(情報入力!$C$23="","",YEAR(DATE(CW$3,12,31))-YEAR(情報入力!$C$23)-IF(DATE(CW$3,12,31)<DATE(CW$3,MONTH(情報入力!$C$23),DAY(情報入力!$C$23)),1,0)))
A9: 家族年齢
A10: ご主人様収入 | B10: =IF(B$3="","",0) | C10: =IF(C$3="","",0) | D10: =IF(D$3="","",0) | E10: =IF(E$3="","",0) | F10: =IF(F$3="","",0) | G10: =IF(G$3="","",0) | H10: =IF(H$3="","",0) | I10: =IF(I$3="","",0) | ... CW10: =IF(CW$3="","",0)
A11: 奥様収入 | B11: =IF(B$3="","",IF(B5<入力データ!$C$110,((入力データ!$C$30*12)+IF(入力データ!$C$31="あり",入力データ!$C$33,0))*(1+前提条件!$C$6)^(B$3-$B$3),0)) | C11: =IF(C$3="","",IF(C5<入力データ!$C$110,((入力データ!$C$30*12)+IF(入力データ!$C$31="あり",入力データ!$C$33,0))*(1+前提条件!$C$6)^(C$3-$B$3),0)) | D11: =IF(D$3="","",IF(D5<入力データ!$C$110,((入力データ!$C$30*12)+IF(入力データ!$C$31="あり",入力データ!$C$33,0))*(1+前提条件!$C$6)^(D$3-$B$3),0)) | E11: =IF(E$3="","",IF(E5<入力データ!$C$110,((入力データ!$C$30*12)+IF(入力データ!$C$31="あり",入力データ!$C$33,0))*(1+前提条件!$C$6)^(E$3-$B$3),0)) | F11: =IF(F$3="","",IF(F5<入力データ!$C$110,((入力データ!$C$30*12)+IF(入力データ!$C$31="あり",入力データ!$C$33,0))*(1+前提条件!$C$6)^(F$3-$B$3),0)) | G11: =IF(G$3="","",IF(G5<入力データ!$C$110,((入力データ!$C$30*12)+IF(入力データ!$C$31="あり",入力データ!$C$33,0))*(1+前提条件!$C$6)^(G$3-$B$3),0)) | H11: =IF(H$3="","",IF(H5<入力データ!$C$110,((入力データ!$C$30*12)+IF(入力データ!$C$31="あり",入力データ!$C$33,0))*(1+前提条件!$C$6)^(H$3-$B$3),0)) | I11: =IF(I$3="","",IF(I5<入力データ!$C$110,((入力データ!$C$30*12)+IF(入力データ!$C$31="あり",入力データ!$C$33,0))*(1+前提条件!$C$6)^(I$3-$B$3),0)) | ... CW11: =IF(CW$3="","",IF(CW5<入力データ!$C$110,((入力データ!$C$30*12)+IF(入力データ!$C$31="あり",入力データ!$C$33,0))*(1+前提条件!$C$6)^(CW$3-$B$3),0))
A12: 児童手当 | B12: =IF(B$3="","",IF(AND(B6<>"",B6<=前提条件!$C$8),IF(1>=3,30000,IF(B6<3,15000,10000))*6,0)+IF(AND(B7<>"",B7<=前提条件!$C$8),IF(2>=3,30000,IF(B7<3,15000,10000))*6,0)+IF(AND(B8<>"",B8<=前提条件!$C$8),30000*6,0)) | C12: =IF(C$3="","",IF(AND(C6<>"",C6<=前提条件!$C$8),IF(1>=3,30000,IF(C6<3,15000,10000))*6,0)+IF(AND(C7<>"",C7<=前提条件!$C$8),IF(2>=3,30000,IF(C7<3,15000,10000))*6,0)+IF(AND(C8<>"",C8<=前提条件!$C$8),30000*6,0)) | D12: =IF(D$3="","",IF(AND(D6<>"",D6<=前提条件!$C$8),IF(1>=3,30000,IF(D6<3,15000,10000))*6,0)+IF(AND(D7<>"",D7<=前提条件!$C$8),IF(2>=3,30000,IF(D7<3,15000,10000))*6,0)+IF(AND(D8<>"",D8<=前提条件!$C$8),30000*6,0)) | E12: =IF(E$3="","",IF(AND(E6<>"",E6<=前提条件!$C$8),IF(1>=3,30000,IF(E6<3,15000,10000))*6,0)+IF(AND(E7<>"",E7<=前提条件!$C$8),IF(2>=3,30000,IF(E7<3,15000,10000))*6,0)+IF(AND(E8<>"",E8<=前提条件!$C$8),30000*6,0)) | F12: =IF(F$3="","",IF(AND(F6<>"",F6<=前提条件!$C$8),IF(1>=3,30000,IF(F6<3,15000,10000))*6,0)+IF(AND(F7<>"",F7<=前提条件!$C$8),IF(2>=3,30000,IF(F7<3,15000,10000))*6,0)+IF(AND(F8<>"",F8<=前提条件!$C$8),30000*6,0)) | G12: =IF(G$3="","",IF(AND(G6<>"",G6<=前提条件!$C$8),IF(1>=3,30000,IF(G6<3,15000,10000))*6,0)+IF(AND(G7<>"",G7<=前提条件!$C$8),IF(2>=3,30000,IF(G7<3,15000,10000))*6,0)+IF(AND(G8<>"",G8<=前提条件!$C$8),30000*6,0)) | H12: =IF(H$3="","",IF(AND(H6<>"",H6<=前提条件!$C$8),IF(1>=3,30000,IF(H6<3,15000,10000))*6,0)+IF(AND(H7<>"",H7<=前提条件!$C$8),IF(2>=3,30000,IF(H7<3,15000,10000))*6,0)+IF(AND(H8<>"",H8<=前提条件!$C$8),30000*6,0)) | I12: =IF(I$3="","",IF(AND(I6<>"",I6<=前提条件!$C$8),IF(1>=3,30000,IF(I6<3,15000,10000))*6,0)+IF(AND(I7<>"",I7<=前提条件!$C$8),IF(2>=3,30000,IF(I7<3,15000,10000))*6,0)+IF(AND(I8<>"",I8<=前提条件!$C$8),30000*6,0)) | ... CV12: =IF(CV$3="","",IF(AND(CV6<>"",CV6<=前提条件!$C$8),IF(1>=3,30000,IF(CV6<3,15000,10000))*6,0)+IF(AND(CV7<>"",CV7<=前提条件!$C$8),IF(2>=3,30000,IF(CV7<3,15000,10000))*6,0)+IF(AND(CV8<>"",CV8<=前提条件!$C$8),30000*6,0)) | CW12: =IF(CW$3="","",IF(AND(CW6<>"",CW6<=前提条件!$C$8),入力データ!$C$34*6,0)+IF(AND(CW7<>"",CW7<=前提条件!$C$8),入力データ!$C$34*6,0)+IF(AND(CW8<>"",CW8<=前提条件!$C$8),入力データ!$C$34*6,0))
A13: その他収入 | B13: =IF(B$3="","",入力データ!$C$35*12+IF(AND(B5<>"",B5<前提条件!$C$38),前提条件!$C$57*12,0)) | C13: =IF(C$3="","",入力データ!$C$35*12+IF(AND(C5<>"",C5<前提条件!$C$38),前提条件!$C$57*12,0)) | D13: =IF(D$3="","",入力データ!$C$35*12+IF(AND(D5<>"",D5<前提条件!$C$38),前提条件!$C$57*12,0)) | E13: =IF(E$3="","",入力データ!$C$35*12+IF(AND(E5<>"",E5<前提条件!$C$38),前提条件!$C$57*12,0)) | F13: =IF(F$3="","",入力データ!$C$35*12+IF(AND(F5<>"",F5<前提条件!$C$38),前提条件!$C$57*12,0)) | G13: =IF(G$3="","",入力データ!$C$35*12+IF(AND(G5<>"",G5<前提条件!$C$38),前提条件!$C$57*12,0)) | H13: =IF(H$3="","",入力データ!$C$35*12+IF(AND(H5<>"",H5<前提条件!$C$38),前提条件!$C$57*12,0)) | I13: =IF(I$3="","",入力データ!$C$35*12+IF(AND(I5<>"",I5<前提条件!$C$38),前提条件!$C$57*12,0)) | ... CW13: =IF(CW$3="","",入力データ!$C$35*12+IF(AND(CW5<>"",CW5<前提条件!$C$38),前提条件!$C$57*12,0))
A14: ご主人様退職金 | B14: =IF(B$3="","",0) | C14: =IF(C$3="","",0) | D14: =IF(D$3="","",0) | E14: =IF(E$3="","",0) | F14: =IF(F$3="","",0) | G14: =IF(G$3="","",0) | H14: =IF(H$3="","",0) | I14: =IF(I$3="","",0) | ... CW14: =IF(CW$3="","",0)
A15: 奥様退職金 | B15: =IF(B$3="","",IF(B5=入力データ!$C$110,入力データ!$C$37,0)) | C15: =IF(C$3="","",IF(C5=入力データ!$C$110,入力データ!$C$37,0)) | D15: =IF(D$3="","",IF(D5=入力データ!$C$110,入力データ!$C$37,0)) | E15: =IF(E$3="","",IF(E5=入力データ!$C$110,入力データ!$C$37,0)) | F15: =IF(F$3="","",IF(F5=入力データ!$C$110,入力データ!$C$37,0)) | G15: =IF(G$3="","",IF(G5=入力データ!$C$110,入力データ!$C$37,0)) | H15: =IF(H$3="","",IF(H5=入力データ!$C$110,入力データ!$C$37,0)) | I15: =IF(I$3="","",IF(I5=入力データ!$C$110,入力データ!$C$37,0)) | ... CW15: =IF(CW$3="","",IF(CW5=入力データ!$C$110,入力データ!$C$37,0))
A16: ご主人様年金収入 | B16: =IF(B$3="","",0) | C16: =IF(C$3="","",0) | D16: =IF(D$3="","",0) | E16: =IF(E$3="","",0) | F16: =IF(F$3="","",0) | G16: =IF(G$3="","",0) | H16: =IF(H$3="","",0) | I16: =IF(I$3="","",0) | ... CW16: =IF(CW$3="","",0)
A17: 奥様年金収入 | B17: =IF(B$3="","",IF(B5>=前提条件!$C$38,前提条件!$C$40*12,0)) | C17: =IF(C$3="","",IF(C5>=前提条件!$C$38,前提条件!$C$40*12,0)) | D17: =IF(D$3="","",IF(D5>=前提条件!$C$38,前提条件!$C$40*12,0)) | E17: =IF(E$3="","",IF(E5>=前提条件!$C$38,前提条件!$C$40*12,0)) | F17: =IF(F$3="","",IF(F5>=前提条件!$C$38,前提条件!$C$40*12,0)) | G17: =IF(G$3="","",IF(G5>=前提条件!$C$38,前提条件!$C$40*12,0)) | H17: =IF(H$3="","",IF(H5>=前提条件!$C$38,前提条件!$C$40*12,0)) | I17: =IF(I$3="","",IF(I5>=前提条件!$C$38,前提条件!$C$40*12,0)) | ... CW17: =IF(CW$3="","",IF(CW5>=前提条件!$C$38,前提条件!$C$40*12,0))
A18: 世帯収入合計 | B18: =IF(B$3="","",SUM(B10:B17)) | C18: =IF(C$3="","",SUM(C10:C17)) | D18: =IF(D$3="","",SUM(D10:D17)) | E18: =IF(E$3="","",SUM(E10:E17)) | F18: =IF(F$3="","",SUM(F10:F17)) | G18: =IF(G$3="","",SUM(G10:G17)) | H18: =IF(H$3="","",SUM(H10:H17)) | I18: =IF(I$3="","",SUM(I10:I17)) | ... CW18: =IF(CW$3="","",SUM(CW10:CW17))
A19: 収入
A20: 基本生活費 | B20: =IF(B$3="","",(IF(MIN(B4,B5)>=入力データ!$C$111,入力データ!$C$112*12*(1+前提条件!$C$14)^(B$3-$B$3),SUM(入力データ!$C$41:$C$52)*12*(1+前提条件!$C$12)^(B$3-$B$3)))*前提条件!$C$52) | C20: =IF(C$3="","",(IF(MIN(C4,C5)>=入力データ!$C$111,入力データ!$C$112*12*(1+前提条件!$C$14)^(C$3-$B$3),SUM(入力データ!$C$41:$C$52)*12*(1+前提条件!$C$12)^(C$3-$B$3)))*前提条件!$C$52) | D20: =IF(D$3="","",(IF(MIN(D4,D5)>=入力データ!$C$111,入力データ!$C$112*12*(1+前提条件!$C$14)^(D$3-$B$3),SUM(入力データ!$C$41:$C$52)*12*(1+前提条件!$C$12)^(D$3-$B$3)))*前提条件!$C$52) | E20: =IF(E$3="","",(IF(MIN(E4,E5)>=入力データ!$C$111,入力データ!$C$112*12*(1+前提条件!$C$14)^(E$3-$B$3),SUM(入力データ!$C$41:$C$52)*12*(1+前提条件!$C$12)^(E$3-$B$3)))*前提条件!$C$52) | F20: =IF(F$3="","",(IF(MIN(F4,F5)>=入力データ!$C$111,入力データ!$C$112*12*(1+前提条件!$C$14)^(F$3-$B$3),SUM(入力データ!$C$41:$C$52)*12*(1+前提条件!$C$12)^(F$3-$B$3)))*前提条件!$C$52) | G20: =IF(G$3="","",(IF(MIN(G4,G5)>=入力データ!$C$111,入力データ!$C$112*12*(1+前提条件!$C$14)^(G$3-$B$3),SUM(入力データ!$C$41:$C$52)*12*(1+前提条件!$C$12)^(G$3-$B$3)))*前提条件!$C$52) | H20: =IF(H$3="","",(IF(MIN(H4,H5)>=入力データ!$C$111,入力データ!$C$112*12*(1+前提条件!$C$14)^(H$3-$B$3),SUM(入力データ!$C$41:$C$52)*12*(1+前提条件!$C$12)^(H$3-$B$3)))*前提条件!$C$52) | I20: =IF(I$3="","",(IF(MIN(I4,I5)>=入力データ!$C$111,入力データ!$C$112*12*(1+前提条件!$C$14)^(I$3-$B$3),SUM(入力データ!$C$41:$C$52)*12*(1+前提条件!$C$12)^(I$3-$B$3)))*前提条件!$C$52) | ... CW20: =IF(CW$3="","",(IF(MIN(CW4,CW5)>=入力データ!$C$111,入力データ!$C$112*12*(1+前提条件!$C$14)^(CW$3-$B$3),SUM(入力データ!$C$41:$C$52)*12*(1+前提条件!$C$12)^(CW$3-$B$3)))*前提条件!$C$52)
A21: 住居費 | B21: =IF(B$3="","",((IF(入力データ!$C$13="持ち家",IF(入力データ!$C$57="あり",0,IF(B4<=前提条件!$C$44,入力データ!$C$53,0)),入力データ!$C$53)+入力データ!$C$54+入力データ!$C$55+入力データ!$C$56)*12+IF(入力データ!$C$13="持ち家",入力データ!$C$83+前提条件!$C$47,入力データ!$C$84+前提条件!$C$48))*(1+前提条件!$C$15)^(B$3-$B$3)) | C21: =IF(C$3="","",((IF(入力データ!$C$13="持ち家",IF(入力データ!$C$57="あり",0,IF(C4<=前提条件!$C$44,入力データ!$C$53,0)),入力データ!$C$53)+入力データ!$C$54+入力データ!$C$55+入力データ!$C$56)*12+IF(入力データ!$C$13="持ち家",入力データ!$C$83+前提条件!$C$47,入力データ!$C$84+前提条件!$C$48))*(1+前提条件!$C$15)^(C$3-$B$3)) | D21: =IF(D$3="","",((IF(入力データ!$C$13="持ち家",IF(入力データ!$C$57="あり",0,IF(D4<=前提条件!$C$44,入力データ!$C$53,0)),入力データ!$C$53)+入力データ!$C$54+入力データ!$C$55+入力データ!$C$56)*12+IF(入力データ!$C$13="持ち家",入力データ!$C$83+前提条件!$C$47,入力データ!$C$84+前提条件!$C$48))*(1+前提条件!$C$15)^(D$3-$B$3)) | E21: =IF(E$3="","",((IF(入力データ!$C$13="持ち家",IF(入力データ!$C$57="あり",0,IF(E4<=前提条件!$C$44,入力データ!$C$53,0)),入力データ!$C$53)+入力データ!$C$54+入力データ!$C$55+入力データ!$C$56)*12+IF(入力データ!$C$13="持ち家",入力データ!$C$83+前提条件!$C$47,入力データ!$C$84+前提条件!$C$48))*(1+前提条件!$C$15)^(E$3-$B$3)) | F21: =IF(F$3="","",((IF(入力データ!$C$13="持ち家",IF(入力データ!$C$57="あり",0,IF(F4<=前提条件!$C$44,入力データ!$C$53,0)),入力データ!$C$53)+入力データ!$C$54+入力データ!$C$55+入力データ!$C$56)*12+IF(入力データ!$C$13="持ち家",入力データ!$C$83+前提条件!$C$47,入力データ!$C$84+前提条件!$C$48))*(1+前提条件!$C$15)^(F$3-$B$3)) | G21: =IF(G$3="","",((IF(入力データ!$C$13="持ち家",IF(入力データ!$C$57="あり",0,IF(G4<=前提条件!$C$44,入力データ!$C$53,0)),入力データ!$C$53)+入力データ!$C$54+入力データ!$C$55+入力データ!$C$56)*12+IF(入力データ!$C$13="持ち家",入力データ!$C$83+前提条件!$C$47,入力データ!$C$84+前提条件!$C$48))*(1+前提条件!$C$15)^(G$3-$B$3)) | H21: =IF(H$3="","",((IF(入力データ!$C$13="持ち家",IF(入力データ!$C$57="あり",0,IF(H4<=前提条件!$C$44,入力データ!$C$53,0)),入力データ!$C$53)+入力データ!$C$54+入力データ!$C$55+入力データ!$C$56)*12+IF(入力データ!$C$13="持ち家",入力データ!$C$83+前提条件!$C$47,入力データ!$C$84+前提条件!$C$48))*(1+前提条件!$C$15)^(H$3-$B$3)) | I21: =IF(I$3="","",((IF(入力データ!$C$13="持ち家",IF(入力データ!$C$57="あり",0,IF(I4<=前提条件!$C$44,入力データ!$C$53,0)),入力データ!$C$53)+入力データ!$C$54+入力データ!$C$55+入力データ!$C$56)*12+IF(入力データ!$C$13="持ち家",入力データ!$C$83+前提条件!$C$47,入力データ!$C$84+前提条件!$C$48))*(1+前提条件!$C$15)^(I$3-$B$3)) | ... CW21: =IF(CW$3="","",((IF(入力データ!$C$13="持ち家",IF(入力データ!$C$57="あり",0,IF(CW4<=前提条件!$C$44,入力データ!$C$53,0)),入力データ!$C$53)+入力データ!$C$54+入力データ!$C$55+入力データ!$C$56)*12+IF(入力データ!$C$13="持ち家",入力データ!$C$83+前提条件!$C$47,入力データ!$C$84+前提条件!$C$48))*(1+前提条件!$C$15)^(CW$3-$B$3))
A22: 終身系保険料 | B22: =IF(B$3="","",SUMPRODUCT(--ISNUMBER(SEARCH("終身",入力データ!$F$5:$F$20)),--(IFERROR(YEAR(入力データ!$J$5:$J$20),0)<=B$3),--(IFERROR(YEAR(入力データ!$K$5:$K$20),9999)>=B$3),入力データ!$M$5:$M$20)*12) | C22: =IF(C$3="","",SUMPRODUCT(--ISNUMBER(SEARCH("終身",入力データ!$F$5:$F$20)),--(IFERROR(YEAR(入力データ!$J$5:$J$20),0)<=C$3),--(IFERROR(YEAR(入力データ!$K$5:$K$20),9999)>=C$3),入力データ!$M$5:$M$20)*12) | D22: =IF(D$3="","",SUMPRODUCT(--ISNUMBER(SEARCH("終身",入力データ!$F$5:$F$20)),--(IFERROR(YEAR(入力データ!$J$5:$J$20),0)<=D$3),--(IFERROR(YEAR(入力データ!$K$5:$K$20),9999)>=D$3),入力データ!$M$5:$M$20)*12) | E22: =IF(E$3="","",SUMPRODUCT(--ISNUMBER(SEARCH("終身",入力データ!$F$5:$F$20)),--(IFERROR(YEAR(入力データ!$J$5:$J$20),0)<=E$3),--(IFERROR(YEAR(入力データ!$K$5:$K$20),9999)>=E$3),入力データ!$M$5:$M$20)*12) | F22: =IF(F$3="","",SUMPRODUCT(--ISNUMBER(SEARCH("終身",入力データ!$F$5:$F$20)),--(IFERROR(YEAR(入力データ!$J$5:$J$20),0)<=F$3),--(IFERROR(YEAR(入力データ!$K$5:$K$20),9999)>=F$3),入力データ!$M$5:$M$20)*12) | G22: =IF(G$3="","",SUMPRODUCT(--ISNUMBER(SEARCH("終身",入力データ!$F$5:$F$20)),--(IFERROR(YEAR(入力データ!$J$5:$J$20),0)<=G$3),--(IFERROR(YEAR(入力データ!$K$5:$K$20),9999)>=G$3),入力データ!$M$5:$M$20)*12) | H22: =IF(H$3="","",SUMPRODUCT(--ISNUMBER(SEARCH("終身",入力データ!$F$5:$F$20)),--(IFERROR(YEAR(入力データ!$J$5:$J$20),0)<=H$3),--(IFERROR(YEAR(入力データ!$K$5:$K$20),9999)>=H$3),入力データ!$M$5:$M$20)*12) | I22: =IF(I$3="","",SUMPRODUCT(--ISNUMBER(SEARCH("終身",入力データ!$F$5:$F$20)),--(IFERROR(YEAR(入力データ!$J$5:$J$20),0)<=I$3),--(IFERROR(YEAR(入力データ!$K$5:$K$20),9999)>=I$3),入力データ!$M$5:$M$20)*12) | ... CW22: =IF(CW$3="","",SUMPRODUCT(--ISNUMBER(SEARCH("終身",入力データ!$F$5:$F$20)),--(IFERROR(YEAR(入力データ!$J$5:$J$20),0)<=CW$3),--(IFERROR(YEAR(入力データ!$K$5:$K$20),9999)>=CW$3),入力データ!$M$5:$M$20)*12)
A23: 定期系保険料 | B23: =IF(B$3="","",SUMPRODUCT(--ISERROR(SEARCH("終身",入力データ!$F$5:$F$20)),--(IFERROR(YEAR(入力データ!$J$5:$J$20),0)<=B$3),--(IFERROR(YEAR(入力データ!$K$5:$K$20),9999)>=B$3),入力データ!$M$5:$M$20)*12) | C23: =IF(C$3="","",SUMPRODUCT(--ISERROR(SEARCH("終身",入力データ!$F$5:$F$20)),--(IFERROR(YEAR(入力データ!$J$5:$J$20),0)<=C$3),--(IFERROR(YEAR(入力データ!$K$5:$K$20),9999)>=C$3),入力データ!$M$5:$M$20)*12) | D23: =IF(D$3="","",SUMPRODUCT(--ISERROR(SEARCH("終身",入力データ!$F$5:$F$20)),--(IFERROR(YEAR(入力データ!$J$5:$J$20),0)<=D$3),--(IFERROR(YEAR(入力データ!$K$5:$K$20),9999)>=D$3),入力データ!$M$5:$M$20)*12) | E23: =IF(E$3="","",SUMPRODUCT(--ISERROR(SEARCH("終身",入力データ!$F$5:$F$20)),--(IFERROR(YEAR(入力データ!$J$5:$J$20),0)<=E$3),--(IFERROR(YEAR(入力データ!$K$5:$K$20),9999)>=E$3),入力データ!$M$5:$M$20)*12) | F23: =IF(F$3="","",SUMPRODUCT(--ISERROR(SEARCH("終身",入力データ!$F$5:$F$20)),--(IFERROR(YEAR(入力データ!$J$5:$J$20),0)<=F$3),--(IFERROR(YEAR(入力データ!$K$5:$K$20),9999)>=F$3),入力データ!$M$5:$M$20)*12) | G23: =IF(G$3="","",SUMPRODUCT(--ISERROR(SEARCH("終身",入力データ!$F$5:$F$20)),--(IFERROR(YEAR(入力データ!$J$5:$J$20),0)<=G$3),--(IFERROR(YEAR(入力データ!$K$5:$K$20),9999)>=G$3),入力データ!$M$5:$M$20)*12) | H23: =IF(H$3="","",SUMPRODUCT(--ISERROR(SEARCH("終身",入力データ!$F$5:$F$20)),--(IFERROR(YEAR(入力データ!$J$5:$J$20),0)<=H$3),--(IFERROR(YEAR(入力データ!$K$5:$K$20),9999)>=H$3),入力データ!$M$5:$M$20)*12) | I23: =IF(I$3="","",SUMPRODUCT(--ISERROR(SEARCH("終身",入力データ!$F$5:$F$20)),--(IFERROR(YEAR(入力データ!$J$5:$J$20),0)<=I$3),--(IFERROR(YEAR(入力データ!$K$5:$K$20),9999)>=I$3),入力データ!$M$5:$M$20)*12) | ... CW23: =IF(CW$3="","",SUMPRODUCT(--ISERROR(SEARCH("終身",入力データ!$F$5:$F$20)),--(IFERROR(YEAR(入力データ!$J$5:$J$20),0)<=CW$3),--(IFERROR(YEAR(入力データ!$K$5:$K$20),9999)>=CW$3),入力データ!$M$5:$M$20)*12)
A24: 教育費 | B24: =IF(B$3="","",IF(入力データ!$C$17<=0,0,IF(B$3="","",((SUM(入力データ!$C$58:$C$61)*12)+IF(B6="",0,IF(B6<=5,IF(入力データ!$G$25="私立",前提条件!$C$22,前提条件!$C$21),IF(B6<=11,IF(入力データ!$H$25="私立",前提条件!$C$24,前提条件!$C$23),IF(B6<=14,IF(入力データ!$I$25="私立",前提条件!$C$26,前提条件!$C$25),IF(B6<=17,IF(入力データ!$J$25="私立",前提条件!$C$28,前提条件!$C$27),IF(B6<=21,IF(入力データ!$K$25="国公立",前提条件!$C$29,IF(入力データ!$K$25="私立理系",前提条件!$C$31,前提条件!$C$30))+IF(入力データ!$L$25="下宿",前提条件!$C$32,0)+IF(B6=18,前提条件!$C$33,0),0))))))+IF(B7="",0,IF(B7<=5,IF(入力データ!$G$26="私立",前提条件!$C$22,前提条件!$C$21),IF(B7<=11,IF(入力データ!$H$26="私立",前提条件!$C$24,前提条件!$C$23),IF(B7<=14,IF(入力データ!$I$26="私立",前提条件!$C$26,前提条件!$C$25),IF(B7<=17,IF(入力データ!$J$26="私立",前提条件!$C$28,前提条件!$C$27),IF(B7<=21,IF(入力データ!$K$26="国公立",前提条件!$C$29,IF(入力データ!$K$26="私立理系",前提条件!$C$31,前提条件!$C$30))+IF(入力データ!$L$26="下宿",前提条件!$C$32,0)+IF(B7=18,前提条件!$C$33,0),0))))))+IF(B8="",0,IF(B8<=5,IF(入力データ!$G$27="私立",前提条件!$C$22,前提条件!$C$21),IF(B8<=11,IF(入力データ!$H$27="私立",前提条件!$C$24,前提条件!$C$23),IF(B8<=14,IF(入力データ!$I$27="私立",前提条件!$C$26,前提条件!$C$25),IF(B8<=17,IF(入力データ!$J$27="私立",前提条件!$C$28,前提条件!$C$27),IF(B8<=21,IF(入力データ!$K$27="国公立",前提条件!$C$29,IF(入力データ!$K$27="私立理系",前提条件!$C$31,前提条件!$C$30))+IF(入力データ!$L$27="下宿",前提条件!$C$32,0)+IF(B8=18,前提条件!$C$33,0),0)))))))*(1+前提条件!$C$13)^(B$3-$B$3)))) | C24: =IF(C$3="","",IF(入力データ!$C$17<=0,0,IF(C$3="","",((SUM(入力データ!$C$58:$C$61)*12)+IF(C6="",0,IF(C6<=5,IF(入力データ!$G$25="私立",前提条件!$C$22,前提条件!$C$21),IF(C6<=11,IF(入力データ!$H$25="私立",前提条件!$C$24,前提条件!$C$23),IF(C6<=14,IF(入力データ!$I$25="私立",前提条件!$C$26,前提条件!$C$25),IF(C6<=17,IF(入力データ!$J$25="私立",前提条件!$C$28,前提条件!$C$27),IF(C6<=21,IF(入力データ!$K$25="国公立",前提条件!$C$29,IF(入力データ!$K$25="私立理系",前提条件!$C$31,前提条件!$C$30))+IF(入力データ!$L$25="下宿",前提条件!$C$32,0)+IF(C6=18,前提条件!$C$33,0),0))))))+IF(C7="",0,IF(C7<=5,IF(入力データ!$G$26="私立",前提条件!$C$22,前提条件!$C$21),IF(C7<=11,IF(入力データ!$H$26="私立",前提条件!$C$24,前提条件!$C$23),IF(C7<=14,IF(入力データ!$I$26="私立",前提条件!$C$26,前提条件!$C$25),IF(C7<=17,IF(入力データ!$J$26="私立",前提条件!$C$28,前提条件!$C$27),IF(C7<=21,IF(入力データ!$K$26="国公立",前提条件!$C$29,IF(入力データ!$K$26="私立理系",前提条件!$C$31,前提条件!$C$30))+IF(入力データ!$L$26="下宿",前提条件!$C$32,0)+IF(C7=18,前提条件!$C$33,0),0))))))+IF(C8="",0,IF(C8<=5,IF(入力データ!$G$27="私立",前提条件!$C$22,前提条件!$C$21),IF(C8<=11,IF(入力データ!$H$27="私立",前提条件!$C$24,前提条件!$C$23),IF(C8<=14,IF(入力データ!$I$27="私立",前提条件!$C$26,前提条件!$C$25),IF(C8<=17,IF(入力データ!$J$27="私立",前提条件!$C$28,前提条件!$C$27),IF(C8<=21,IF(入力データ!$K$27="国公立",前提条件!$C$29,IF(入力データ!$K$27="私立理系",前提条件!$C$31,前提条件!$C$30))+IF(入力データ!$L$27="下宿",前提条件!$C$32,0)+IF(C8=18,前提条件!$C$33,0),0)))))))*(1+前提条件!$C$13)^(C$3-$B$3)))) | D24: =IF(D$3="","",IF(入力データ!$C$17<=0,0,IF(D$3="","",((SUM(入力データ!$C$58:$C$61)*12)+IF(D6="",0,IF(D6<=5,IF(入力データ!$G$25="私立",前提条件!$C$22,前提条件!$C$21),IF(D6<=11,IF(入力データ!$H$25="私立",前提条件!$C$24,前提条件!$C$23),IF(D6<=14,IF(入力データ!$I$25="私立",前提条件!$C$26,前提条件!$C$25),IF(D6<=17,IF(入力データ!$J$25="私立",前提条件!$C$28,前提条件!$C$27),IF(D6<=21,IF(入力データ!$K$25="国公立",前提条件!$C$29,IF(入力データ!$K$25="私立理系",前提条件!$C$31,前提条件!$C$30))+IF(入力データ!$L$25="下宿",前提条件!$C$32,0)+IF(D6=18,前提条件!$C$33,0),0))))))+IF(D7="",0,IF(D7<=5,IF(入力データ!$G$26="私立",前提条件!$C$22,前提条件!$C$21),IF(D7<=11,IF(入力データ!$H$26="私立",前提条件!$C$24,前提条件!$C$23),IF(D7<=14,IF(入力データ!$I$26="私立",前提条件!$C$26,前提条件!$C$25),IF(D7<=17,IF(入力データ!$J$26="私立",前提条件!$C$28,前提条件!$C$27),IF(D7<=21,IF(入力データ!$K$26="国公立",前提条件!$C$29,IF(入力データ!$K$26="私立理系",前提条件!$C$31,前提条件!$C$30))+IF(入力データ!$L$26="下宿",前提条件!$C$32,0)+IF(D7=18,前提条件!$C$33,0),0))))))+IF(D8="",0,IF(D8<=5,IF(入力データ!$G$27="私立",前提条件!$C$22,前提条件!$C$21),IF(D8<=11,IF(入力データ!$H$27="私立",前提条件!$C$24,前提条件!$C$23),IF(D8<=14,IF(入力データ!$I$27="私立",前提条件!$C$26,前提条件!$C$25),IF(D8<=17,IF(入力データ!$J$27="私立",前提条件!$C$28,前提条件!$C$27),IF(D8<=21,IF(入力データ!$K$27="国公立",前提条件!$C$29,IF(入力データ!$K$27="私立理系",前提条件!$C$31,前提条件!$C$30))+IF(入力データ!$L$27="下宿",前提条件!$C$32,0)+IF(D8=18,前提条件!$C$33,0),0)))))))*(1+前提条件!$C$13)^(D$3-$B$3)))) | E24: =IF(E$3="","",IF(入力データ!$C$17<=0,0,IF(E$3="","",((SUM(入力データ!$C$58:$C$61)*12)+IF(E6="",0,IF(E6<=5,IF(入力データ!$G$25="私立",前提条件!$C$22,前提条件!$C$21),IF(E6<=11,IF(入力データ!$H$25="私立",前提条件!$C$24,前提条件!$C$23),IF(E6<=14,IF(入力データ!$I$25="私立",前提条件!$C$26,前提条件!$C$25),IF(E6<=17,IF(入力データ!$J$25="私立",前提条件!$C$28,前提条件!$C$27),IF(E6<=21,IF(入力データ!$K$25="国公立",前提条件!$C$29,IF(入力データ!$K$25="私立理系",前提条件!$C$31,前提条件!$C$30))+IF(入力データ!$L$25="下宿",前提条件!$C$32,0)+IF(E6=18,前提条件!$C$33,0),0))))))+IF(E7="",0,IF(E7<=5,IF(入力データ!$G$26="私立",前提条件!$C$22,前提条件!$C$21),IF(E7<=11,IF(入力データ!$H$26="私立",前提条件!$C$24,前提条件!$C$23),IF(E7<=14,IF(入力データ!$I$26="私立",前提条件!$C$26,前提条件!$C$25),IF(E7<=17,IF(入力データ!$J$26="私立",前提条件!$C$28,前提条件!$C$27),IF(E7<=21,IF(入力データ!$K$26="国公立",前提条件!$C$29,IF(入力データ!$K$26="私立理系",前提条件!$C$31,前提条件!$C$30))+IF(入力データ!$L$26="下宿",前提条件!$C$32,0)+IF(E7=18,前提条件!$C$33,0),0))))))+IF(E8="",0,IF(E8<=5,IF(入力データ!$G$27="私立",前提条件!$C$22,前提条件!$C$21),IF(E8<=11,IF(入力データ!$H$27="私立",前提条件!$C$24,前提条件!$C$23),IF(E8<=14,IF(入力データ!$I$27="私立",前提条件!$C$26,前提条件!$C$25),IF(E8<=17,IF(入力データ!$J$27="私立",前提条件!$C$28,前提条件!$C$27),IF(E8<=21,IF(入力データ!$K$27="国公立",前提条件!$C$29,IF(入力データ!$K$27="私立理系",前提条件!$C$31,前提条件!$C$30))+IF(入力データ!$L$27="下宿",前提条件!$C$32,0)+IF(E8=18,前提条件!$C$33,0),0)))))))*(1+前提条件!$C$13)^(E$3-$B$3)))) | F24: =IF(F$3="","",IF(入力データ!$C$17<=0,0,IF(F$3="","",((SUM(入力データ!$C$58:$C$61)*12)+IF(F6="",0,IF(F6<=5,IF(入力データ!$G$25="私立",前提条件!$C$22,前提条件!$C$21),IF(F6<=11,IF(入力データ!$H$25="私立",前提条件!$C$24,前提条件!$C$23),IF(F6<=14,IF(入力データ!$I$25="私立",前提条件!$C$26,前提条件!$C$25),IF(F6<=17,IF(入力データ!$J$25="私立",前提条件!$C$28,前提条件!$C$27),IF(F6<=21,IF(入力データ!$K$25="国公立",前提条件!$C$29,IF(入力データ!$K$25="私立理系",前提条件!$C$31,前提条件!$C$30))+IF(入力データ!$L$25="下宿",前提条件!$C$32,0)+IF(F6=18,前提条件!$C$33,0),0))))))+IF(F7="",0,IF(F7<=5,IF(入力データ!$G$26="私立",前提条件!$C$22,前提条件!$C$21),IF(F7<=11,IF(入力データ!$H$26="私立",前提条件!$C$24,前提条件!$C$23),IF(F7<=14,IF(入力データ!$I$26="私立",前提条件!$C$26,前提条件!$C$25),IF(F7<=17,IF(入力データ!$J$26="私立",前提条件!$C$28,前提条件!$C$27),IF(F7<=21,IF(入力データ!$K$26="国公立",前提条件!$C$29,IF(入力データ!$K$26="私立理系",前提条件!$C$31,前提条件!$C$30))+IF(入力データ!$L$26="下宿",前提条件!$C$32,0)+IF(F7=18,前提条件!$C$33,0),0))))))+IF(F8="",0,IF(F8<=5,IF(入力データ!$G$27="私立",前提条件!$C$22,前提条件!$C$21),IF(F8<=11,IF(入力データ!$H$27="私立",前提条件!$C$24,前提条件!$C$23),IF(F8<=14,IF(入力データ!$I$27="私立",前提条件!$C$26,前提条件!$C$25),IF(F8<=17,IF(入力データ!$J$27="私立",前提条件!$C$28,前提条件!$C$27),IF(F8<=21,IF(入力データ!$K$27="国公立",前提条件!$C$29,IF(入力データ!$K$27="私立理系",前提条件!$C$31,前提条件!$C$30))+IF(入力データ!$L$27="下宿",前提条件!$C$32,0)+IF(F8=18,前提条件!$C$33,0),0)))))))*(1+前提条件!$C$13)^(F$3-$B$3)))) | G24: =IF(G$3="","",IF(入力データ!$C$17<=0,0,IF(G$3="","",((SUM(入力データ!$C$58:$C$61)*12)+IF(G6="",0,IF(G6<=5,IF(入力データ!$G$25="私立",前提条件!$C$22,前提条件!$C$21),IF(G6<=11,IF(入力データ!$H$25="私立",前提条件!$C$24,前提条件!$C$23),IF(G6<=14,IF(入力データ!$I$25="私立",前提条件!$C$26,前提条件!$C$25),IF(G6<=17,IF(入力データ!$J$25="私立",前提条件!$C$28,前提条件!$C$27),IF(G6<=21,IF(入力データ!$K$25="国公立",前提条件!$C$29,IF(入力データ!$K$25="私立理系",前提条件!$C$31,前提条件!$C$30))+IF(入力データ!$L$25="下宿",前提条件!$C$32,0)+IF(G6=18,前提条件!$C$33,0),0))))))+IF(G7="",0,IF(G7<=5,IF(入力データ!$G$26="私立",前提条件!$C$22,前提条件!$C$21),IF(G7<=11,IF(入力データ!$H$26="私立",前提条件!$C$24,前提条件!$C$23),IF(G7<=14,IF(入力データ!$I$26="私立",前提条件!$C$26,前提条件!$C$25),IF(G7<=17,IF(入力データ!$J$26="私立",前提条件!$C$28,前提条件!$C$27),IF(G7<=21,IF(入力データ!$K$26="国公立",前提条件!$C$29,IF(入力データ!$K$26="私立理系",前提条件!$C$31,前提条件!$C$30))+IF(入力データ!$L$26="下宿",前提条件!$C$32,0)+IF(G7=18,前提条件!$C$33,0),0))))))+IF(G8="",0,IF(G8<=5,IF(入力データ!$G$27="私立",前提条件!$C$22,前提条件!$C$21),IF(G8<=11,IF(入力データ!$H$27="私立",前提条件!$C$24,前提条件!$C$23),IF(G8<=14,IF(入力データ!$I$27="私立",前提条件!$C$26,前提条件!$C$25),IF(G8<=17,IF(入力データ!$J$27="私立",前提条件!$C$28,前提条件!$C$27),IF(G8<=21,IF(入力データ!$K$27="国公立",前提条件!$C$29,IF(入力データ!$K$27="私立理系",前提条件!$C$31,前提条件!$C$30))+IF(入力データ!$L$27="下宿",前提条件!$C$32,0)+IF(G8=18,前提条件!$C$33,0),0)))))))*(1+前提条件!$C$13)^(G$3-$B$3)))) | H24: =IF(H$3="","",IF(入力データ!$C$17<=0,0,IF(H$3="","",((SUM(入力データ!$C$58:$C$61)*12)+IF(H6="",0,IF(H6<=5,IF(入力データ!$G$25="私立",前提条件!$C$22,前提条件!$C$21),IF(H6<=11,IF(入力データ!$H$25="私立",前提条件!$C$24,前提条件!$C$23),IF(H6<=14,IF(入力データ!$I$25="私立",前提条件!$C$26,前提条件!$C$25),IF(H6<=17,IF(入力データ!$J$25="私立",前提条件!$C$28,前提条件!$C$27),IF(H6<=21,IF(入力データ!$K$25="国公立",前提条件!$C$29,IF(入力データ!$K$25="私立理系",前提条件!$C$31,前提条件!$C$30))+IF(入力データ!$L$25="下宿",前提条件!$C$32,0)+IF(H6=18,前提条件!$C$33,0),0))))))+IF(H7="",0,IF(H7<=5,IF(入力データ!$G$26="私立",前提条件!$C$22,前提条件!$C$21),IF(H7<=11,IF(入力データ!$H$26="私立",前提条件!$C$24,前提条件!$C$23),IF(H7<=14,IF(入力データ!$I$26="私立",前提条件!$C$26,前提条件!$C$25),IF(H7<=17,IF(入力データ!$J$26="私立",前提条件!$C$28,前提条件!$C$27),IF(H7<=21,IF(入力データ!$K$26="国公立",前提条件!$C$29,IF(入力データ!$K$26="私立理系",前提条件!$C$31,前提条件!$C$30))+IF(入力データ!$L$26="下宿",前提条件!$C$32,0)+IF(H7=18,前提条件!$C$33,0),0))))))+IF(H8="",0,IF(H8<=5,IF(入力データ!$G$27="私立",前提条件!$C$22,前提条件!$C$21),IF(H8<=11,IF(入力データ!$H$27="私立",前提条件!$C$24,前提条件!$C$23),IF(H8<=14,IF(入力データ!$I$27="私立",前提条件!$C$26,前提条件!$C$25),IF(H8<=17,IF(入力データ!$J$27="私立",前提条件!$C$28,前提条件!$C$27),IF(H8<=21,IF(入力データ!$K$27="国公立",前提条件!$C$29,IF(入力データ!$K$27="私立理系",前提条件!$C$31,前提条件!$C$30))+IF(入力データ!$L$27="下宿",前提条件!$C$32,0)+IF(H8=18,前提条件!$C$33,0),0)))))))*(1+前提条件!$C$13)^(H$3-$B$3)))) | I24: =IF(I$3="","",IF(入力データ!$C$17<=0,0,IF(I$3="","",((SUM(入力データ!$C$58:$C$61)*12)+IF(I6="",0,IF(I6<=5,IF(入力データ!$G$25="私立",前提条件!$C$22,前提条件!$C$21),IF(I6<=11,IF(入力データ!$H$25="私立",前提条件!$C$24,前提条件!$C$23),IF(I6<=14,IF(入力データ!$I$25="私立",前提条件!$C$26,前提条件!$C$25),IF(I6<=17,IF(入力データ!$J$25="私立",前提条件!$C$28,前提条件!$C$27),IF(I6<=21,IF(入力データ!$K$25="国公立",前提条件!$C$29,IF(入力データ!$K$25="私立理系",前提条件!$C$31,前提条件!$C$30))+IF(入力データ!$L$25="下宿",前提条件!$C$32,0)+IF(I6=18,前提条件!$C$33,0),0))))))+IF(I7="",0,IF(I7<=5,IF(入力データ!$G$26="私立",前提条件!$C$22,前提条件!$C$21),IF(I7<=11,IF(入力データ!$H$26="私立",前提条件!$C$24,前提条件!$C$23),IF(I7<=14,IF(入力データ!$I$26="私立",前提条件!$C$26,前提条件!$C$25),IF(I7<=17,IF(入力データ!$J$26="私立",前提条件!$C$28,前提条件!$C$27),IF(I7<=21,IF(入力データ!$K$26="国公立",前提条件!$C$29,IF(入力データ!$K$26="私立理系",前提条件!$C$31,前提条件!$C$30))+IF(入力データ!$L$26="下宿",前提条件!$C$32,0)+IF(I7=18,前提条件!$C$33,0),0))))))+IF(I8="",0,IF(I8<=5,IF(入力データ!$G$27="私立",前提条件!$C$22,前提条件!$C$21),IF(I8<=11,IF(入力データ!$H$27="私立",前提条件!$C$24,前提条件!$C$23),IF(I8<=14,IF(入力データ!$I$27="私立",前提条件!$C$26,前提条件!$C$25),IF(I8<=17,IF(入力データ!$J$27="私立",前提条件!$C$28,前提条件!$C$27),IF(I8<=21,IF(入力データ!$K$27="国公立",前提条件!$C$29,IF(入力データ!$K$27="私立理系",前提条件!$C$31,前提条件!$C$30))+IF(入力データ!$L$27="下宿",前提条件!$C$32,0)+IF(I8=18,前提条件!$C$33,0),0)))))))*(1+前提条件!$C$13)^(I$3-$B$3)))) | ... CW24: =IF(CW$3="","",IF(入力データ!$C$17<=0,0,IF(CW$3="","",((SUM(入力データ!$C$58:$C$61)*12)+IF(CW6="",0,IF(CW6<=5,IF(入力データ!$G$25="私立",前提条件!$C$22,前提条件!$C$21),IF(CW6<=11,IF(入力データ!$H$25="私立",前提条件!$C$24,前提条件!$C$23),IF(CW6<=14,IF(入力データ!$I$25="私立",前提条件!$C$26,前提条件!$C$25),IF(CW6<=17,IF(入力データ!$J$25="私立",前提条件!$C$28,前提条件!$C$27),IF(CW6<=21,IF(入力データ!$K$25="国公立",前提条件!$C$29,IF(入力データ!$K$25="私立理系",前提条件!$C$31,前提条件!$C$30))+IF(入力データ!$L$25="下宿",前提条件!$C$32,0)+IF(CW6=18,前提条件!$C$33,0),0))))))+IF(CW7="",0,IF(CW7<=5,IF(入力データ!$G$26="私立",前提条件!$C$22,前提条件!$C$21),IF(CW7<=11,IF(入力データ!$H$26="私立",前提条件!$C$24,前提条件!$C$23),IF(CW7<=14,IF(入力データ!$I$26="私立",前提条件!$C$26,前提条件!$C$25),IF(CW7<=17,IF(入力データ!$J$26="私立",前提条件!$C$28,前提条件!$C$27),IF(CW7<=21,IF(入力データ!$K$26="国公立",前提条件!$C$29,IF(入力データ!$K$26="私立理系",前提条件!$C$31,前提条件!$C$30))+IF(入力データ!$L$26="下宿",前提条件!$C$32,0)+IF(CW7=18,前提条件!$C$33,0),0))))))+IF(CW8="",0,IF(CW8<=5,IF(入力データ!$G$27="私立",前提条件!$C$22,前提条件!$C$21),IF(CW8<=11,IF(入力データ!$H$27="私立",前提条件!$C$24,前提条件!$C$23),IF(CW8<=14,IF(入力データ!$I$27="私立",前提条件!$C$26,前提条件!$C$25),IF(CW8<=17,IF(入力データ!$J$27="私立",前提条件!$C$28,前提条件!$C$27),IF(CW8<=21,IF(入力データ!$K$27="国公立",前提条件!$C$29,IF(入力データ!$K$27="私立理系",前提条件!$C$31,前提条件!$C$30))+IF(入力データ!$L$27="下宿",前提条件!$C$32,0)+IF(CW8=18,前提条件!$C$33,0),0)))))))*(1+前提条件!$C$13)^(CW$3-$B$3))))
A25: 車関連費 | B25: =IF(B$3="","",N(入力データ!$C$69)*12*(1+前提条件!$C$12)^(B$3-$B$3)) | C25: =IF(C$3="","",N(入力データ!$C$69)*12*(1+前提条件!$C$12)^(C$3-$B$3)) | D25: =IF(D$3="","",N(入力データ!$C$69)*12*(1+前提条件!$C$12)^(D$3-$B$3)) | E25: =IF(E$3="","",N(入力データ!$C$69)*12*(1+前提条件!$C$12)^(E$3-$B$3)) | F25: =IF(F$3="","",N(入力データ!$C$69)*12*(1+前提条件!$C$12)^(F$3-$B$3)) | G25: =IF(G$3="","",N(入力データ!$C$69)*12*(1+前提条件!$C$12)^(G$3-$B$3)) | H25: =IF(H$3="","",N(入力データ!$C$69)*12*(1+前提条件!$C$12)^(H$3-$B$3)) | I25: =IF(I$3="","",N(入力データ!$C$69)*12*(1+前提条件!$C$12)^(I$3-$B$3)) | ... CW25: =IF(CW$3="","",N(入力データ!$C$69)*12*(1+前提条件!$C$12)^(CW$3-$B$3))
A26: その他支出 | B26: =IF(B$3="","",SUM(入力データ!$C$71:$C$74)*12*(1+前提条件!$C$12)^(B$3-$B$3)) | C26: =IF(C$3="","",SUM(入力データ!$C$71:$C$74)*12*(1+前提条件!$C$12)^(C$3-$B$3)) | D26: =IF(D$3="","",SUM(入力データ!$C$71:$C$74)*12*(1+前提条件!$C$12)^(D$3-$B$3)) | E26: =IF(E$3="","",SUM(入力データ!$C$71:$C$74)*12*(1+前提条件!$C$12)^(E$3-$B$3)) | F26: =IF(F$3="","",SUM(入力データ!$C$71:$C$74)*12*(1+前提条件!$C$12)^(F$3-$B$3)) | G26: =IF(G$3="","",SUM(入力データ!$C$71:$C$74)*12*(1+前提条件!$C$12)^(G$3-$B$3)) | H26: =IF(H$3="","",SUM(入力データ!$C$71:$C$74)*12*(1+前提条件!$C$12)^(H$3-$B$3)) | I26: =IF(I$3="","",SUM(入力データ!$C$71:$C$74)*12*(1+前提条件!$C$12)^(I$3-$B$3)) | ... CW26: =IF(CW$3="","",SUM(入力データ!$C$71:$C$74)*12*(1+前提条件!$C$12)^(CW$3-$B$3))
A27: 一時支出 | B27: =IF(B$3="","",SUM(入力データ!$C$78:$C$82)) | C27: =IF(C$3="","",SUM(入力データ!$C$78:$C$82)) | D27: =IF(D$3="","",SUM(入力データ!$C$78:$C$82)) | E27: =IF(E$3="","",SUM(入力データ!$C$78:$C$82)) | F27: =IF(F$3="","",SUM(入力データ!$C$78:$C$82)) | G27: =IF(G$3="","",SUM(入力データ!$C$78:$C$82)) | H27: =IF(H$3="","",SUM(入力データ!$C$78:$C$82)) | I27: =IF(I$3="","",SUM(入力データ!$C$78:$C$82)) | ... CW27: =IF(CW$3="","",SUM(入力データ!$C$78:$C$82))
A28: 支出合計 | B28: =IF(B$3="","",SUM(B20:B27)) | C28: =IF(C$3="","",SUM(C20:C27)) | D28: =IF(D$3="","",SUM(D20:D27)) | E28: =IF(E$3="","",SUM(E20:E27)) | F28: =IF(F$3="","",SUM(F20:F27)) | G28: =IF(G$3="","",SUM(G20:G27)) | H28: =IF(H$3="","",SUM(H20:H27)) | I28: =IF(I$3="","",SUM(I20:I27)) | ... CW28: =IF(CW$3="","",SUM(CW20:CW27))
A29: 収支・資産
A30: 年間収支 | B30: =IF(B$3="","",B18-B28) | C30: =IF(C$3="","",C18-C28) | D30: =IF(D$3="","",D18-D28) | E30: =IF(E$3="","",E18-E28) | F30: =IF(F$3="","",F18-F28) | G30: =IF(G$3="","",G18-G28) | H30: =IF(H$3="","",H18-H28) | I30: =IF(I$3="","",I18-I28) | ... CW30: =IF(CW$3="","",CW18-CW28)
A31: 預貯金残高 | B31: =IF(B$3="","",B38) | C31: =IF(C$3="","",C38) | D31: =IF(D$3="","",D38) | E31: =IF(E$3="","",E38) | F31: =IF(F$3="","",F38) | G31: =IF(G$3="","",G38) | H31: =IF(H$3="","",H38) | I31: =IF(I$3="","",I38) | ... CW31: =IF(CW$3="","",CW38)
A32: 投資資産残高 | B32: =IF(B$3="","",((SUM(入力データ!$C$90:$C$92,入力データ!$C$94)*(1+前提条件!$C$60))+B36-B39)) | C32: =IF(C$3="","",((SUM(入力データ!$C$90:$C$92,入力データ!$C$94)*(1+前提条件!$C$60))+C36-C39)) | D32: =IF(D$3="","",((SUM(入力データ!$C$90:$C$92,入力データ!$C$94)*(1+前提条件!$C$60))+D36-D39)) | E32: =IF(E$3="","",((SUM(入力データ!$C$90:$C$92,入力データ!$C$94)*(1+前提条件!$C$60))+E36-E39)) | F32: =IF(F$3="","",((SUM(入力データ!$C$90:$C$92,入力データ!$C$94)*(1+前提条件!$C$60))+F36-F39)) | G32: =IF(G$3="","",((SUM(入力データ!$C$90:$C$92,入力データ!$C$94)*(1+前提条件!$C$60))+G36-G39)) | H32: =IF(H$3="","",((SUM(入力データ!$C$90:$C$92,入力データ!$C$94)*(1+前提条件!$C$60))+H36-H39)) | I32: =IF(I$3="","",((SUM(入力データ!$C$90:$C$92,入力データ!$C$94)*(1+前提条件!$C$60))+I36-I39)) | ... CW32: =IF(CW$3="","",((SUM(入力データ!$C$90:$C$92,入力データ!$C$94)*(1+前提条件!$C$60))+CW36-CW39))
A33: 解約返戻金残高 | B33: =IF(B$3="","",((入力データ!$C$93*(1+前提条件!$C$61))+B37-B40)) | C33: =IF(C$3="","",((入力データ!$C$93*(1+前提条件!$C$61))+C37-C40)) | D33: =IF(D$3="","",((入力データ!$C$93*(1+前提条件!$C$61))+D37-D40)) | E33: =IF(E$3="","",((入力データ!$C$93*(1+前提条件!$C$61))+E37-E40)) | F33: =IF(F$3="","",((入力データ!$C$93*(1+前提条件!$C$61))+F37-F40)) | G33: =IF(G$3="","",((入力データ!$C$93*(1+前提条件!$C$61))+G37-G40)) | H33: =IF(H$3="","",((入力データ!$C$93*(1+前提条件!$C$61))+H37-H40)) | I33: =IF(I$3="","",((入力データ!$C$93*(1+前提条件!$C$61))+I37-I40)) | ... CW33: =IF(CW$3="","",((入力データ!$C$93*(1+前提条件!$C$61))+CW37-CW40))
A34: 住宅ローン残高 | B34: =IF(B$3="","",IF(入力データ!$C$57="あり",0,MAX(入力データ!$C$95-B41,0))) | C34: =IF(C$3="","",IF(入力データ!$C$57="あり",0,MAX(B34-C41,0))) | D34: =IF(D$3="","",IF(入力データ!$C$57="あり",0,MAX(C34-D41,0))) | E34: =IF(E$3="","",IF(入力データ!$C$57="あり",0,MAX(D34-E41,0))) | F34: =IF(F$3="","",IF(入力データ!$C$57="あり",0,MAX(E34-F41,0))) | G34: =IF(G$3="","",IF(入力データ!$C$57="あり",0,MAX(F34-G41,0))) | H34: =IF(H$3="","",IF(入力データ!$C$57="あり",0,MAX(G34-H41,0))) | I34: =IF(I$3="","",IF(入力データ!$C$57="あり",0,MAX(H34-I41,0))) | J34: =IF(J$3="","",IF(入力データ!$C$57="あり",0,MAX(I34-J41,0))) | ... CW34: =IF(CW$3="","",IF(入力データ!$C$57="あり",0,MAX(CV34-CW41,0)))
A35: 保有資産合計（ローン除く） | B35: =IF(B$3="","",B31+B32+B33) | C35: =IF(C$3="","",C31+C32+C33) | D35: =IF(D$3="","",D31+D32+D33) | E35: =IF(E$3="","",E31+E32+E33) | F35: =IF(F$3="","",F31+F32+F33) | G35: =IF(G$3="","",G31+G32+G33) | H35: =IF(H$3="","",H31+H32+H33) | I35: =IF(I$3="","",I31+I32+I33) | ... CW35: =IF(CW$3="","",CW31+CW32+CW33)
A36: 投資積立年額(補助) | B36: =IF(B$3="","",SUM(入力データ!$C$101:$C$103,入力データ!$C$105)*12) | C36: =IF(C$3="","",SUM(入力データ!$C$101:$C$103,入力データ!$C$105)*12) | D36: =IF(D$3="","",SUM(入力データ!$C$101:$C$103,入力データ!$C$105)*12) | E36: =IF(E$3="","",SUM(入力データ!$C$101:$C$103,入力データ!$C$105)*12) | F36: =IF(F$3="","",SUM(入力データ!$C$101:$C$103,入力データ!$C$105)*12) | G36: =IF(G$3="","",SUM(入力データ!$C$101:$C$103,入力データ!$C$105)*12) | H36: =IF(H$3="","",SUM(入力データ!$C$101:$C$103,入力データ!$C$105)*12) | I36: =IF(I$3="","",SUM(入力データ!$C$101:$C$103,入力データ!$C$105)*12) | ... CW36: =IF(CW$3="","",SUM(入力データ!$C$101:$C$103,入力データ!$C$105)*12)
A37: 返戻金積立年額(補助) | B37: =IF(B$3="","",入力データ!$C$104*12) | C37: =IF(C$3="","",入力データ!$C$104*12) | D37: =IF(D$3="","",入力データ!$C$104*12) | E37: =IF(E$3="","",入力データ!$C$104*12) | F37: =IF(F$3="","",入力データ!$C$104*12) | G37: =IF(G$3="","",入力データ!$C$104*12) | H37: =IF(H$3="","",入力データ!$C$104*12) | I37: =IF(I$3="","",入力データ!$C$104*12) | ... CW37: =IF(CW$3="","",入力データ!$C$104*12)
A38: 預貯金前年差引前(補助) | B38: =IF(B$3="","",SUM(入力データ!$C$88:$C$89)+B30-B36-B37) | C38: =IF(C$3="","",B31+C30-C36-C37) | D38: =IF(D$3="","",C31+D30-D36-D37) | E38: =IF(E$3="","",D31+E30-E36-E37) | F38: =IF(F$3="","",E31+F30-F36-F37) | G38: =IF(G$3="","",F31+G30-G36-G37) | H38: =IF(H$3="","",G31+H30-H36-H37) | I38: =IF(I$3="","",H31+I30-I36-I37) | J38: =IF(J$3="","",I31+J30-J36-J37) | ... CW38: =IF(CW$3="","",CV31+CW30-CW36-CW37)
A39: 投資取り崩し額(補助) | B39: =IF(B$3="","",MAX(0,-B38)) | C39: =IF(C$3="","",MAX(0,-C38)) | D39: =IF(D$3="","",MAX(0,-D38)) | E39: =IF(E$3="","",MAX(0,-E38)) | F39: =IF(F$3="","",MAX(0,-F38)) | G39: =IF(G$3="","",MAX(0,-G38)) | H39: =IF(H$3="","",MAX(0,-H38)) | I39: =IF(I$3="","",MAX(0,-I38)) | ... CW39: =IF(CW$3="","",MAX(0,-CW38))
A40: 返戻金取り崩し額(補助) | B40: =IF(B$3="","",MAX(0,B39-((SUM(入力データ!$C$90:$C$92,入力データ!$C$94)*(1+前提条件!$C$60))+B36))) | C40: =IF(C$3="","",MAX(0,C39-((B32*(1+前提条件!$C$60))+C36))) | D40: =IF(D$3="","",MAX(0,D39-((C32*(1+前提条件!$C$60))+D36))) | E40: =IF(E$3="","",MAX(0,E39-((D32*(1+前提条件!$C$60))+E36))) | F40: =IF(F$3="","",MAX(0,F39-((E32*(1+前提条件!$C$60))+F36))) | G40: =IF(G$3="","",MAX(0,G39-((F32*(1+前提条件!$C$60))+G36))) | H40: =IF(H$3="","",MAX(0,H39-((G32*(1+前提条件!$C$60))+H36))) | I40: =IF(I$3="","",MAX(0,I39-((H32*(1+前提条件!$C$60))+I36))) | J40: =IF(J$3="","",MAX(0,J39-((I32*(1+前提条件!$C$60))+J36))) | ... CW40: =IF(CW$3="","",MAX(0,CW39-((CV32*(1+前提条件!$C$60))+CW36)))
A41: 年間住宅ローン元本返済(補助) | B41: =IF(B$3="","",IF(OR(入力データ!$C$57="あり",NOT(AND(B4<>"",B4<=前提条件!$C$44,入力データ!$C$95>0))),0,入力データ!$C$95/MAX(1,前提条件!$C$44-B4+1))) | C41: =IF(C$3="","",IF(OR(入力データ!$C$57="あり",C4>前提条件!$C$44),0,$B$41)) | D41: =IF(D$3="","",IF(OR(入力データ!$C$57="あり",D4>前提条件!$C$44),0,$B$41)) | E41: =IF(E$3="","",IF(OR(入力データ!$C$57="あり",E4>前提条件!$C$44),0,$B$41)) | F41: =IF(F$3="","",IF(OR(入力データ!$C$57="あり",F4>前提条件!$C$44),0,$B$41)) | G41: =IF(G$3="","",IF(OR(入力データ!$C$57="あり",G4>前提条件!$C$44),0,$B$41)) | H41: =IF(H$3="","",IF(OR(入力データ!$C$57="あり",H4>前提条件!$C$44),0,$B$41)) | I41: =IF(I$3="","",IF(OR(入力データ!$C$57="あり",I4>前提条件!$C$44),0,$B$41)) | J41: =IF(J$3="","",IF(OR(入力データ!$C$57="あり",J4>前提条件!$C$44),0,$B$41)) | ... CW41: =IF(CW$3="","",IF(OR(入力データ!$C$57="あり",CW4>前提条件!$C$44),0,$B$41))
A42: 老後期フラグ(補助) | B42: =IF(B$3="","",IF(AND(B4>=入力データ!$C$111,B5>=入力データ!$C$111),1,0)) | C42: =IF(C$3="","",IF(AND(C4>=入力データ!$C$111,C5>=入力データ!$C$111),1,0)) | D42: =IF(D$3="","",IF(AND(D4>=入力データ!$C$111,D5>=入力データ!$C$111),1,0)) | E42: =IF(E$3="","",IF(AND(E4>=入力データ!$C$111,E5>=入力データ!$C$111),1,0)) | F42: =IF(F$3="","",IF(AND(F4>=入力データ!$C$111,F5>=入力データ!$C$111),1,0)) | G42: =IF(G$3="","",IF(AND(G4>=入力データ!$C$111,G5>=入力データ!$C$111),1,0)) | H42: =IF(H$3="","",IF(AND(H4>=入力データ!$C$111,H5>=入力データ!$C$111),1,0)) | I42: =IF(I$3="","",IF(AND(I4>=入力データ!$C$111,I5>=入力データ!$C$111),1,0)) | ... CW42: =IF(CW$3="","",IF(AND(CW4>=入力データ!$C$111,CW5>=入力データ!$C$111),1,0))
A43: 老後不足額(補助) | B43: =IF(B$3="","",IF(B42=1,MAX(0,-B30),0)) | C43: =IF(C$3="","",IF(C42=1,MAX(0,-C30),0)) | D43: =IF(D$3="","",IF(D42=1,MAX(0,-D30),0)) | E43: =IF(E$3="","",IF(E42=1,MAX(0,-E30),0)) | F43: =IF(F$3="","",IF(F42=1,MAX(0,-F30),0)) | G43: =IF(G$3="","",IF(G42=1,MAX(0,-G30),0)) | H43: =IF(H$3="","",IF(H42=1,MAX(0,-H30),0)) | I43: =IF(I$3="","",IF(I42=1,MAX(0,-I30),0)) | ... CW43: =IF(CW$3="","",IF(CW42=1,MAX(0,-CW30),0))
A44: 保有資産合計（参考） | B44: =IF(B$3="","",B31+B32+B33) | C44: =IF(C$3="","",C31+C32+C33) | D44: =IF(D$3="","",D31+D32+D33) | E44: =IF(E$3="","",E31+E32+E33) | F44: =IF(F$3="","",F31+F32+F33) | G44: =IF(G$3="","",G31+G32+G33) | H44: =IF(H$3="","",H31+H32+H33) | I44: =IF(I$3="","",I31+I32+I33) | ... CW44: =IF(CW$3="","",CW31+CW32+CW33)
A45: 負債合計（参考） | B45: =IF(B$3="","",B34) | C45: =IF(C$3="","",C34) | D45: =IF(D$3="","",D34) | E45: =IF(E$3="","",E34) | F45: =IF(F$3="","",F34) | G45: =IF(G$3="","",G34) | H45: =IF(H$3="","",H34) | I45: =IF(I$3="","",I34) | ... CW45: =IF(CW$3="","",CW34)
A47: ※初版前提：ご主人様収入・ご主人様退職金・ご主人様年金を0、基本生活費圧縮、遺族年金・団信を反映。死亡保険金の受取額は未反映です。

Sheet CF表（奥様死亡時）
A1: CF表（奥様死亡時 / 年次CF / 左→右に年が進む）
A2: 試算終了年 | B2: =MAX(IF(入力データ!$C$10<>"",YEAR(入力データ!$C$10)+100,0),IF(入力データ!$C$11<>"",YEAR(入力データ!$C$11)+100,0))
A3: 年 | B3: =IF(YEAR(入力データ!$C$5)>$B$2,"",YEAR(入力データ!$C$5)) | C3: =IF(B3="","",IF(B3+1>$B$2,"",B3+1)) | D3: =IF(C3="","",IF(C3+1>$B$2,"",C3+1)) | E3: =IF(D3="","",IF(D3+1>$B$2,"",D3+1)) | F3: =IF(E3="","",IF(E3+1>$B$2,"",E3+1)) | G3: =IF(F3="","",IF(F3+1>$B$2,"",F3+1)) | H3: =IF(G3="","",IF(G3+1>$B$2,"",G3+1)) | I3: =IF(H3="","",IF(H3+1>$B$2,"",H3+1)) | J3: =IF(I3="","",IF(I3+1>$B$2,"",I3+1)) | ... CW3: =IF(CV3="","",IF(CV3+1>$B$2,"",CV3+1))
A4: ご主人様年齢 | B4: =IF(B$3="","",IF(入力データ!$C$10="","",YEAR(DATE(B$3,12,31))-YEAR(入力データ!$C$10)-IF(DATE(B$3,12,31)<DATE(B$3,MONTH(入力データ!$C$10),DAY(入力データ!$C$10)),1,0))) | C4: =IF(C$3="","",IF(入力データ!$C$10="","",YEAR(DATE(C$3,12,31))-YEAR(入力データ!$C$10)-IF(DATE(C$3,12,31)<DATE(C$3,MONTH(入力データ!$C$10),DAY(入力データ!$C$10)),1,0))) | D4: =IF(D$3="","",IF(入力データ!$C$10="","",YEAR(DATE(D$3,12,31))-YEAR(入力データ!$C$10)-IF(DATE(D$3,12,31)<DATE(D$3,MONTH(入力データ!$C$10),DAY(入力データ!$C$10)),1,0))) | E4: =IF(E$3="","",IF(入力データ!$C$10="","",YEAR(DATE(E$3,12,31))-YEAR(入力データ!$C$10)-IF(DATE(E$3,12,31)<DATE(E$3,MONTH(入力データ!$C$10),DAY(入力データ!$C$10)),1,0))) | F4: =IF(F$3="","",IF(入力データ!$C$10="","",YEAR(DATE(F$3,12,31))-YEAR(入力データ!$C$10)-IF(DATE(F$3,12,31)<DATE(F$3,MONTH(入力データ!$C$10),DAY(入力データ!$C$10)),1,0))) | G4: =IF(G$3="","",IF(入力データ!$C$10="","",YEAR(DATE(G$3,12,31))-YEAR(入力データ!$C$10)-IF(DATE(G$3,12,31)<DATE(G$3,MONTH(入力データ!$C$10),DAY(入力データ!$C$10)),1,0))) | H4: =IF(H$3="","",IF(入力データ!$C$10="","",YEAR(DATE(H$3,12,31))-YEAR(入力データ!$C$10)-IF(DATE(H$3,12,31)<DATE(H$3,MONTH(入力データ!$C$10),DAY(入力データ!$C$10)),1,0))) | I4: =IF(I$3="","",IF(入力データ!$C$10="","",YEAR(DATE(I$3,12,31))-YEAR(入力データ!$C$10)-IF(DATE(I$3,12,31)<DATE(I$3,MONTH(入力データ!$C$10),DAY(入力データ!$C$10)),1,0))) | ... CW4: =IF(CW$3="","",IF(入力データ!$C$10="","",YEAR(DATE(CW$3,12,31))-YEAR(入力データ!$C$10)-IF(DATE(CW$3,12,31)<DATE(CW$3,MONTH(入力データ!$C$10),DAY(入力データ!$C$10)),1,0)))
A5: 奥様年齢 | B5: =IF(B$3="","",IF(入力データ!$C$11="","",YEAR(DATE(B$3,12,31))-YEAR(入力データ!$C$11)-IF(DATE(B$3,12,31)<DATE(B$3,MONTH(入力データ!$C$11),DAY(入力データ!$C$11)),1,0))) | C5: =IF(C$3="","",IF(入力データ!$C$11="","",YEAR(DATE(C$3,12,31))-YEAR(入力データ!$C$11)-IF(DATE(C$3,12,31)<DATE(C$3,MONTH(入力データ!$C$11),DAY(入力データ!$C$11)),1,0))) | D5: =IF(D$3="","",IF(入力データ!$C$11="","",YEAR(DATE(D$3,12,31))-YEAR(入力データ!$C$11)-IF(DATE(D$3,12,31)<DATE(D$3,MONTH(入力データ!$C$11),DAY(入力データ!$C$11)),1,0))) | E5: =IF(E$3="","",IF(入力データ!$C$11="","",YEAR(DATE(E$3,12,31))-YEAR(入力データ!$C$11)-IF(DATE(E$3,12,31)<DATE(E$3,MONTH(入力データ!$C$11),DAY(入力データ!$C$11)),1,0))) | F5: =IF(F$3="","",IF(入力データ!$C$11="","",YEAR(DATE(F$3,12,31))-YEAR(入力データ!$C$11)-IF(DATE(F$3,12,31)<DATE(F$3,MONTH(入力データ!$C$11),DAY(入力データ!$C$11)),1,0))) | G5: =IF(G$3="","",IF(入力データ!$C$11="","",YEAR(DATE(G$3,12,31))-YEAR(入力データ!$C$11)-IF(DATE(G$3,12,31)<DATE(G$3,MONTH(入力データ!$C$11),DAY(入力データ!$C$11)),1,0))) | H5: =IF(H$3="","",IF(入力データ!$C$11="","",YEAR(DATE(H$3,12,31))-YEAR(入力データ!$C$11)-IF(DATE(H$3,12,31)<DATE(H$3,MONTH(入力データ!$C$11),DAY(入力データ!$C$11)),1,0))) | I5: =IF(I$3="","",IF(入力データ!$C$11="","",YEAR(DATE(I$3,12,31))-YEAR(入力データ!$C$11)-IF(DATE(I$3,12,31)<DATE(I$3,MONTH(入力データ!$C$11),DAY(入力データ!$C$11)),1,0))) | ... CW5: =IF(CW$3="","",IF(入力データ!$C$11="","",YEAR(DATE(CW$3,12,31))-YEAR(入力データ!$C$11)-IF(DATE(CW$3,12,31)<DATE(CW$3,MONTH(入力データ!$C$11),DAY(入力データ!$C$11)),1,0)))
A6: 子1年齢 | B6: =IF(B$3="","",IF(入力データ!$C$19="","",YEAR(DATE(B$3,12,31))-YEAR(入力データ!$C$19)-IF(DATE(B$3,12,31)<DATE(B$3,MONTH(入力データ!$C$19),DAY(入力データ!$C$19)),1,0))) | C6: =IF(C$3="","",IF(入力データ!$C$19="","",YEAR(DATE(C$3,12,31))-YEAR(入力データ!$C$19)-IF(DATE(C$3,12,31)<DATE(C$3,MONTH(入力データ!$C$19),DAY(入力データ!$C$19)),1,0))) | D6: =IF(D$3="","",IF(入力データ!$C$19="","",YEAR(DATE(D$3,12,31))-YEAR(入力データ!$C$19)-IF(DATE(D$3,12,31)<DATE(D$3,MONTH(入力データ!$C$19),DAY(入力データ!$C$19)),1,0))) | E6: =IF(E$3="","",IF(入力データ!$C$19="","",YEAR(DATE(E$3,12,31))-YEAR(入力データ!$C$19)-IF(DATE(E$3,12,31)<DATE(E$3,MONTH(入力データ!$C$19),DAY(入力データ!$C$19)),1,0))) | F6: =IF(F$3="","",IF(入力データ!$C$19="","",YEAR(DATE(F$3,12,31))-YEAR(入力データ!$C$19)-IF(DATE(F$3,12,31)<DATE(F$3,MONTH(入力データ!$C$19),DAY(入力データ!$C$19)),1,0))) | G6: =IF(G$3="","",IF(入力データ!$C$19="","",YEAR(DATE(G$3,12,31))-YEAR(入力データ!$C$19)-IF(DATE(G$3,12,31)<DATE(G$3,MONTH(入力データ!$C$19),DAY(入力データ!$C$19)),1,0))) | H6: =IF(H$3="","",IF(入力データ!$C$19="","",YEAR(DATE(H$3,12,31))-YEAR(入力データ!$C$19)-IF(DATE(H$3,12,31)<DATE(H$3,MONTH(入力データ!$C$19),DAY(入力データ!$C$19)),1,0))) | I6: =IF(I$3="","",IF(入力データ!$C$19="","",YEAR(DATE(I$3,12,31))-YEAR(入力データ!$C$19)-IF(DATE(I$3,12,31)<DATE(I$3,MONTH(入力データ!$C$19),DAY(入力データ!$C$19)),1,0))) | ... CW6: =IF(CW$3="","",IF(入力データ!$C$19="","",YEAR(DATE(CW$3,12,31))-YEAR(入力データ!$C$19)-IF(DATE(CW$3,12,31)<DATE(CW$3,MONTH(入力データ!$C$19),DAY(入力データ!$C$19)),1,0)))
A7: 子2年齢 | B7: =IF(B$3="","",IF(入力データ!$C$21="","",YEAR(DATE(B$3,12,31))-YEAR(入力データ!$C$21)-IF(DATE(B$3,12,31)<DATE(B$3,MONTH(入力データ!$C$21),DAY(入力データ!$C$21)),1,0))) | C7: =IF(C$3="","",IF(入力データ!$C$21="","",YEAR(DATE(C$3,12,31))-YEAR(入力データ!$C$21)-IF(DATE(C$3,12,31)<DATE(C$3,MONTH(入力データ!$C$21),DAY(入力データ!$C$21)),1,0))) | D7: =IF(D$3="","",IF(入力データ!$C$21="","",YEAR(DATE(D$3,12,31))-YEAR(入力データ!$C$21)-IF(DATE(D$3,12,31)<DATE(D$3,MONTH(入力データ!$C$21),DAY(入力データ!$C$21)),1,0))) | E7: =IF(E$3="","",IF(入力データ!$C$21="","",YEAR(DATE(E$3,12,31))-YEAR(入力データ!$C$21)-IF(DATE(E$3,12,31)<DATE(E$3,MONTH(入力データ!$C$21),DAY(入力データ!$C$21)),1,0))) | F7: =IF(F$3="","",IF(入力データ!$C$21="","",YEAR(DATE(F$3,12,31))-YEAR(入力データ!$C$21)-IF(DATE(F$3,12,31)<DATE(F$3,MONTH(入力データ!$C$21),DAY(入力データ!$C$21)),1,0))) | G7: =IF(G$3="","",IF(入力データ!$C$21="","",YEAR(DATE(G$3,12,31))-YEAR(入力データ!$C$21)-IF(DATE(G$3,12,31)<DATE(G$3,MONTH(入力データ!$C$21),DAY(入力データ!$C$21)),1,0))) | H7: =IF(H$3="","",IF(入力データ!$C$21="","",YEAR(DATE(H$3,12,31))-YEAR(入力データ!$C$21)-IF(DATE(H$3,12,31)<DATE(H$3,MONTH(入力データ!$C$21),DAY(入力データ!$C$21)),1,0))) | I7: =IF(I$3="","",IF(入力データ!$C$21="","",YEAR(DATE(I$3,12,31))-YEAR(入力データ!$C$21)-IF(DATE(I$3,12,31)<DATE(I$3,MONTH(入力データ!$C$21),DAY(入力データ!$C$21)),1,0))) | ... CW7: =IF(CW$3="","",IF(入力データ!$C$21="","",YEAR(DATE(CW$3,12,31))-YEAR(入力データ!$C$21)-IF(DATE(CW$3,12,31)<DATE(CW$3,MONTH(入力データ!$C$21),DAY(入力データ!$C$21)),1,0)))
A8: 子3年齢 | B8: =IF(B$3="","",IF(情報入力!$C$23="","",YEAR(DATE(B$3,12,31))-YEAR(情報入力!$C$23)-IF(DATE(B$3,12,31)<DATE(B$3,MONTH(情報入力!$C$23),DAY(情報入力!$C$23)),1,0))) | C8: =IF(C$3="","",IF(情報入力!$C$23="","",YEAR(DATE(C$3,12,31))-YEAR(情報入力!$C$23)-IF(DATE(C$3,12,31)<DATE(C$3,MONTH(情報入力!$C$23),DAY(情報入力!$C$23)),1,0))) | D8: =IF(D$3="","",IF(情報入力!$C$23="","",YEAR(DATE(D$3,12,31))-YEAR(情報入力!$C$23)-IF(DATE(D$3,12,31)<DATE(D$3,MONTH(情報入力!$C$23),DAY(情報入力!$C$23)),1,0))) | E8: =IF(E$3="","",IF(情報入力!$C$23="","",YEAR(DATE(E$3,12,31))-YEAR(情報入力!$C$23)-IF(DATE(E$3,12,31)<DATE(E$3,MONTH(情報入力!$C$23),DAY(情報入力!$C$23)),1,0))) | F8: =IF(F$3="","",IF(情報入力!$C$23="","",YEAR(DATE(F$3,12,31))-YEAR(情報入力!$C$23)-IF(DATE(F$3,12,31)<DATE(F$3,MONTH(情報入力!$C$23),DAY(情報入力!$C$23)),1,0))) | G8: =IF(G$3="","",IF(情報入力!$C$23="","",YEAR(DATE(G$3,12,31))-YEAR(情報入力!$C$23)-IF(DATE(G$3,12,31)<DATE(G$3,MONTH(情報入力!$C$23),DAY(情報入力!$C$23)),1,0))) | H8: =IF(H$3="","",IF(情報入力!$C$23="","",YEAR(DATE(H$3,12,31))-YEAR(情報入力!$C$23)-IF(DATE(H$3,12,31)<DATE(H$3,MONTH(情報入力!$C$23),DAY(情報入力!$C$23)),1,0))) | I8: =IF(I$3="","",IF(情報入力!$C$23="","",YEAR(DATE(I$3,12,31))-YEAR(情報入力!$C$23)-IF(DATE(I$3,12,31)<DATE(I$3,MONTH(情報入力!$C$23),DAY(情報入力!$C$23)),1,0))) | ... CW8: =IF(CW$3="","",IF(情報入力!$C$23="","",YEAR(DATE(CW$3,12,31))-YEAR(情報入力!$C$23)-IF(DATE(CW$3,12,31)<DATE(CW$3,MONTH(情報入力!$C$23),DAY(情報入力!$C$23)),1,0)))
A9: 家族年齢
A10: ご主人様収入 | B10: =IF(B$3="","",IF(B4<入力データ!$C$109,((入力データ!$C$29*12)+IF(入力データ!$C$31="あり",入力データ!$C$32,0))*(1+前提条件!$C$5)^(B$3-$B$3),0)) | C10: =IF(C$3="","",IF(C4<入力データ!$C$109,((入力データ!$C$29*12)+IF(入力データ!$C$31="あり",入力データ!$C$32,0))*(1+前提条件!$C$5)^(C$3-$B$3),0)) | D10: =IF(D$3="","",IF(D4<入力データ!$C$109,((入力データ!$C$29*12)+IF(入力データ!$C$31="あり",入力データ!$C$32,0))*(1+前提条件!$C$5)^(D$3-$B$3),0)) | E10: =IF(E$3="","",IF(E4<入力データ!$C$109,((入力データ!$C$29*12)+IF(入力データ!$C$31="あり",入力データ!$C$32,0))*(1+前提条件!$C$5)^(E$3-$B$3),0)) | F10: =IF(F$3="","",IF(F4<入力データ!$C$109,((入力データ!$C$29*12)+IF(入力データ!$C$31="あり",入力データ!$C$32,0))*(1+前提条件!$C$5)^(F$3-$B$3),0)) | G10: =IF(G$3="","",IF(G4<入力データ!$C$109,((入力データ!$C$29*12)+IF(入力データ!$C$31="あり",入力データ!$C$32,0))*(1+前提条件!$C$5)^(G$3-$B$3),0)) | H10: =IF(H$3="","",IF(H4<入力データ!$C$109,((入力データ!$C$29*12)+IF(入力データ!$C$31="あり",入力データ!$C$32,0))*(1+前提条件!$C$5)^(H$3-$B$3),0)) | I10: =IF(I$3="","",IF(I4<入力データ!$C$109,((入力データ!$C$29*12)+IF(入力データ!$C$31="あり",入力データ!$C$32,0))*(1+前提条件!$C$5)^(I$3-$B$3),0)) | ... CW10: =IF(CW$3="","",IF(CW4<入力データ!$C$109,((入力データ!$C$29*12)+IF(入力データ!$C$31="あり",入力データ!$C$32,0))*(1+前提条件!$C$5)^(CW$3-$B$3),0))
A11: 奥様収入 | B11: =IF(B$3="","",0) | C11: =IF(C$3="","",0) | D11: =IF(D$3="","",0) | E11: =IF(E$3="","",0) | F11: =IF(F$3="","",0) | G11: =IF(G$3="","",0) | H11: =IF(H$3="","",0) | I11: =IF(I$3="","",0) | ... CW11: =IF(CW$3="","",0)
A12: 児童手当 | B12: =IF(B$3="","",IF(AND(B6<>"",B6<=前提条件!$C$8),IF(1>=3,30000,IF(B6<3,15000,10000))*6,0)+IF(AND(B7<>"",B7<=前提条件!$C$8),IF(2>=3,30000,IF(B7<3,15000,10000))*6,0)+IF(AND(B8<>"",B8<=前提条件!$C$8),30000*6,0)) | C12: =IF(C$3="","",IF(AND(C6<>"",C6<=前提条件!$C$8),IF(1>=3,30000,IF(C6<3,15000,10000))*6,0)+IF(AND(C7<>"",C7<=前提条件!$C$8),IF(2>=3,30000,IF(C7<3,15000,10000))*6,0)+IF(AND(C8<>"",C8<=前提条件!$C$8),30000*6,0)) | D12: =IF(D$3="","",IF(AND(D6<>"",D6<=前提条件!$C$8),IF(1>=3,30000,IF(D6<3,15000,10000))*6,0)+IF(AND(D7<>"",D7<=前提条件!$C$8),IF(2>=3,30000,IF(D7<3,15000,10000))*6,0)+IF(AND(D8<>"",D8<=前提条件!$C$8),30000*6,0)) | E12: =IF(E$3="","",IF(AND(E6<>"",E6<=前提条件!$C$8),IF(1>=3,30000,IF(E6<3,15000,10000))*6,0)+IF(AND(E7<>"",E7<=前提条件!$C$8),IF(2>=3,30000,IF(E7<3,15000,10000))*6,0)+IF(AND(E8<>"",E8<=前提条件!$C$8),30000*6,0)) | F12: =IF(F$3="","",IF(AND(F6<>"",F6<=前提条件!$C$8),IF(1>=3,30000,IF(F6<3,15000,10000))*6,0)+IF(AND(F7<>"",F7<=前提条件!$C$8),IF(2>=3,30000,IF(F7<3,15000,10000))*6,0)+IF(AND(F8<>"",F8<=前提条件!$C$8),30000*6,0)) | G12: =IF(G$3="","",IF(AND(G6<>"",G6<=前提条件!$C$8),IF(1>=3,30000,IF(G6<3,15000,10000))*6,0)+IF(AND(G7<>"",G7<=前提条件!$C$8),IF(2>=3,30000,IF(G7<3,15000,10000))*6,0)+IF(AND(G8<>"",G8<=前提条件!$C$8),30000*6,0)) | H12: =IF(H$3="","",IF(AND(H6<>"",H6<=前提条件!$C$8),IF(1>=3,30000,IF(H6<3,15000,10000))*6,0)+IF(AND(H7<>"",H7<=前提条件!$C$8),IF(2>=3,30000,IF(H7<3,15000,10000))*6,0)+IF(AND(H8<>"",H8<=前提条件!$C$8),30000*6,0)) | I12: =IF(I$3="","",IF(AND(I6<>"",I6<=前提条件!$C$8),IF(1>=3,30000,IF(I6<3,15000,10000))*6,0)+IF(AND(I7<>"",I7<=前提条件!$C$8),IF(2>=3,30000,IF(I7<3,15000,10000))*6,0)+IF(AND(I8<>"",I8<=前提条件!$C$8),30000*6,0)) | ... CV12: =IF(CV$3="","",IF(AND(CV6<>"",CV6<=前提条件!$C$8),IF(1>=3,30000,IF(CV6<3,15000,10000))*6,0)+IF(AND(CV7<>"",CV7<=前提条件!$C$8),IF(2>=3,30000,IF(CV7<3,15000,10000))*6,0)+IF(AND(CV8<>"",CV8<=前提条件!$C$8),30000*6,0)) | CW12: =IF(CW$3="","",IF(AND(CW6<>"",CW6<=前提条件!$C$8),入力データ!$C$34*6,0)+IF(AND(CW7<>"",CW7<=前提条件!$C$8),入力データ!$C$34*6,0)+IF(AND(CW8<>"",CW8<=前提条件!$C$8),入力データ!$C$34*6,0))
A13: その他収入 | B13: =IF(B$3="","",入力データ!$C$35*12+IF(AND(B4<>"",B4<前提条件!$C$37),前提条件!$C$58*12,0)) | C13: =IF(C$3="","",入力データ!$C$35*12+IF(AND(C4<>"",C4<前提条件!$C$37),前提条件!$C$58*12,0)) | D13: =IF(D$3="","",入力データ!$C$35*12+IF(AND(D4<>"",D4<前提条件!$C$37),前提条件!$C$58*12,0)) | E13: =IF(E$3="","",入力データ!$C$35*12+IF(AND(E4<>"",E4<前提条件!$C$37),前提条件!$C$58*12,0)) | F13: =IF(F$3="","",入力データ!$C$35*12+IF(AND(F4<>"",F4<前提条件!$C$37),前提条件!$C$58*12,0)) | G13: =IF(G$3="","",入力データ!$C$35*12+IF(AND(G4<>"",G4<前提条件!$C$37),前提条件!$C$58*12,0)) | H13: =IF(H$3="","",入力データ!$C$35*12+IF(AND(H4<>"",H4<前提条件!$C$37),前提条件!$C$58*12,0)) | I13: =IF(I$3="","",入力データ!$C$35*12+IF(AND(I4<>"",I4<前提条件!$C$37),前提条件!$C$58*12,0)) | ... CW13: =IF(CW$3="","",入力データ!$C$35*12+IF(AND(CW4<>"",CW4<前提条件!$C$37),前提条件!$C$58*12,0))
A14: ご主人様退職金 | B14: =IF(B$3="","",IF(B4=入力データ!$C$109,入力データ!$C$36,0)) | C14: =IF(C$3="","",IF(C4=入力データ!$C$109,入力データ!$C$36,0)) | D14: =IF(D$3="","",IF(D4=入力データ!$C$109,入力データ!$C$36,0)) | E14: =IF(E$3="","",IF(E4=入力データ!$C$109,入力データ!$C$36,0)) | F14: =IF(F$3="","",IF(F4=入力データ!$C$109,入力データ!$C$36,0)) | G14: =IF(G$3="","",IF(G4=入力データ!$C$109,入力データ!$C$36,0)) | H14: =IF(H$3="","",IF(H4=入力データ!$C$109,入力データ!$C$36,0)) | I14: =IF(I$3="","",IF(I4=入力データ!$C$109,入力データ!$C$36,0)) | ... CW14: =IF(CW$3="","",IF(CW4=入力データ!$C$109,入力データ!$C$36,0))
A15: 奥様退職金 | B15: =IF(B$3="","",0) | C15: =IF(C$3="","",0) | D15: =IF(D$3="","",0) | E15: =IF(E$3="","",0) | F15: =IF(F$3="","",0) | G15: =IF(G$3="","",0) | H15: =IF(H$3="","",0) | I15: =IF(I$3="","",0) | ... CW15: =IF(CW$3="","",0)
A16: ご主人様年金収入 | B16: =IF(B$3="","",IF(B4>=前提条件!$C$37,前提条件!$C$39*12,0)) | C16: =IF(C$3="","",IF(C4>=前提条件!$C$37,前提条件!$C$39*12,0)) | D16: =IF(D$3="","",IF(D4>=前提条件!$C$37,前提条件!$C$39*12,0)) | E16: =IF(E$3="","",IF(E4>=前提条件!$C$37,前提条件!$C$39*12,0)) | F16: =IF(F$3="","",IF(F4>=前提条件!$C$37,前提条件!$C$39*12,0)) | G16: =IF(G$3="","",IF(G4>=前提条件!$C$37,前提条件!$C$39*12,0)) | H16: =IF(H$3="","",IF(H4>=前提条件!$C$37,前提条件!$C$39*12,0)) | I16: =IF(I$3="","",IF(I4>=前提条件!$C$37,前提条件!$C$39*12,0)) | ... CW16: =IF(CW$3="","",IF(CW4>=前提条件!$C$37,前提条件!$C$39*12,0))
A17: 奥様年金収入 | B17: =IF(B$3="","",0) | C17: =IF(C$3="","",0) | D17: =IF(D$3="","",0) | E17: =IF(E$3="","",0) | F17: =IF(F$3="","",0) | G17: =IF(G$3="","",0) | H17: =IF(H$3="","",0) | I17: =IF(I$3="","",0) | ... CW17: =IF(CW$3="","",0)
A18: 世帯収入合計 | B18: =IF(B$3="","",SUM(B10:B17)) | C18: =IF(C$3="","",SUM(C10:C17)) | D18: =IF(D$3="","",SUM(D10:D17)) | E18: =IF(E$3="","",SUM(E10:E17)) | F18: =IF(F$3="","",SUM(F10:F17)) | G18: =IF(G$3="","",SUM(G10:G17)) | H18: =IF(H$3="","",SUM(H10:H17)) | I18: =IF(I$3="","",SUM(I10:I17)) | ... CW18: =IF(CW$3="","",SUM(CW10:CW17))
A19: 収入
A20: 基本生活費 | B20: =IF(B$3="","",(IF(MIN(B4,B5)>=入力データ!$C$111,入力データ!$C$112*12*(1+前提条件!$C$14)^(B$3-$B$3),SUM(入力データ!$C$41:$C$52)*12*(1+前提条件!$C$12)^(B$3-$B$3)))*前提条件!$C$52) | C20: =IF(C$3="","",(IF(MIN(C4,C5)>=入力データ!$C$111,入力データ!$C$112*12*(1+前提条件!$C$14)^(C$3-$B$3),SUM(入力データ!$C$41:$C$52)*12*(1+前提条件!$C$12)^(C$3-$B$3)))*前提条件!$C$52) | D20: =IF(D$3="","",(IF(MIN(D4,D5)>=入力データ!$C$111,入力データ!$C$112*12*(1+前提条件!$C$14)^(D$3-$B$3),SUM(入力データ!$C$41:$C$52)*12*(1+前提条件!$C$12)^(D$3-$B$3)))*前提条件!$C$52) | E20: =IF(E$3="","",(IF(MIN(E4,E5)>=入力データ!$C$111,入力データ!$C$112*12*(1+前提条件!$C$14)^(E$3-$B$3),SUM(入力データ!$C$41:$C$52)*12*(1+前提条件!$C$12)^(E$3-$B$3)))*前提条件!$C$52) | F20: =IF(F$3="","",(IF(MIN(F4,F5)>=入力データ!$C$111,入力データ!$C$112*12*(1+前提条件!$C$14)^(F$3-$B$3),SUM(入力データ!$C$41:$C$52)*12*(1+前提条件!$C$12)^(F$3-$B$3)))*前提条件!$C$52) | G20: =IF(G$3="","",(IF(MIN(G4,G5)>=入力データ!$C$111,入力データ!$C$112*12*(1+前提条件!$C$14)^(G$3-$B$3),SUM(入力データ!$C$41:$C$52)*12*(1+前提条件!$C$12)^(G$3-$B$3)))*前提条件!$C$52) | H20: =IF(H$3="","",(IF(MIN(H4,H5)>=入力データ!$C$111,入力データ!$C$112*12*(1+前提条件!$C$14)^(H$3-$B$3),SUM(入力データ!$C$41:$C$52)*12*(1+前提条件!$C$12)^(H$3-$B$3)))*前提条件!$C$52) | I20: =IF(I$3="","",(IF(MIN(I4,I5)>=入力データ!$C$111,入力データ!$C$112*12*(1+前提条件!$C$14)^(I$3-$B$3),SUM(入力データ!$C$41:$C$52)*12*(1+前提条件!$C$12)^(I$3-$B$3)))*前提条件!$C$52) | ... CW20: =IF(CW$3="","",(IF(MIN(CW4,CW5)>=入力データ!$C$111,入力データ!$C$112*12*(1+前提条件!$C$14)^(CW$3-$B$3),SUM(入力データ!$C$41:$C$52)*12*(1+前提条件!$C$12)^(CW$3-$B$3)))*前提条件!$C$52)
A21: 住居費 | B21: =IF(B$3="","",((IF(入力データ!$C$13="持ち家",IF(入力データ!$C$57="あり",0,IF(B5<=前提条件!$C$44,入力データ!$C$53,0)),入力データ!$C$53)+入力データ!$C$54+入力データ!$C$55+入力データ!$C$56)*12+IF(入力データ!$C$13="持ち家",入力データ!$C$83+前提条件!$C$47,入力データ!$C$84+前提条件!$C$48))*(1+前提条件!$C$15)^(B$3-$B$3)) | C21: =IF(C$3="","",((IF(入力データ!$C$13="持ち家",IF(入力データ!$C$57="あり",0,IF(C5<=前提条件!$C$44,入力データ!$C$53,0)),入力データ!$C$53)+入力データ!$C$54+入力データ!$C$55+入力データ!$C$56)*12+IF(入力データ!$C$13="持ち家",入力データ!$C$83+前提条件!$C$47,入力データ!$C$84+前提条件!$C$48))*(1+前提条件!$C$15)^(C$3-$B$3)) | D21: =IF(D$3="","",((IF(入力データ!$C$13="持ち家",IF(入力データ!$C$57="あり",0,IF(D5<=前提条件!$C$44,入力データ!$C$53,0)),入力データ!$C$53)+入力データ!$C$54+入力データ!$C$55+入力データ!$C$56)*12+IF(入力データ!$C$13="持ち家",入力データ!$C$83+前提条件!$C$47,入力データ!$C$84+前提条件!$C$48))*(1+前提条件!$C$15)^(D$3-$B$3)) | E21: =IF(E$3="","",((IF(入力データ!$C$13="持ち家",IF(入力データ!$C$57="あり",0,IF(E5<=前提条件!$C$44,入力データ!$C$53,0)),入力データ!$C$53)+入力データ!$C$54+入力データ!$C$55+入力データ!$C$56)*12+IF(入力データ!$C$13="持ち家",入力データ!$C$83+前提条件!$C$47,入力データ!$C$84+前提条件!$C$48))*(1+前提条件!$C$15)^(E$3-$B$3)) | F21: =IF(F$3="","",((IF(入力データ!$C$13="持ち家",IF(入力データ!$C$57="あり",0,IF(F5<=前提条件!$C$44,入力データ!$C$53,0)),入力データ!$C$53)+入力データ!$C$54+入力データ!$C$55+入力データ!$C$56)*12+IF(入力データ!$C$13="持ち家",入力データ!$C$83+前提条件!$C$47,入力データ!$C$84+前提条件!$C$48))*(1+前提条件!$C$15)^(F$3-$B$3)) | G21: =IF(G$3="","",((IF(入力データ!$C$13="持ち家",IF(入力データ!$C$57="あり",0,IF(G5<=前提条件!$C$44,入力データ!$C$53,0)),入力データ!$C$53)+入力データ!$C$54+入力データ!$C$55+入力データ!$C$56)*12+IF(入力データ!$C$13="持ち家",入力データ!$C$83+前提条件!$C$47,入力データ!$C$84+前提条件!$C$48))*(1+前提条件!$C$15)^(G$3-$B$3)) | H21: =IF(H$3="","",((IF(入力データ!$C$13="持ち家",IF(入力データ!$C$57="あり",0,IF(H5<=前提条件!$C$44,入力データ!$C$53,0)),入力データ!$C$53)+入力データ!$C$54+入力データ!$C$55+入力データ!$C$56)*12+IF(入力データ!$C$13="持ち家",入力データ!$C$83+前提条件!$C$47,入力データ!$C$84+前提条件!$C$48))*(1+前提条件!$C$15)^(H$3-$B$3)) | I21: =IF(I$3="","",((IF(入力データ!$C$13="持ち家",IF(入力データ!$C$57="あり",0,IF(I5<=前提条件!$C$44,入力データ!$C$53,0)),入力データ!$C$53)+入力データ!$C$54+入力データ!$C$55+入力データ!$C$56)*12+IF(入力データ!$C$13="持ち家",入力データ!$C$83+前提条件!$C$47,入力データ!$C$84+前提条件!$C$48))*(1+前提条件!$C$15)^(I$3-$B$3)) | ... CW21: =IF(CW$3="","",((IF(入力データ!$C$13="持ち家",IF(入力データ!$C$57="あり",0,IF(CW5<=前提条件!$C$44,入力データ!$C$53,0)),入力データ!$C$53)+入力データ!$C$54+入力データ!$C$55+入力データ!$C$56)*12+IF(入力データ!$C$13="持ち家",入力データ!$C$83+前提条件!$C$47,入力データ!$C$84+前提条件!$C$48))*(1+前提条件!$C$15)^(CW$3-$B$3))
A22: 終身系保険料 | B22: =IF(B$3="","",SUMPRODUCT(--ISNUMBER(SEARCH("終身",入力データ!$F$5:$F$20)),--(IFERROR(YEAR(入力データ!$J$5:$J$20),0)<=B$3),--(IFERROR(YEAR(入力データ!$K$5:$K$20),9999)>=B$3),入力データ!$M$5:$M$20)*12) | C22: =IF(C$3="","",SUMPRODUCT(--ISNUMBER(SEARCH("終身",入力データ!$F$5:$F$20)),--(IFERROR(YEAR(入力データ!$J$5:$J$20),0)<=C$3),--(IFERROR(YEAR(入力データ!$K$5:$K$20),9999)>=C$3),入力データ!$M$5:$M$20)*12) | D22: =IF(D$3="","",SUMPRODUCT(--ISNUMBER(SEARCH("終身",入力データ!$F$5:$F$20)),--(IFERROR(YEAR(入力データ!$J$5:$J$20),0)<=D$3),--(IFERROR(YEAR(入力データ!$K$5:$K$20),9999)>=D$3),入力データ!$M$5:$M$20)*12) | E22: =IF(E$3="","",SUMPRODUCT(--ISNUMBER(SEARCH("終身",入力データ!$F$5:$F$20)),--(IFERROR(YEAR(入力データ!$J$5:$J$20),0)<=E$3),--(IFERROR(YEAR(入力データ!$K$5:$K$20),9999)>=E$3),入力データ!$M$5:$M$20)*12) | F22: =IF(F$3="","",SUMPRODUCT(--ISNUMBER(SEARCH("終身",入力データ!$F$5:$F$20)),--(IFERROR(YEAR(入力データ!$J$5:$J$20),0)<=F$3),--(IFERROR(YEAR(入力データ!$K$5:$K$20),9999)>=F$3),入力データ!$M$5:$M$20)*12) | G22: =IF(G$3="","",SUMPRODUCT(--ISNUMBER(SEARCH("終身",入力データ!$F$5:$F$20)),--(IFERROR(YEAR(入力データ!$J$5:$J$20),0)<=G$3),--(IFERROR(YEAR(入力データ!$K$5:$K$20),9999)>=G$3),入力データ!$M$5:$M$20)*12) | H22: =IF(H$3="","",SUMPRODUCT(--ISNUMBER(SEARCH("終身",入力データ!$F$5:$F$20)),--(IFERROR(YEAR(入力データ!$J$5:$J$20),0)<=H$3),--(IFERROR(YEAR(入力データ!$K$5:$K$20),9999)>=H$3),入力データ!$M$5:$M$20)*12) | I22: =IF(I$3="","",SUMPRODUCT(--ISNUMBER(SEARCH("終身",入力データ!$F$5:$F$20)),--(IFERROR(YEAR(入力データ!$J$5:$J$20),0)<=I$3),--(IFERROR(YEAR(入力データ!$K$5:$K$20),9999)>=I$3),入力データ!$M$5:$M$20)*12) | ... CW22: =IF(CW$3="","",SUMPRODUCT(--ISNUMBER(SEARCH("終身",入力データ!$F$5:$F$20)),--(IFERROR(YEAR(入力データ!$J$5:$J$20),0)<=CW$3),--(IFERROR(YEAR(入力データ!$K$5:$K$20),9999)>=CW$3),入力データ!$M$5:$M$20)*12)
A23: 定期系保険料 | B23: =IF(B$3="","",SUMPRODUCT(--ISERROR(SEARCH("終身",入力データ!$F$5:$F$20)),--(IFERROR(YEAR(入力データ!$J$5:$J$20),0)<=B$3),--(IFERROR(YEAR(入力データ!$K$5:$K$20),9999)>=B$3),入力データ!$M$5:$M$20)*12) | C23: =IF(C$3="","",SUMPRODUCT(--ISERROR(SEARCH("終身",入力データ!$F$5:$F$20)),--(IFERROR(YEAR(入力データ!$J$5:$J$20),0)<=C$3),--(IFERROR(YEAR(入力データ!$K$5:$K$20),9999)>=C$3),入力データ!$M$5:$M$20)*12) | D23: =IF(D$3="","",SUMPRODUCT(--ISERROR(SEARCH("終身",入力データ!$F$5:$F$20)),--(IFERROR(YEAR(入力データ!$J$5:$J$20),0)<=D$3),--(IFERROR(YEAR(入力データ!$K$5:$K$20),9999)>=D$3),入力データ!$M$5:$M$20)*12) | E23: =IF(E$3="","",SUMPRODUCT(--ISERROR(SEARCH("終身",入力データ!$F$5:$F$20)),--(IFERROR(YEAR(入力データ!$J$5:$J$20),0)<=E$3),--(IFERROR(YEAR(入力データ!$K$5:$K$20),9999)>=E$3),入力データ!$M$5:$M$20)*12) | F23: =IF(F$3="","",SUMPRODUCT(--ISERROR(SEARCH("終身",入力データ!$F$5:$F$20)),--(IFERROR(YEAR(入力データ!$J$5:$J$20),0)<=F$3),--(IFERROR(YEAR(入力データ!$K$5:$K$20),9999)>=F$3),入力データ!$M$5:$M$20)*12) | G23: =IF(G$3="","",SUMPRODUCT(--ISERROR(SEARCH("終身",入力データ!$F$5:$F$20)),--(IFERROR(YEAR(入力データ!$J$5:$J$20),0)<=G$3),--(IFERROR(YEAR(入力データ!$K$5:$K$20),9999)>=G$3),入力データ!$M$5:$M$20)*12) | H23: =IF(H$3="","",SUMPRODUCT(--ISERROR(SEARCH("終身",入力データ!$F$5:$F$20)),--(IFERROR(YEAR(入力データ!$J$5:$J$20),0)<=H$3),--(IFERROR(YEAR(入力データ!$K$5:$K$20),9999)>=H$3),入力データ!$M$5:$M$20)*12) | I23: =IF(I$3="","",SUMPRODUCT(--ISERROR(SEARCH("終身",入力データ!$F$5:$F$20)),--(IFERROR(YEAR(入力データ!$J$5:$J$20),0)<=I$3),--(IFERROR(YEAR(入力データ!$K$5:$K$20),9999)>=I$3),入力データ!$M$5:$M$20)*12) | ... CW23: =IF(CW$3="","",SUMPRODUCT(--ISERROR(SEARCH("終身",入力データ!$F$5:$F$20)),--(IFERROR(YEAR(入力データ!$J$5:$J$20),0)<=CW$3),--(IFERROR(YEAR(入力データ!$K$5:$K$20),9999)>=CW$3),入力データ!$M$5:$M$20)*12)
A24: 教育費 | B24: =IF(B$3="","",IF(入力データ!$C$17<=0,0,IF(B$3="","",((SUM(入力データ!$C$58:$C$61)*12)+IF(B6="",0,IF(B6<=5,IF(入力データ!$G$25="私立",前提条件!$C$22,前提条件!$C$21),IF(B6<=11,IF(入力データ!$H$25="私立",前提条件!$C$24,前提条件!$C$23),IF(B6<=14,IF(入力データ!$I$25="私立",前提条件!$C$26,前提条件!$C$25),IF(B6<=17,IF(入力データ!$J$25="私立",前提条件!$C$28,前提条件!$C$27),IF(B6<=21,IF(入力データ!$K$25="国公立",前提条件!$C$29,IF(入力データ!$K$25="私立理系",前提条件!$C$31,前提条件!$C$30))+IF(入力データ!$L$25="下宿",前提条件!$C$32,0)+IF(B6=18,前提条件!$C$33,0),0))))))+IF(B7="",0,IF(B7<=5,IF(入力データ!$G$26="私立",前提条件!$C$22,前提条件!$C$21),IF(B7<=11,IF(入力データ!$H$26="私立",前提条件!$C$24,前提条件!$C$23),IF(B7<=14,IF(入力データ!$I$26="私立",前提条件!$C$26,前提条件!$C$25),IF(B7<=17,IF(入力データ!$J$26="私立",前提条件!$C$28,前提条件!$C$27),IF(B7<=21,IF(入力データ!$K$26="国公立",前提条件!$C$29,IF(入力データ!$K$26="私立理系",前提条件!$C$31,前提条件!$C$30))+IF(入力データ!$L$26="下宿",前提条件!$C$32,0)+IF(B7=18,前提条件!$C$33,0),0))))))+IF(B8="",0,IF(B8<=5,IF(入力データ!$G$27="私立",前提条件!$C$22,前提条件!$C$21),IF(B8<=11,IF(入力データ!$H$27="私立",前提条件!$C$24,前提条件!$C$23),IF(B8<=14,IF(入力データ!$I$27="私立",前提条件!$C$26,前提条件!$C$25),IF(B8<=17,IF(入力データ!$J$27="私立",前提条件!$C$28,前提条件!$C$27),IF(B8<=21,IF(入力データ!$K$27="国公立",前提条件!$C$29,IF(入力データ!$K$27="私立理系",前提条件!$C$31,前提条件!$C$30))+IF(入力データ!$L$27="下宿",前提条件!$C$32,0)+IF(B8=18,前提条件!$C$33,0),0)))))))*(1+前提条件!$C$13)^(B$3-$B$3)))) | C24: =IF(C$3="","",IF(入力データ!$C$17<=0,0,IF(C$3="","",((SUM(入力データ!$C$58:$C$61)*12)+IF(C6="",0,IF(C6<=5,IF(入力データ!$G$25="私立",前提条件!$C$22,前提条件!$C$21),IF(C6<=11,IF(入力データ!$H$25="私立",前提条件!$C$24,前提条件!$C$23),IF(C6<=14,IF(入力データ!$I$25="私立",前提条件!$C$26,前提条件!$C$25),IF(C6<=17,IF(入力データ!$J$25="私立",前提条件!$C$28,前提条件!$C$27),IF(C6<=21,IF(入力データ!$K$25="国公立",前提条件!$C$29,IF(入力データ!$K$25="私立理系",前提条件!$C$31,前提条件!$C$30))+IF(入力データ!$L$25="下宿",前提条件!$C$32,0)+IF(C6=18,前提条件!$C$33,0),0))))))+IF(C7="",0,IF(C7<=5,IF(入力データ!$G$26="私立",前提条件!$C$22,前提条件!$C$21),IF(C7<=11,IF(入力データ!$H$26="私立",前提条件!$C$24,前提条件!$C$23),IF(C7<=14,IF(入力データ!$I$26="私立",前提条件!$C$26,前提条件!$C$25),IF(C7<=17,IF(入力データ!$J$26="私立",前提条件!$C$28,前提条件!$C$27),IF(C7<=21,IF(入力データ!$K$26="国公立",前提条件!$C$29,IF(入力データ!$K$26="私立理系",前提条件!$C$31,前提条件!$C$30))+IF(入力データ!$L$26="下宿",前提条件!$C$32,0)+IF(C7=18,前提条件!$C$33,0),0))))))+IF(C8="",0,IF(C8<=5,IF(入力データ!$G$27="私立",前提条件!$C$22,前提条件!$C$21),IF(C8<=11,IF(入力データ!$H$27="私立",前提条件!$C$24,前提条件!$C$23),IF(C8<=14,IF(入力データ!$I$27="私立",前提条件!$C$26,前提条件!$C$25),IF(C8<=17,IF(入力データ!$J$27="私立",前提条件!$C$28,前提条件!$C$27),IF(C8<=21,IF(入力データ!$K$27="国公立",前提条件!$C$29,IF(入力データ!$K$27="私立理系",前提条件!$C$31,前提条件!$C$30))+IF(入力データ!$L$27="下宿",前提条件!$C$32,0)+IF(C8=18,前提条件!$C$33,0),0)))))))*(1+前提条件!$C$13)^(C$3-$B$3)))) | D24: =IF(D$3="","",IF(入力データ!$C$17<=0,0,IF(D$3="","",((SUM(入力データ!$C$58:$C$61)*12)+IF(D6="",0,IF(D6<=5,IF(入力データ!$G$25="私立",前提条件!$C$22,前提条件!$C$21),IF(D6<=11,IF(入力データ!$H$25="私立",前提条件!$C$24,前提条件!$C$23),IF(D6<=14,IF(入力データ!$I$25="私立",前提条件!$C$26,前提条件!$C$25),IF(D6<=17,IF(入力データ!$J$25="私立",前提条件!$C$28,前提条件!$C$27),IF(D6<=21,IF(入力データ!$K$25="国公立",前提条件!$C$29,IF(入力データ!$K$25="私立理系",前提条件!$C$31,前提条件!$C$30))+IF(入力データ!$L$25="下宿",前提条件!$C$32,0)+IF(D6=18,前提条件!$C$33,0),0))))))+IF(D7="",0,IF(D7<=5,IF(入力データ!$G$26="私立",前提条件!$C$22,前提条件!$C$21),IF(D7<=11,IF(入力データ!$H$26="私立",前提条件!$C$24,前提条件!$C$23),IF(D7<=14,IF(入力データ!$I$26="私立",前提条件!$C$26,前提条件!$C$25),IF(D7<=17,IF(入力データ!$J$26="私立",前提条件!$C$28,前提条件!$C$27),IF(D7<=21,IF(入力データ!$K$26="国公立",前提条件!$C$29,IF(入力データ!$K$26="私立理系",前提条件!$C$31,前提条件!$C$30))+IF(入力データ!$L$26="下宿",前提条件!$C$32,0)+IF(D7=18,前提条件!$C$33,0),0))))))+IF(D8="",0,IF(D8<=5,IF(入力データ!$G$27="私立",前提条件!$C$22,前提条件!$C$21),IF(D8<=11,IF(入力データ!$H$27="私立",前提条件!$C$24,前提条件!$C$23),IF(D8<=14,IF(入力データ!$I$27="私立",前提条件!$C$26,前提条件!$C$25),IF(D8<=17,IF(入力データ!$J$27="私立",前提条件!$C$28,前提条件!$C$27),IF(D8<=21,IF(入力データ!$K$27="国公立",前提条件!$C$29,IF(入力データ!$K$27="私立理系",前提条件!$C$31,前提条件!$C$30))+IF(入力データ!$L$27="下宿",前提条件!$C$32,0)+IF(D8=18,前提条件!$C$33,0),0)))))))*(1+前提条件!$C$13)^(D$3-$B$3)))) | E24: =IF(E$3="","",IF(入力データ!$C$17<=0,0,IF(E$3="","",((SUM(入力データ!$C$58:$C$61)*12)+IF(E6="",0,IF(E6<=5,IF(入力データ!$G$25="私立",前提条件!$C$22,前提条件!$C$21),IF(E6<=11,IF(入力データ!$H$25="私立",前提条件!$C$24,前提条件!$C$23),IF(E6<=14,IF(入力データ!$I$25="私立",前提条件!$C$26,前提条件!$C$25),IF(E6<=17,IF(入力データ!$J$25="私立",前提条件!$C$28,前提条件!$C$27),IF(E6<=21,IF(入力データ!$K$25="国公立",前提条件!$C$29,IF(入力データ!$K$25="私立理系",前提条件!$C$31,前提条件!$C$30))+IF(入力データ!$L$25="下宿",前提条件!$C$32,0)+IF(E6=18,前提条件!$C$33,0),0))))))+IF(E7="",0,IF(E7<=5,IF(入力データ!$G$26="私立",前提条件!$C$22,前提条件!$C$21),IF(E7<=11,IF(入力データ!$H$26="私立",前提条件!$C$24,前提条件!$C$23),IF(E7<=14,IF(入力データ!$I$26="私立",前提条件!$C$26,前提条件!$C$25),IF(E7<=17,IF(入力データ!$J$26="私立",前提条件!$C$28,前提条件!$C$27),IF(E7<=21,IF(入力データ!$K$26="国公立",前提条件!$C$29,IF(入力データ!$K$26="私立理系",前提条件!$C$31,前提条件!$C$30))+IF(入力データ!$L$26="下宿",前提条件!$C$32,0)+IF(E7=18,前提条件!$C$33,0),0))))))+IF(E8="",0,IF(E8<=5,IF(入力データ!$G$27="私立",前提条件!$C$22,前提条件!$C$21),IF(E8<=11,IF(入力データ!$H$27="私立",前提条件!$C$24,前提条件!$C$23),IF(E8<=14,IF(入力データ!$I$27="私立",前提条件!$C$26,前提条件!$C$25),IF(E8<=17,IF(入力データ!$J$27="私立",前提条件!$C$28,前提条件!$C$27),IF(E8<=21,IF(入力データ!$K$27="国公立",前提条件!$C$29,IF(入力データ!$K$27="私立理系",前提条件!$C$31,前提条件!$C$30))+IF(入力データ!$L$27="下宿",前提条件!$C$32,0)+IF(E8=18,前提条件!$C$33,0),0)))))))*(1+前提条件!$C$13)^(E$3-$B$3)))) | F24: =IF(F$3="","",IF(入力データ!$C$17<=0,0,IF(F$3="","",((SUM(入力データ!$C$58:$C$61)*12)+IF(F6="",0,IF(F6<=5,IF(入力データ!$G$25="私立",前提条件!$C$22,前提条件!$C$21),IF(F6<=11,IF(入力データ!$H$25="私立",前提条件!$C$24,前提条件!$C$23),IF(F6<=14,IF(入力データ!$I$25="私立",前提条件!$C$26,前提条件!$C$25),IF(F6<=17,IF(入力データ!$J$25="私立",前提条件!$C$28,前提条件!$C$27),IF(F6<=21,IF(入力データ!$K$25="国公立",前提条件!$C$29,IF(入力データ!$K$25="私立理系",前提条件!$C$31,前提条件!$C$30))+IF(入力データ!$L$25="下宿",前提条件!$C$32,0)+IF(F6=18,前提条件!$C$33,0),0))))))+IF(F7="",0,IF(F7<=5,IF(入力データ!$G$26="私立",前提条件!$C$22,前提条件!$C$21),IF(F7<=11,IF(入力データ!$H$26="私立",前提条件!$C$24,前提条件!$C$23),IF(F7<=14,IF(入力データ!$I$26="私立",前提条件!$C$26,前提条件!$C$25),IF(F7<=17,IF(入力データ!$J$26="私立",前提条件!$C$28,前提条件!$C$27),IF(F7<=21,IF(入力データ!$K$26="国公立",前提条件!$C$29,IF(入力データ!$K$26="私立理系",前提条件!$C$31,前提条件!$C$30))+IF(入力データ!$L$26="下宿",前提条件!$C$32,0)+IF(F7=18,前提条件!$C$33,0),0))))))+IF(F8="",0,IF(F8<=5,IF(入力データ!$G$27="私立",前提条件!$C$22,前提条件!$C$21),IF(F8<=11,IF(入力データ!$H$27="私立",前提条件!$C$24,前提条件!$C$23),IF(F8<=14,IF(入力データ!$I$27="私立",前提条件!$C$26,前提条件!$C$25),IF(F8<=17,IF(入力データ!$J$27="私立",前提条件!$C$28,前提条件!$C$27),IF(F8<=21,IF(入力データ!$K$27="国公立",前提条件!$C$29,IF(入力データ!$K$27="私立理系",前提条件!$C$31,前提条件!$C$30))+IF(入力データ!$L$27="下宿",前提条件!$C$32,0)+IF(F8=18,前提条件!$C$33,0),0)))))))*(1+前提条件!$C$13)^(F$3-$B$3)))) | G24: =IF(G$3="","",IF(入力データ!$C$17<=0,0,IF(G$3="","",((SUM(入力データ!$C$58:$C$61)*12)+IF(G6="",0,IF(G6<=5,IF(入力データ!$G$25="私立",前提条件!$C$22,前提条件!$C$21),IF(G6<=11,IF(入力データ!$H$25="私立",前提条件!$C$24,前提条件!$C$23),IF(G6<=14,IF(入力データ!$I$25="私立",前提条件!$C$26,前提条件!$C$25),IF(G6<=17,IF(入力データ!$J$25="私立",前提条件!$C$28,前提条件!$C$27),IF(G6<=21,IF(入力データ!$K$25="国公立",前提条件!$C$29,IF(入力データ!$K$25="私立理系",前提条件!$C$31,前提条件!$C$30))+IF(入力データ!$L$25="下宿",前提条件!$C$32,0)+IF(G6=18,前提条件!$C$33,0),0))))))+IF(G7="",0,IF(G7<=5,IF(入力データ!$G$26="私立",前提条件!$C$22,前提条件!$C$21),IF(G7<=11,IF(入力データ!$H$26="私立",前提条件!$C$24,前提条件!$C$23),IF(G7<=14,IF(入力データ!$I$26="私立",前提条件!$C$26,前提条件!$C$25),IF(G7<=17,IF(入力データ!$J$26="私立",前提条件!$C$28,前提条件!$C$27),IF(G7<=21,IF(入力データ!$K$26="国公立",前提条件!$C$29,IF(入力データ!$K$26="私立理系",前提条件!$C$31,前提条件!$C$30))+IF(入力データ!$L$26="下宿",前提条件!$C$32,0)+IF(G7=18,前提条件!$C$33,0),0))))))+IF(G8="",0,IF(G8<=5,IF(入力データ!$G$27="私立",前提条件!$C$22,前提条件!$C$21),IF(G8<=11,IF(入力データ!$H$27="私立",前提条件!$C$24,前提条件!$C$23),IF(G8<=14,IF(入力データ!$I$27="私立",前提条件!$C$26,前提条件!$C$25),IF(G8<=17,IF(入力データ!$J$27="私立",前提条件!$C$28,前提条件!$C$27),IF(G8<=21,IF(入力データ!$K$27="国公立",前提条件!$C$29,IF(入力データ!$K$27="私立理系",前提条件!$C$31,前提条件!$C$30))+IF(入力データ!$L$27="下宿",前提条件!$C$32,0)+IF(G8=18,前提条件!$C$33,0),0)))))))*(1+前提条件!$C$13)^(G$3-$B$3)))) | H24: =IF(H$3="","",IF(入力データ!$C$17<=0,0,IF(H$3="","",((SUM(入力データ!$C$58:$C$61)*12)+IF(H6="",0,IF(H6<=5,IF(入力データ!$G$25="私立",前提条件!$C$22,前提条件!$C$21),IF(H6<=11,IF(入力データ!$H$25="私立",前提条件!$C$24,前提条件!$C$23),IF(H6<=14,IF(入力データ!$I$25="私立",前提条件!$C$26,前提条件!$C$25),IF(H6<=17,IF(入力データ!$J$25="私立",前提条件!$C$28,前提条件!$C$27),IF(H6<=21,IF(入力データ!$K$25="国公立",前提条件!$C$29,IF(入力データ!$K$25="私立理系",前提条件!$C$31,前提条件!$C$30))+IF(入力データ!$L$25="下宿",前提条件!$C$32,0)+IF(H6=18,前提条件!$C$33,0),0))))))+IF(H7="",0,IF(H7<=5,IF(入力データ!$G$26="私立",前提条件!$C$22,前提条件!$C$21),IF(H7<=11,IF(入力データ!$H$26="私立",前提条件!$C$24,前提条件!$C$23),IF(H7<=14,IF(入力データ!$I$26="私立",前提条件!$C$26,前提条件!$C$25),IF(H7<=17,IF(入力データ!$J$26="私立",前提条件!$C$28,前提条件!$C$27),IF(H7<=21,IF(入力データ!$K$26="国公立",前提条件!$C$29,IF(入力データ!$K$26="私立理系",前提条件!$C$31,前提条件!$C$30))+IF(入力データ!$L$26="下宿",前提条件!$C$32,0)+IF(H7=18,前提条件!$C$33,0),0))))))+IF(H8="",0,IF(H8<=5,IF(入力データ!$G$27="私立",前提条件!$C$22,前提条件!$C$21),IF(H8<=11,IF(入力データ!$H$27="私立",前提条件!$C$24,前提条件!$C$23),IF(H8<=14,IF(入力データ!$I$27="私立",前提条件!$C$26,前提条件!$C$25),IF(H8<=17,IF(入力データ!$J$27="私立",前提条件!$C$28,前提条件!$C$27),IF(H8<=21,IF(入力データ!$K$27="国公立",前提条件!$C$29,IF(入力データ!$K$27="私立理系",前提条件!$C$31,前提条件!$C$30))+IF(入力データ!$L$27="下宿",前提条件!$C$32,0)+IF(H8=18,前提条件!$C$33,0),0)))))))*(1+前提条件!$C$13)^(H$3-$B$3)))) | I24: =IF(I$3="","",IF(入力データ!$C$17<=0,0,IF(I$3="","",((SUM(入力データ!$C$58:$C$61)*12)+IF(I6="",0,IF(I6<=5,IF(入力データ!$G$25="私立",前提条件!$C$22,前提条件!$C$21),IF(I6<=11,IF(入力データ!$H$25="私立",前提条件!$C$24,前提条件!$C$23),IF(I6<=14,IF(入力データ!$I$25="私立",前提条件!$C$26,前提条件!$C$25),IF(I6<=17,IF(入力データ!$J$25="私立",前提条件!$C$28,前提条件!$C$27),IF(I6<=21,IF(入力データ!$K$25="国公立",前提条件!$C$29,IF(入力データ!$K$25="私立理系",前提条件!$C$31,前提条件!$C$30))+IF(入力データ!$L$25="下宿",前提条件!$C$32,0)+IF(I6=18,前提条件!$C$33,0),0))))))+IF(I7="",0,IF(I7<=5,IF(入力データ!$G$26="私立",前提条件!$C$22,前提条件!$C$21),IF(I7<=11,IF(入力データ!$H$26="私立",前提条件!$C$24,前提条件!$C$23),IF(I7<=14,IF(入力データ!$I$26="私立",前提条件!$C$26,前提条件!$C$25),IF(I7<=17,IF(入力データ!$J$26="私立",前提条件!$C$28,前提条件!$C$27),IF(I7<=21,IF(入力データ!$K$26="国公立",前提条件!$C$29,IF(入力データ!$K$26="私立理系",前提条件!$C$31,前提条件!$C$30))+IF(入力データ!$L$26="下宿",前提条件!$C$32,0)+IF(I7=18,前提条件!$C$33,0),0))))))+IF(I8="",0,IF(I8<=5,IF(入力データ!$G$27="私立",前提条件!$C$22,前提条件!$C$21),IF(I8<=11,IF(入力データ!$H$27="私立",前提条件!$C$24,前提条件!$C$23),IF(I8<=14,IF(入力データ!$I$27="私立",前提条件!$C$26,前提条件!$C$25),IF(I8<=17,IF(入力データ!$J$27="私立",前提条件!$C$28,前提条件!$C$27),IF(I8<=21,IF(入力データ!$K$27="国公立",前提条件!$C$29,IF(入力データ!$K$27="私立理系",前提条件!$C$31,前提条件!$C$30))+IF(入力データ!$L$27="下宿",前提条件!$C$32,0)+IF(I8=18,前提条件!$C$33,0),0)))))))*(1+前提条件!$C$13)^(I$3-$B$3)))) | ... CW24: =IF(CW$3="","",IF(入力データ!$C$17<=0,0,IF(CW$3="","",((SUM(入力データ!$C$58:$C$61)*12)+IF(CW6="",0,IF(CW6<=5,IF(入力データ!$G$25="私立",前提条件!$C$22,前提条件!$C$21),IF(CW6<=11,IF(入力データ!$H$25="私立",前提条件!$C$24,前提条件!$C$23),IF(CW6<=14,IF(入力データ!$I$25="私立",前提条件!$C$26,前提条件!$C$25),IF(CW6<=17,IF(入力データ!$J$25="私立",前提条件!$C$28,前提条件!$C$27),IF(CW6<=21,IF(入力データ!$K$25="国公立",前提条件!$C$29,IF(入力データ!$K$25="私立理系",前提条件!$C$31,前提条件!$C$30))+IF(入力データ!$L$25="下宿",前提条件!$C$32,0)+IF(CW6=18,前提条件!$C$33,0),0))))))+IF(CW7="",0,IF(CW7<=5,IF(入力データ!$G$26="私立",前提条件!$C$22,前提条件!$C$21),IF(CW7<=11,IF(入力データ!$H$26="私立",前提条件!$C$24,前提条件!$C$23),IF(CW7<=14,IF(入力データ!$I$26="私立",前提条件!$C$26,前提条件!$C$25),IF(CW7<=17,IF(入力データ!$J$26="私立",前提条件!$C$28,前提条件!$C$27),IF(CW7<=21,IF(入力データ!$K$26="国公立",前提条件!$C$29,IF(入力データ!$K$26="私立理系",前提条件!$C$31,前提条件!$C$30))+IF(入力データ!$L$26="下宿",前提条件!$C$32,0)+IF(CW7=18,前提条件!$C$33,0),0))))))+IF(CW8="",0,IF(CW8<=5,IF(入力データ!$G$27="私立",前提条件!$C$22,前提条件!$C$21),IF(CW8<=11,IF(入力データ!$H$27="私立",前提条件!$C$24,前提条件!$C$23),IF(CW8<=14,IF(入力データ!$I$27="私立",前提条件!$C$26,前提条件!$C$25),IF(CW8<=17,IF(入力データ!$J$27="私立",前提条件!$C$28,前提条件!$C$27),IF(CW8<=21,IF(入力データ!$K$27="国公立",前提条件!$C$29,IF(入力データ!$K$27="私立理系",前提条件!$C$31,前提条件!$C$30))+IF(入力データ!$L$27="下宿",前提条件!$C$32,0)+IF(CW8=18,前提条件!$C$33,0),0)))))))*(1+前提条件!$C$13)^(CW$3-$B$3))))
A25: 車関連費 | B25: =IF(B$3="","",N(入力データ!$C$69)*12*(1+前提条件!$C$12)^(B$3-$B$3)) | C25: =IF(C$3="","",N(入力データ!$C$69)*12*(1+前提条件!$C$12)^(C$3-$B$3)) | D25: =IF(D$3="","",N(入力データ!$C$69)*12*(1+前提条件!$C$12)^(D$3-$B$3)) | E25: =IF(E$3="","",N(入力データ!$C$69)*12*(1+前提条件!$C$12)^(E$3-$B$3)) | F25: =IF(F$3="","",N(入力データ!$C$69)*12*(1+前提条件!$C$12)^(F$3-$B$3)) | G25: =IF(G$3="","",N(入力データ!$C$69)*12*(1+前提条件!$C$12)^(G$3-$B$3)) | H25: =IF(H$3="","",N(入力データ!$C$69)*12*(1+前提条件!$C$12)^(H$3-$B$3)) | I25: =IF(I$3="","",N(入力データ!$C$69)*12*(1+前提条件!$C$12)^(I$3-$B$3)) | ... CW25: =IF(CW$3="","",N(入力データ!$C$69)*12*(1+前提条件!$C$12)^(CW$3-$B$3))
A26: その他支出 | B26: =IF(B$3="","",SUM(入力データ!$C$71:$C$74)*12*(1+前提条件!$C$12)^(B$3-$B$3)) | C26: =IF(C$3="","",SUM(入力データ!$C$71:$C$74)*12*(1+前提条件!$C$12)^(C$3-$B$3)) | D26: =IF(D$3="","",SUM(入力データ!$C$71:$C$74)*12*(1+前提条件!$C$12)^(D$3-$B$3)) | E26: =IF(E$3="","",SUM(入力データ!$C$71:$C$74)*12*(1+前提条件!$C$12)^(E$3-$B$3)) | F26: =IF(F$3="","",SUM(入力データ!$C$71:$C$74)*12*(1+前提条件!$C$12)^(F$3-$B$3)) | G26: =IF(G$3="","",SUM(入力データ!$C$71:$C$74)*12*(1+前提条件!$C$12)^(G$3-$B$3)) | H26: =IF(H$3="","",SUM(入力データ!$C$71:$C$74)*12*(1+前提条件!$C$12)^(H$3-$B$3)) | I26: =IF(I$3="","",SUM(入力データ!$C$71:$C$74)*12*(1+前提条件!$C$12)^(I$3-$B$3)) | ... CW26: =IF(CW$3="","",SUM(入力データ!$C$71:$C$74)*12*(1+前提条件!$C$12)^(CW$3-$B$3))
A27: 一時支出 | B27: =IF(B$3="","",SUM(入力データ!$C$78:$C$82)) | C27: =IF(C$3="","",SUM(入力データ!$C$78:$C$82)) | D27: =IF(D$3="","",SUM(入力データ!$C$78:$C$82)) | E27: =IF(E$3="","",SUM(入力データ!$C$78:$C$82)) | F27: =IF(F$3="","",SUM(入力データ!$C$78:$C$82)) | G27: =IF(G$3="","",SUM(入力データ!$C$78:$C$82)) | H27: =IF(H$3="","",SUM(入力データ!$C$78:$C$82)) | I27: =IF(I$3="","",SUM(入力データ!$C$78:$C$82)) | ... CW27: =IF(CW$3="","",SUM(入力データ!$C$78:$C$82))
A28: 支出合計 | B28: =IF(B$3="","",SUM(B20:B27)) | C28: =IF(C$3="","",SUM(C20:C27)) | D28: =IF(D$3="","",SUM(D20:D27)) | E28: =IF(E$3="","",SUM(E20:E27)) | F28: =IF(F$3="","",SUM(F20:F27)) | G28: =IF(G$3="","",SUM(G20:G27)) | H28: =IF(H$3="","",SUM(H20:H27)) | I28: =IF(I$3="","",SUM(I20:I27)) | ... CW28: =IF(CW$3="","",SUM(CW20:CW27))
A29: 収支・資産
A30: 年間収支 | B30: =IF(B$3="","",B18-B28) | C30: =IF(C$3="","",C18-C28) | D30: =IF(D$3="","",D18-D28) | E30: =IF(E$3="","",E18-E28) | F30: =IF(F$3="","",F18-F28) | G30: =IF(G$3="","",G18-G28) | H30: =IF(H$3="","",H18-H28) | I30: =IF(I$3="","",I18-I28) | ... CW30: =IF(CW$3="","",CW18-CW28)
A31: 預貯金残高 | B31: =IF(B$3="","",B38) | C31: =IF(C$3="","",C38) | D31: =IF(D$3="","",D38) | E31: =IF(E$3="","",E38) | F31: =IF(F$3="","",F38) | G31: =IF(G$3="","",G38) | H31: =IF(H$3="","",H38) | I31: =IF(I$3="","",I38) | ... CW31: =IF(CW$3="","",CW38)
A32: 投資資産残高 | B32: =IF(B$3="","",((SUM(入力データ!$C$90:$C$92,入力データ!$C$94)*(1+前提条件!$C$60))+B36-B39)) | C32: =IF(C$3="","",((SUM(入力データ!$C$90:$C$92,入力データ!$C$94)*(1+前提条件!$C$60))+C36-C39)) | D32: =IF(D$3="","",((SUM(入力データ!$C$90:$C$92,入力データ!$C$94)*(1+前提条件!$C$60))+D36-D39)) | E32: =IF(E$3="","",((SUM(入力データ!$C$90:$C$92,入力データ!$C$94)*(1+前提条件!$C$60))+E36-E39)) | F32: =IF(F$3="","",((SUM(入力データ!$C$90:$C$92,入力データ!$C$94)*(1+前提条件!$C$60))+F36-F39)) | G32: =IF(G$3="","",((SUM(入力データ!$C$90:$C$92,入力データ!$C$94)*(1+前提条件!$C$60))+G36-G39)) | H32: =IF(H$3="","",((SUM(入力データ!$C$90:$C$92,入力データ!$C$94)*(1+前提条件!$C$60))+H36-H39)) | I32: =IF(I$3="","",((SUM(入力データ!$C$90:$C$92,入力データ!$C$94)*(1+前提条件!$C$60))+I36-I39)) | ... CW32: =IF(CW$3="","",((SUM(入力データ!$C$90:$C$92,入力データ!$C$94)*(1+前提条件!$C$60))+CW36-CW39))
A33: 解約返戻金残高 | B33: =IF(B$3="","",((入力データ!$C$93*(1+前提条件!$C$61))+B37-B40)) | C33: =IF(C$3="","",((入力データ!$C$93*(1+前提条件!$C$61))+C37-C40)) | D33: =IF(D$3="","",((入力データ!$C$93*(1+前提条件!$C$61))+D37-D40)) | E33: =IF(E$3="","",((入力データ!$C$93*(1+前提条件!$C$61))+E37-E40)) | F33: =IF(F$3="","",((入力データ!$C$93*(1+前提条件!$C$61))+F37-F40)) | G33: =IF(G$3="","",((入力データ!$C$93*(1+前提条件!$C$61))+G37-G40)) | H33: =IF(H$3="","",((入力データ!$C$93*(1+前提条件!$C$61))+H37-H40)) | I33: =IF(I$3="","",((入力データ!$C$93*(1+前提条件!$C$61))+I37-I40)) | ... CW33: =IF(CW$3="","",((入力データ!$C$93*(1+前提条件!$C$61))+CW37-CW40))
A34: 住宅ローン残高 | B34: =IF(B$3="","",IF(入力データ!$C$57="あり",0,MAX(入力データ!$C$95-B41,0))) | C34: =IF(C$3="","",IF(入力データ!$C$57="あり",0,MAX(B34-C41,0))) | D34: =IF(D$3="","",IF(入力データ!$C$57="あり",0,MAX(C34-D41,0))) | E34: =IF(E$3="","",IF(入力データ!$C$57="あり",0,MAX(D34-E41,0))) | F34: =IF(F$3="","",IF(入力データ!$C$57="あり",0,MAX(E34-F41,0))) | G34: =IF(G$3="","",IF(入力データ!$C$57="あり",0,MAX(F34-G41,0))) | H34: =IF(H$3="","",IF(入力データ!$C$57="あり",0,MAX(G34-H41,0))) | I34: =IF(I$3="","",IF(入力データ!$C$57="あり",0,MAX(H34-I41,0))) | J34: =IF(J$3="","",IF(入力データ!$C$57="あり",0,MAX(I34-J41,0))) | ... CW34: =IF(CW$3="","",IF(入力データ!$C$57="あり",0,MAX(CV34-CW41,0)))
A35: 保有資産合計（ローン除く） | B35: =IF(B$3="","",B31+B32+B33) | C35: =IF(C$3="","",C31+C32+C33) | D35: =IF(D$3="","",D31+D32+D33) | E35: =IF(E$3="","",E31+E32+E33) | F35: =IF(F$3="","",F31+F32+F33) | G35: =IF(G$3="","",G31+G32+G33) | H35: =IF(H$3="","",H31+H32+H33) | I35: =IF(I$3="","",I31+I32+I33) | ... CW35: =IF(CW$3="","",CW31+CW32+CW33)
A36: 投資積立年額(補助) | B36: =IF(B$3="","",SUM(入力データ!$C$101:$C$103,入力データ!$C$105)*12) | C36: =IF(C$3="","",SUM(入力データ!$C$101:$C$103,入力データ!$C$105)*12) | D36: =IF(D$3="","",SUM(入力データ!$C$101:$C$103,入力データ!$C$105)*12) | E36: =IF(E$3="","",SUM(入力データ!$C$101:$C$103,入力データ!$C$105)*12) | F36: =IF(F$3="","",SUM(入力データ!$C$101:$C$103,入力データ!$C$105)*12) | G36: =IF(G$3="","",SUM(入力データ!$C$101:$C$103,入力データ!$C$105)*12) | H36: =IF(H$3="","",SUM(入力データ!$C$101:$C$103,入力データ!$C$105)*12) | I36: =IF(I$3="","",SUM(入力データ!$C$101:$C$103,入力データ!$C$105)*12) | ... CW36: =IF(CW$3="","",SUM(入力データ!$C$101:$C$103,入力データ!$C$105)*12)
A37: 返戻金積立年額(補助) | B37: =IF(B$3="","",入力データ!$C$104*12) | C37: =IF(C$3="","",入力データ!$C$104*12) | D37: =IF(D$3="","",入力データ!$C$104*12) | E37: =IF(E$3="","",入力データ!$C$104*12) | F37: =IF(F$3="","",入力データ!$C$104*12) | G37: =IF(G$3="","",入力データ!$C$104*12) | H37: =IF(H$3="","",入力データ!$C$104*12) | I37: =IF(I$3="","",入力データ!$C$104*12) | ... CW37: =IF(CW$3="","",入力データ!$C$104*12)
A38: 預貯金前年差引前(補助) | B38: =IF(B$3="","",SUM(入力データ!$C$88:$C$89)+B30-B36-B37) | C38: =IF(C$3="","",B31+C30-C36-C37) | D38: =IF(D$3="","",C31+D30-D36-D37) | E38: =IF(E$3="","",D31+E30-E36-E37) | F38: =IF(F$3="","",E31+F30-F36-F37) | G38: =IF(G$3="","",F31+G30-G36-G37) | H38: =IF(H$3="","",G31+H30-H36-H37) | I38: =IF(I$3="","",H31+I30-I36-I37) | J38: =IF(J$3="","",I31+J30-J36-J37) | ... CW38: =IF(CW$3="","",CV31+CW30-CW36-CW37)
A39: 投資取り崩し額(補助) | B39: =IF(B$3="","",MAX(0,-B38)) | C39: =IF(C$3="","",MAX(0,-C38)) | D39: =IF(D$3="","",MAX(0,-D38)) | E39: =IF(E$3="","",MAX(0,-E38)) | F39: =IF(F$3="","",MAX(0,-F38)) | G39: =IF(G$3="","",MAX(0,-G38)) | H39: =IF(H$3="","",MAX(0,-H38)) | I39: =IF(I$3="","",MAX(0,-I38)) | ... CW39: =IF(CW$3="","",MAX(0,-CW38))
A40: 返戻金取り崩し額(補助) | B40: =IF(B$3="","",MAX(0,B39-((SUM(入力データ!$C$90:$C$92,入力データ!$C$94)*(1+前提条件!$C$60))+B36))) | C40: =IF(C$3="","",MAX(0,C39-((B32*(1+前提条件!$C$60))+C36))) | D40: =IF(D$3="","",MAX(0,D39-((C32*(1+前提条件!$C$60))+D36))) | E40: =IF(E$3="","",MAX(0,E39-((D32*(1+前提条件!$C$60))+E36))) | F40: =IF(F$3="","",MAX(0,F39-((E32*(1+前提条件!$C$60))+F36))) | G40: =IF(G$3="","",MAX(0,G39-((F32*(1+前提条件!$C$60))+G36))) | H40: =IF(H$3="","",MAX(0,H39-((G32*(1+前提条件!$C$60))+H36))) | I40: =IF(I$3="","",MAX(0,I39-((H32*(1+前提条件!$C$60))+I36))) | J40: =IF(J$3="","",MAX(0,J39-((I32*(1+前提条件!$C$60))+J36))) | ... CW40: =IF(CW$3="","",MAX(0,CW39-((CV32*(1+前提条件!$C$60))+CW36)))
A41: 年間住宅ローン元本返済(補助) | B41: =IF(B$3="","",IF(OR(入力データ!$C$57="あり",NOT(AND(B5<>"",B5<=前提条件!$C$44,入力データ!$C$95>0))),0,入力データ!$C$95/MAX(1,前提条件!$C$44-B5+1))) | C41: =IF(C$3="","",IF(OR(入力データ!$C$57="あり",C5>前提条件!$C$44),0,$B$41)) | D41: =IF(D$3="","",IF(OR(入力データ!$C$57="あり",D5>前提条件!$C$44),0,$B$41)) | E41: =IF(E$3="","",IF(OR(入力データ!$C$57="あり",E5>前提条件!$C$44),0,$B$41)) | F41: =IF(F$3="","",IF(OR(入力データ!$C$57="あり",F5>前提条件!$C$44),0,$B$41)) | G41: =IF(G$3="","",IF(OR(入力データ!$C$57="あり",G5>前提条件!$C$44),0,$B$41)) | H41: =IF(H$3="","",IF(OR(入力データ!$C$57="あり",H5>前提条件!$C$44),0,$B$41)) | I41: =IF(I$3="","",IF(OR(入力データ!$C$57="あり",I5>前提条件!$C$44),0,$B$41)) | J41: =IF(J$3="","",IF(OR(入力データ!$C$57="あり",J5>前提条件!$C$44),0,$B$41)) | ... CW41: =IF(CW$3="","",IF(OR(入力データ!$C$57="あり",CW5>前提条件!$C$44),0,$B$41))
A42: 老後期フラグ(補助) | B42: =IF(B$3="","",IF(AND(B4>=入力データ!$C$111,B5>=入力データ!$C$111),1,0)) | C42: =IF(C$3="","",IF(AND(C4>=入力データ!$C$111,C5>=入力データ!$C$111),1,0)) | D42: =IF(D$3="","",IF(AND(D4>=入力データ!$C$111,D5>=入力データ!$C$111),1,0)) | E42: =IF(E$3="","",IF(AND(E4>=入力データ!$C$111,E5>=入力データ!$C$111),1,0)) | F42: =IF(F$3="","",IF(AND(F4>=入力データ!$C$111,F5>=入力データ!$C$111),1,0)) | G42: =IF(G$3="","",IF(AND(G4>=入力データ!$C$111,G5>=入力データ!$C$111),1,0)) | H42: =IF(H$3="","",IF(AND(H4>=入力データ!$C$111,H5>=入力データ!$C$111),1,0)) | I42: =IF(I$3="","",IF(AND(I4>=入力データ!$C$111,I5>=入力データ!$C$111),1,0)) | ... CW42: =IF(CW$3="","",IF(AND(CW4>=入力データ!$C$111,CW5>=入力データ!$C$111),1,0))
A43: 老後不足額(補助) | B43: =IF(B$3="","",IF(B42=1,MAX(0,-B30),0)) | C43: =IF(C$3="","",IF(C42=1,MAX(0,-C30),0)) | D43: =IF(D$3="","",IF(D42=1,MAX(0,-D30),0)) | E43: =IF(E$3="","",IF(E42=1,MAX(0,-E30),0)) | F43: =IF(F$3="","",IF(F42=1,MAX(0,-F30),0)) | G43: =IF(G$3="","",IF(G42=1,MAX(0,-G30),0)) | H43: =IF(H$3="","",IF(H42=1,MAX(0,-H30),0)) | I43: =IF(I$3="","",IF(I42=1,MAX(0,-I30),0)) | ... CW43: =IF(CW$3="","",IF(CW42=1,MAX(0,-CW30),0))
A44: 保有資産合計（参考） | B44: =IF(B$3="","",B31+B32+B33) | C44: =IF(C$3="","",C31+C32+C33) | D44: =IF(D$3="","",D31+D32+D33) | E44: =IF(E$3="","",E31+E32+E33) | F44: =IF(F$3="","",F31+F32+F33) | G44: =IF(G$3="","",G31+G32+G33) | H44: =IF(H$3="","",H31+H32+H33) | I44: =IF(I$3="","",I31+I32+I33) | ... CW44: =IF(CW$3="","",CW31+CW32+CW33)
A45: 負債合計（参考） | B45: =IF(B$3="","",B34) | C45: =IF(C$3="","",C34) | D45: =IF(D$3="","",D34) | E45: =IF(E$3="","",E34) | F45: =IF(F$3="","",F34) | G45: =IF(G$3="","",G34) | H45: =IF(H$3="","",H34) | I45: =IF(I$3="","",I34) | ... CW45: =IF(CW$3="","",CW34)
A47: ※初版前提：奥様収入・奥様退職金・奥様年金を0、基本生活費圧縮、遺族年金・団信を反映。死亡保険金の受取額は未反映です。

Sheet CF表（ご主人様働けない時）
A1: ライフプラン表（ご主人様働けない時）
A2: 試算終了年 | B2: =MAX(IF(入力データ!$C$10<>"",YEAR(入力データ!$C$10)+100,0),IF(入力データ!$C$11<>"",YEAR(入力データ!$C$11)+100,0))
A3: 年 | B3: =IF(YEAR(入力データ!$C$5)>$B$2,"",YEAR(入力データ!$C$5)) | C3: =IF(B3="","",IF(B3+1>$B$2,"",B3+1)) | D3: =IF(C3="","",IF(C3+1>$B$2,"",C3+1)) | E3: =IF(D3="","",IF(D3+1>$B$2,"",D3+1)) | F3: =IF(E3="","",IF(E3+1>$B$2,"",E3+1)) | G3: =IF(F3="","",IF(F3+1>$B$2,"",F3+1)) | H3: =IF(G3="","",IF(G3+1>$B$2,"",G3+1)) | I3: =IF(H3="","",IF(H3+1>$B$2,"",H3+1)) | J3: =IF(I3="","",IF(I3+1>$B$2,"",I3+1)) | ... CW3: =IF(CV3="","",IF(CV3+1>$B$2,"",CV3+1))
A4: ご主人様年齢 | B4: =IF(B$3="","",IF(入力データ!$C$10="","",YEAR(DATE(B$3,12,31))-YEAR(入力データ!$C$10)-IF(DATE(B$3,12,31)<DATE(B$3,MONTH(入力データ!$C$10),DAY(入力データ!$C$10)),1,0))) | C4: =IF(C$3="","",IF(入力データ!$C$10="","",YEAR(DATE(C$3,12,31))-YEAR(入力データ!$C$10)-IF(DATE(C$3,12,31)<DATE(C$3,MONTH(入力データ!$C$10),DAY(入力データ!$C$10)),1,0))) | D4: =IF(D$3="","",IF(入力データ!$C$10="","",YEAR(DATE(D$3,12,31))-YEAR(入力データ!$C$10)-IF(DATE(D$3,12,31)<DATE(D$3,MONTH(入力データ!$C$10),DAY(入力データ!$C$10)),1,0))) | E4: =IF(E$3="","",IF(入力データ!$C$10="","",YEAR(DATE(E$3,12,31))-YEAR(入力データ!$C$10)-IF(DATE(E$3,12,31)<DATE(E$3,MONTH(入力データ!$C$10),DAY(入力データ!$C$10)),1,0))) | F4: =IF(F$3="","",IF(入力データ!$C$10="","",YEAR(DATE(F$3,12,31))-YEAR(入力データ!$C$10)-IF(DATE(F$3,12,31)<DATE(F$3,MONTH(入力データ!$C$10),DAY(入力データ!$C$10)),1,0))) | G4: =IF(G$3="","",IF(入力データ!$C$10="","",YEAR(DATE(G$3,12,31))-YEAR(入力データ!$C$10)-IF(DATE(G$3,12,31)<DATE(G$3,MONTH(入力データ!$C$10),DAY(入力データ!$C$10)),1,0))) | H4: =IF(H$3="","",IF(入力データ!$C$10="","",YEAR(DATE(H$3,12,31))-YEAR(入力データ!$C$10)-IF(DATE(H$3,12,31)<DATE(H$3,MONTH(入力データ!$C$10),DAY(入力データ!$C$10)),1,0))) | I4: =IF(I$3="","",IF(入力データ!$C$10="","",YEAR(DATE(I$3,12,31))-YEAR(入力データ!$C$10)-IF(DATE(I$3,12,31)<DATE(I$3,MONTH(入力データ!$C$10),DAY(入力データ!$C$10)),1,0))) | ... CW4: =IF(CW$3="","",IF(入力データ!$C$10="","",YEAR(DATE(CW$3,12,31))-YEAR(入力データ!$C$10)-IF(DATE(CW$3,12,31)<DATE(CW$3,MONTH(入力データ!$C$10),DAY(入力データ!$C$10)),1,0)))
A5: 奥様年齢 | B5: =IF(B$3="","",IF(入力データ!$C$11="","",YEAR(DATE(B$3,12,31))-YEAR(入力データ!$C$11)-IF(DATE(B$3,12,31)<DATE(B$3,MONTH(入力データ!$C$11),DAY(入力データ!$C$11)),1,0))) | C5: =IF(C$3="","",IF(入力データ!$C$11="","",YEAR(DATE(C$3,12,31))-YEAR(入力データ!$C$11)-IF(DATE(C$3,12,31)<DATE(C$3,MONTH(入力データ!$C$11),DAY(入力データ!$C$11)),1,0))) | D5: =IF(D$3="","",IF(入力データ!$C$11="","",YEAR(DATE(D$3,12,31))-YEAR(入力データ!$C$11)-IF(DATE(D$3,12,31)<DATE(D$3,MONTH(入力データ!$C$11),DAY(入力データ!$C$11)),1,0))) | E5: =IF(E$3="","",IF(入力データ!$C$11="","",YEAR(DATE(E$3,12,31))-YEAR(入力データ!$C$11)-IF(DATE(E$3,12,31)<DATE(E$3,MONTH(入力データ!$C$11),DAY(入力データ!$C$11)),1,0))) | F5: =IF(F$3="","",IF(入力データ!$C$11="","",YEAR(DATE(F$3,12,31))-YEAR(入力データ!$C$11)-IF(DATE(F$3,12,31)<DATE(F$3,MONTH(入力データ!$C$11),DAY(入力データ!$C$11)),1,0))) | G5: =IF(G$3="","",IF(入力データ!$C$11="","",YEAR(DATE(G$3,12,31))-YEAR(入力データ!$C$11)-IF(DATE(G$3,12,31)<DATE(G$3,MONTH(入力データ!$C$11),DAY(入力データ!$C$11)),1,0))) | H5: =IF(H$3="","",IF(入力データ!$C$11="","",YEAR(DATE(H$3,12,31))-YEAR(入力データ!$C$11)-IF(DATE(H$3,12,31)<DATE(H$3,MONTH(入力データ!$C$11),DAY(入力データ!$C$11)),1,0))) | I5: =IF(I$3="","",IF(入力データ!$C$11="","",YEAR(DATE(I$3,12,31))-YEAR(入力データ!$C$11)-IF(DATE(I$3,12,31)<DATE(I$3,MONTH(入力データ!$C$11),DAY(入力データ!$C$11)),1,0))) | ... CW5: =IF(CW$3="","",IF(入力データ!$C$11="","",YEAR(DATE(CW$3,12,31))-YEAR(入力データ!$C$11)-IF(DATE(CW$3,12,31)<DATE(CW$3,MONTH(入力データ!$C$11),DAY(入力データ!$C$11)),1,0)))
A6: 子1年齢 | B6: =IF(B$3="","",IF(入力データ!$C$19="","",YEAR(DATE(B$3,12,31))-YEAR(入力データ!$C$19)-IF(DATE(B$3,12,31)<DATE(B$3,MONTH(入力データ!$C$19),DAY(入力データ!$C$19)),1,0))) | C6: =IF(C$3="","",IF(入力データ!$C$19="","",YEAR(DATE(C$3,12,31))-YEAR(入力データ!$C$19)-IF(DATE(C$3,12,31)<DATE(C$3,MONTH(入力データ!$C$19),DAY(入力データ!$C$19)),1,0))) | D6: =IF(D$3="","",IF(入力データ!$C$19="","",YEAR(DATE(D$3,12,31))-YEAR(入力データ!$C$19)-IF(DATE(D$3,12,31)<DATE(D$3,MONTH(入力データ!$C$19),DAY(入力データ!$C$19)),1,0))) | E6: =IF(E$3="","",IF(入力データ!$C$19="","",YEAR(DATE(E$3,12,31))-YEAR(入力データ!$C$19)-IF(DATE(E$3,12,31)<DATE(E$3,MONTH(入力データ!$C$19),DAY(入力データ!$C$19)),1,0))) | F6: =IF(F$3="","",IF(入力データ!$C$19="","",YEAR(DATE(F$3,12,31))-YEAR(入力データ!$C$19)-IF(DATE(F$3,12,31)<DATE(F$3,MONTH(入力データ!$C$19),DAY(入力データ!$C$19)),1,0))) | G6: =IF(G$3="","",IF(入力データ!$C$19="","",YEAR(DATE(G$3,12,31))-YEAR(入力データ!$C$19)-IF(DATE(G$3,12,31)<DATE(G$3,MONTH(入力データ!$C$19),DAY(入力データ!$C$19)),1,0))) | H6: =IF(H$3="","",IF(入力データ!$C$19="","",YEAR(DATE(H$3,12,31))-YEAR(入力データ!$C$19)-IF(DATE(H$3,12,31)<DATE(H$3,MONTH(入力データ!$C$19),DAY(入力データ!$C$19)),1,0))) | I6: =IF(I$3="","",IF(入力データ!$C$19="","",YEAR(DATE(I$3,12,31))-YEAR(入力データ!$C$19)-IF(DATE(I$3,12,31)<DATE(I$3,MONTH(入力データ!$C$19),DAY(入力データ!$C$19)),1,0))) | ... CW6: =IF(CW$3="","",IF(入力データ!$C$19="","",YEAR(DATE(CW$3,12,31))-YEAR(入力データ!$C$19)-IF(DATE(CW$3,12,31)<DATE(CW$3,MONTH(入力データ!$C$19),DAY(入力データ!$C$19)),1,0)))
A7: 子2年齢 | B7: =IF(B$3="","",IF(入力データ!$C$21="","",YEAR(DATE(B$3,12,31))-YEAR(入力データ!$C$21)-IF(DATE(B$3,12,31)<DATE(B$3,MONTH(入力データ!$C$21),DAY(入力データ!$C$21)),1,0))) | C7: =IF(C$3="","",IF(入力データ!$C$21="","",YEAR(DATE(C$3,12,31))-YEAR(入力データ!$C$21)-IF(DATE(C$3,12,31)<DATE(C$3,MONTH(入力データ!$C$21),DAY(入力データ!$C$21)),1,0))) | D7: =IF(D$3="","",IF(入力データ!$C$21="","",YEAR(DATE(D$3,12,31))-YEAR(入力データ!$C$21)-IF(DATE(D$3,12,31)<DATE(D$3,MONTH(入力データ!$C$21),DAY(入力データ!$C$21)),1,0))) | E7: =IF(E$3="","",IF(入力データ!$C$21="","",YEAR(DATE(E$3,12,31))-YEAR(入力データ!$C$21)-IF(DATE(E$3,12,31)<DATE(E$3,MONTH(入力データ!$C$21),DAY(入力データ!$C$21)),1,0))) | F7: =IF(F$3="","",IF(入力データ!$C$21="","",YEAR(DATE(F$3,12,31))-YEAR(入力データ!$C$21)-IF(DATE(F$3,12,31)<DATE(F$3,MONTH(入力データ!$C$21),DAY(入力データ!$C$21)),1,0))) | G7: =IF(G$3="","",IF(入力データ!$C$21="","",YEAR(DATE(G$3,12,31))-YEAR(入力データ!$C$21)-IF(DATE(G$3,12,31)<DATE(G$3,MONTH(入力データ!$C$21),DAY(入力データ!$C$21)),1,0))) | H7: =IF(H$3="","",IF(入力データ!$C$21="","",YEAR(DATE(H$3,12,31))-YEAR(入力データ!$C$21)-IF(DATE(H$3,12,31)<DATE(H$3,MONTH(入力データ!$C$21),DAY(入力データ!$C$21)),1,0))) | I7: =IF(I$3="","",IF(入力データ!$C$21="","",YEAR(DATE(I$3,12,31))-YEAR(入力データ!$C$21)-IF(DATE(I$3,12,31)<DATE(I$3,MONTH(入力データ!$C$21),DAY(入力データ!$C$21)),1,0))) | ... CW7: =IF(CW$3="","",IF(入力データ!$C$21="","",YEAR(DATE(CW$3,12,31))-YEAR(入力データ!$C$21)-IF(DATE(CW$3,12,31)<DATE(CW$3,MONTH(入力データ!$C$21),DAY(入力データ!$C$21)),1,0)))
A8: 子3年齢 | B8: =IF(B$3="","",IF(情報入力!$C$23="","",YEAR(DATE(B$3,12,31))-YEAR(情報入力!$C$23)-IF(DATE(B$3,12,31)<DATE(B$3,MONTH(情報入力!$C$23),DAY(情報入力!$C$23)),1,0))) | C8: =IF(C$3="","",IF(情報入力!$C$23="","",YEAR(DATE(C$3,12,31))-YEAR(情報入力!$C$23)-IF(DATE(C$3,12,31)<DATE(C$3,MONTH(情報入力!$C$23),DAY(情報入力!$C$23)),1,0))) | D8: =IF(D$3="","",IF(情報入力!$C$23="","",YEAR(DATE(D$3,12,31))-YEAR(情報入力!$C$23)-IF(DATE(D$3,12,31)<DATE(D$3,MONTH(情報入力!$C$23),DAY(情報入力!$C$23)),1,0))) | E8: =IF(E$3="","",IF(情報入力!$C$23="","",YEAR(DATE(E$3,12,31))-YEAR(情報入力!$C$23)-IF(DATE(E$3,12,31)<DATE(E$3,MONTH(情報入力!$C$23),DAY(情報入力!$C$23)),1,0))) | F8: =IF(F$3="","",IF(情報入力!$C$23="","",YEAR(DATE(F$3,12,31))-YEAR(情報入力!$C$23)-IF(DATE(F$3,12,31)<DATE(F$3,MONTH(情報入力!$C$23),DAY(情報入力!$C$23)),1,0))) | G8: =IF(G$3="","",IF(情報入力!$C$23="","",YEAR(DATE(G$3,12,31))-YEAR(情報入力!$C$23)-IF(DATE(G$3,12,31)<DATE(G$3,MONTH(情報入力!$C$23),DAY(情報入力!$C$23)),1,0))) | H8: =IF(H$3="","",IF(情報入力!$C$23="","",YEAR(DATE(H$3,12,31))-YEAR(情報入力!$C$23)-IF(DATE(H$3,12,31)<DATE(H$3,MONTH(情報入力!$C$23),DAY(情報入力!$C$23)),1,0))) | I8: =IF(I$3="","",IF(情報入力!$C$23="","",YEAR(DATE(I$3,12,31))-YEAR(情報入力!$C$23)-IF(DATE(I$3,12,31)<DATE(I$3,MONTH(情報入力!$C$23),DAY(情報入力!$C$23)),1,0))) | ... CW8: =IF(CW$3="","",IF(情報入力!$C$23="","",YEAR(DATE(CW$3,12,31))-YEAR(情報入力!$C$23)-IF(DATE(CW$3,12,31)<DATE(CW$3,MONTH(情報入力!$C$23),DAY(情報入力!$C$23)),1,0)))
A9: 家族年齢
A10: ご主人様収入 | B10: =IF(B$3="","",0) | C10: =IF(C$3="","",0) | D10: =IF(D$3="","",0) | E10: =IF(E$3="","",0) | F10: =IF(F$3="","",0) | G10: =IF(G$3="","",0) | H10: =IF(H$3="","",0) | I10: =IF(I$3="","",0) | ... CW10: =IF(CW$3="","",0)
